Workbook

Sheet Pivot Master1
B3: INVOICE | Q3: PROVISION
B4: BU | C4: TOTAL | Q4: BU | R4: TOTAL
B6: Invoice Net Amt (CLP) | I6: Customer | Q6: Provision Net Amt (CLP) | X6: Customer
B7: Year | C7: Invoice Received | D7: Impact Month | E7: Invoice Registered | F7: Invoice Status | G7: Commission Type | H7: Doc Type | I7: FALABELLA (DIRECT) | J7: PARIS (FULLKOM) | K7: WALMART (FULLKOM) | L7: RIPLEY (FULLKOM) | M7: MERCADO PAGO | N7: TRANSBANK | O7: OMS (V SOPTEC) | Q7: Year | R7: Invoice Received | S7: Impact Month | T7: Invoice Registered | U7: Invoice Status | V7: Commission Type | W7: Doc Type | X7: FALABELLA (DIRECT) | Y7: PARIS (FULLKOM) | Z7: WALMART (FULLKOM) | AA7: RIPLEY (FULLKOM) | AB7: MERCADO PAGO | AC7: TRANSBANK | AD7: OMS (V SOPTEC)
B8: 2026 | C8: MAY | D8: JUL (Provision) | E8: JUL | F8: AP Completed | G8: Commission (2da Quincena) | H8: Invoice | J8: 11257458 | K8: 7477508 | L8: 990593 | Q8: 2026 | R8: MAY | S8: JUL (Provision) | T8: JUL | U8: AP Completed | V8: Commission (2da Quincena) | W8: Invoice
B9: 2026 | C9: MAY | D9: JUL (Provision) | E9: AUG | F9: AP Completed | G9: Monthly Commission | H9: Invoice | N9: 4393086 | Q9: 2026 | R9: MAY | S9: JUL (Provision) | T9: AUG | U9: AP Completed | V9: Monthly Commission | W9: Invoice
B10: 2026 | C10: MAY | D10: JUL (Provision) | E10: Rejected | F10: Rejected | G10: Monthly Commission | H10: Invoice | M10: 5049775 | Q10: 2026 | R10: MAY | S10: JUL (Provision) | T10: Rejected | U10: Rejected | V10: Monthly Commission | W10: Invoice
B11: 2026 | C11: MAY Total | J11: 11257458 | K11: 7477508 | L11: 990593 | M11: 5049775 | N11: 4393086 | Q11: 2026 | R11: MAY Total
B12: 2026 | C12: JUN | D12: JUL (Provision) | E12: JUL | F12: AP Completed | G12: Commission (1era Quincena) | H12: Invoice | J12: 41580654 | K12: 29182345 | L12: 6642066 | Q12: 2026 | R12: JUN | S12: JUL (Provision) | T12: JUL | U12: AP Completed | V12: Commission (1era Quincena) | W12: Invoice | Y12: 31782550 | Z12: 27262067 | AA12: 5811311.5
B13: 2026 | C13: JUN | D13: JUL (Provision) | E13: JUL | F13: AP Completed | G13: Commission (2da Quincena) | H13: Invoice | J13: 13569540 | K13: 6754211 | L13: 2368348 | Q13: 2026 | R13: JUN | S13: JUL (Provision) | T13: JUL | U13: AP Completed | V13: Commission (2da Quincena) | W13: Invoice | Y13: 14193628 | Z13: 6861185.2 | AA13: 2960848
B14: 2026 | C14: JUN | D14: JUL (Provision) | E14: JUL | F14: AP Completed | G14: Commission (In transit) | H14: Invoice | K14: 0 | L14: 0 | Q14: 2026 | R14: JUN | S14: JUL (Provision) | T14: JUL | U14: AP Completed | V14: Commission (In transit) | W14: Invoice | Z14: 8213814.3 | AA14: 1752661.4
B15: 2026 | C15: JUN | D15: JUL (Provision) | E15: JUL | F15: AP Completed | G15: Logistic Cost | H15: Invoice | J15: 35307369 | Q15: 2026 | R15: JUN | S15: JUL (Provision) | T15: JUL | U15: AP Completed | V15: Logistic Cost | W15: Invoice
B16: 2026 | C16: JUN | D16: JUL (Provision) | E16: AUG | F16: AP Completed | G16: Monthly Commission | H16: Invoice | I16: 2.5181058e+08 | M16: 8819906 | N16: 8153422 | Q16: 2026 | R16: JUN | S16: JUL (Provision) | T16: AUG | U16: AP Completed | V16: Monthly Commission | W16: Invoice | AB16: 8963409.4 | AC16: 15914399
B17: 2026 | C17: JUN | D17: JUL (Provision) | E17: AUG | F17: AP Completed | G17: Monthly Commission | H17: Credit Note | I17: -99583029 | Q17: 2026 | R17: JUN | S17: JUL (Provision) | T17: AUG | U17: AP Completed | V17: Monthly Commission | W17: Credit Note
B18: 2026 | C18: JUN Total | I18: 1.5222755e+08 | J18: 90457563 | K18: 35936556 | L18: 9010414 | M18: 8819906 | N18: 8153422 | Q18: 2026 | R18: JUN Total | Y18: 45976178 | Z18: 42337067 | AA18: 10524821 | AB18: 8963409.4 | AC18: 15914399
B19: 2026 | C19: JUL | D19: JUL (Provision) | E19: AUG | F19: AP Completed | G19: Monthly Commission | H19: Invoice | I19: 141164774 | Q19: 2026 | R19: JUL | S19: JUL (Provision) | T19: AUG | U19: AP Completed | V19: Monthly Commission | W19: Invoice | X19: 141164774
B20: 2026 | C20: JUL | D20: JUL (Provision) | E20: AUG | F20: AP Completed | G20: Monthly Commission | H20: Credit Note | I20: -59216876 | Q20: 2026 | R20: JUL | S20: JUL (Provision) | T20: AUG | U20: AP Completed | V20: Monthly Commission | W20: Credit Note | X20: -59216876
B21: 2026 | C21: JUL | D21: JUL (Provision) | E21: Pending | F21: Pending | G21: Monthly Commission | H21: Invoice | M21: 5778926 | N21: 6122740.6 | Q21: 2026 | R21: JUL | S21: JUL (Provision) | T21: Pending | U21: Pending | V21: Monthly Commission | W21: Invoice
B22: 2026 | C22: JUL | D22: JUL (Provision) | E22: Pending | F22: Pending | G22: Commission (1era Quincena) | H22: Invoice | J22: 17265549 | K22: 9202504.1 | L22: 2735581.8 | Q22: 2026 | R22: JUL | S22: JUL (Provision) | T22: Pending | U22: Pending | V22: Commission (1era Quincena) | W22: Invoice
B23: 2026 | C23: JUL | D23: JUL (Provision) | E23: Pending | F23: Pending | G23: Commission (2da Quincena) | H23: Invoice | J23: 16791454 | K23: 9167913.9 | L23: 6558778.3 | Q23: 2026 | R23: JUL | S23: JUL (Provision) | T23: Pending | U23: Pending | V23: Commission (2da Quincena) | W23: Invoice
B24: 2026 | C24: JUL | D24: JUL (Provision) | E24: Pending | F24: Pending | G24: Logistic Cost | H24: Invoice | J24: 34222222 | Q24: 2026 | R24: JUL | S24: JUL (Provision) | T24: Pending | U24: Pending | V24: Logistic Cost | W24: Invoice
B25: 2026 | C25: JUL Total | I25: 81947898 | J25: 68279225 | K25: 18370418 | L25: 9294360.1 | M25: 5778926 | N25: 6122740.6 | Q25: 2026 | R25: JUL Total | X25: 81947898
B26: 2026 | C26: AUG | D26: AUG (Provision) | E26: Pending | F26: Pending | G26: Monthly Commission | H26: Invoice | I26: 2.0333005e+08 | M26: 7255543 | N26: 0 | O26: 2378590 | Q26: 2026 | R26: AUG | S26: AUG (Provision) | T26: Pending | U26: Pending | V26: Monthly Commission | W26: Invoice | AB26: 0 | AC26: 7261730.8 | AD26: 0
B27: 2026 | C27: AUG | D27: AUG (Provision) | E27: Pending | F27: Pending | G27: Monthly Commission | H27: Credit Note | I27: -82305000 | Q27: 2026 | R27: AUG | S27: AUG (Provision) | T27: Pending | U27: Pending | V27: Monthly Commission | W27: Credit Note
B28: 2026 | C28: AUG | D28: AUG (Provision) | E28: Pending | F28: Pending | G28: Commission (1era Quincena) | H28: Invoice | J28: 0 | K28: 0 | L28: 0 | Q28: 2026 | R28: AUG | S28: AUG (Provision) | T28: Pending | U28: Pending | V28: Commission (1era Quincena) | W28: Invoice | Y28: 11104183 | Z28: 10173825 | AA28: 7249876.2
B29: 2026 | C29: AUG | D29: AUG (Provision) | E29: Pending | F29: Pending | G29: Commission (2da Quincena) | H29: Invoice | J29: 0 | K29: 0 | L29: 0 | Q29: 2026 | R29: AUG | S29: AUG (Provision) | T29: Pending | U29: Pending | V29: Commission (2da Quincena) | W29: Invoice | Y29: 14355291 | Z29: 5460548.2 | AA29: 4291111
B30: 2026 | C30: AUG Total | I30: 1.2102505e+08 | J30: 0 | K30: 0 | L30: 0 | M30: 7255543 | N30: 0 | O30: 2378590 | Q30: 2026 | R30: AUG Total | Y30: 25459474 | Z30: 15634373 | AA30: 11540987 | AB30: 0 | AC30: 7261730.8 | AD30: 0
B31: Grand Total | I31: 3.552005e+08 | J31: 1.6999425e+08 | K31: 61784482 | L31: 19295367 | M31: 26904150 | N31: 18669249 | O31: 2378590 | Q31: Grand Total | X31: 81947898 | Y31: 71435651 | Z31: 57971440 | AA31: 22065808 | AB31: 8963409.4 | AC31: 23176130 | AD31: 0

Sheet Master 1_BU
D2: Incluir al final toda la info de Map2
B4: Year | C4: Cut Date | D4: Invoice Received | E4: Impact Month | F4: Invoice Registered | G4: Invoice Date | H4: Invoice Number | I4: Customer | J4: OBS/3P | K4: BU | L4: Division | M4: Invoice Net Amt (CLP) | N4: VAT (CLP) | O4: Total Amt (CLP) | P4: Invoice Net Amt (USD) | Q4: VAT (USD) | R4: Total Amt (USD) | S4: FX Rate | T4: Commission Type | U4: Provision | V4: Doc Type | W4: Variable /Fixed | X4: Invoice Status | Y4: BU | Z4: Provision Net Amt (CLP) | AA4: Provision VAT (CLP) | AB4: Provision Amt (CLP) | AC4: Provision Net Amt (USD) | AD4: Provision VAT (USD) | AE4: Provision Amt (USD) | AF4: Invoice URL
B5: 2026 | C5: Jun21 to Jul20 | D5: JUL | E5: JUL (Provision) | F5: AUG | G5: 46230 | H5: 478270 | I5: FALABELLA (DIRECT) | J5: =IFERROR(VLOOKUP(I5,Map!$F$18:$G$56,2,0),"Add in Map") -> 3P | K5: =VLOOKUP(L5,Map!$C$18:$D$29,2,0) -> CNT | L5: Refrigeration | M5: 24645503 | N5: =IF(L5="TOTAL",(M5*0.19),0) -> 0 | O5: =M5*1.19 -> 29328148 | P5: =M5/S5 -> 26672.622 | Q5: =IF(L5="TOTAL",(P5*0.19),0) -> 0 | R5: =P5*1.19 -> 31740.42 | S5: =INDEX(FX!$D$3:$O$19,MATCH(B5,FX!$B$3:$B$32,0),MATCH(D5,FX!$D$2:$O$2,0)) -> 924 | T5: Monthly Commission | U5: Provision (Based on External Report) | V5: Invoice | W5: =VLOOKUP(I5,Map!$F$18:$H$51,3,0) -> Variable | X5: AP Completed | Y5: =VLOOKUP(L5,Map!$C$18:$D$29,2,0) -> CNT | Z5: 24645503 | AA5: =IF(Y5="TOTAL",(Z5*0.19),0) -> 0 | AB5: =Z5*1.19 -> 29328148 | AC5: =Z5/S5 -> 26672.622 | AD5: =IF(Y5="TOTAL",(AC5*0.19),0) -> 0 | AE5: =AC5*1.19 -> 31740.42
B6: 2026 | C6: Jun21 to Jul20 | D6: JUL | E6: JUL (Provision) | F6: AUG | G6: 46230 | H6: 478270 | I6: FALABELLA (DIRECT) | J6: =IFERROR(VLOOKUP(I6,Map!$F$18:$G$56,2,0),"Add in Map") -> 3P | K6: =VLOOKUP(L6,Map!$C$18:$D$29,2,0) -> CVT | L6: Cooking | M6: 291662.76 | N6: =IF(L6="TOTAL",(M6*0.19),0) -> 0 | O6: =M6*1.19 -> 347078.68 | P6: =M6/S6 -> 315.65233 | Q6: =IF(L6="TOTAL",(P6*0.19),0) -> 0 | R6: =P6*1.19 -> 375.62628 | S6: =INDEX(FX!$D$3:$O$19,MATCH(B6,FX!$B$3:$B$32,0),MATCH(D6,FX!$D$2:$O$2,0)) -> 924 | T6: Monthly Commission | U6: Provision (Based on External Report) | V6: Invoice | W6: =VLOOKUP(I6,Map!$F$18:$H$51,3,0) -> Variable | X6: AP Completed | Y6: =VLOOKUP(L6,Map!$C$18:$D$29,2,0) -> CVT | Z6: 291662.76 | AA6: =IF(Y6="TOTAL",(Z6*0.19),0) -> 0 | AB6: =Z6*1.19 -> 347078.68 | AC6: =Z6/S6 -> 315.65233 | AD6: =IF(Y6="TOTAL",(AC6*0.19),0) -> 0 | AE6: =AC6*1.19 -> 375.62628
B7: 2026 | C7: Jun21 to Jul20 | D7: JUL | E7: JUL (Provision) | F7: AUG | G7: 46230 | H7: 478270 | I7: FALABELLA (DIRECT) | J7: =IFERROR(VLOOKUP(I7,Map!$F$18:$G$56,2,0),"Add in Map") -> 3P | K7: =VLOOKUP(L7,Map!$C$18:$D$29,2,0) -> CDT | L7: Dishwasher | M7: 1020819.6 | N7: =IF(L7="TOTAL",(M7*0.19),0) -> 0 | O7: =M7*1.19 -> 1214775.4 | P7: =M7/S7 -> 1104.7832 | Q7: =IF(L7="TOTAL",(P7*0.19),0) -> 0 | R7: =P7*1.19 -> 1314.692 | S7: =INDEX(FX!$D$3:$O$19,MATCH(B7,FX!$B$3:$B$32,0),MATCH(D7,FX!$D$2:$O$2,0)) -> 924 | T7: Monthly Commission | U7: Provision (Based on External Report) | V7: Invoice | W7: =VLOOKUP(I7,Map!$F$18:$H$51,3,0) -> Variable | X7: AP Completed | Y7: =VLOOKUP(L7,Map!$C$18:$D$29,2,0) -> CDT | Z7: 1020819.6 | AA7: =IF(Y7="TOTAL",(Z7*0.19),0) -> 0 | AB7: =Z7*1.19 -> 1214775.4 | AC7: =Z7/S7 -> 1104.7832 | AD7: =IF(Y7="TOTAL",(AC7*0.19),0) -> 0 | AE7: =AC7*1.19 -> 1314.692
B8: 2026 | C8: Jun21 to Jul20 | D8: JUL | E8: JUL (Provision) | F8: AUG | G8: 46230 | H8: 478270 | I8: FALABELLA (DIRECT) | J8: =IFERROR(VLOOKUP(I8,Map!$F$18:$G$56,2,0),"Add in Map") -> 3P | K8: =VLOOKUP(L8,Map!$C$18:$D$29,2,0) -> DFT | L8: WM | M8: 73207352 | N8: =IF(L8="TOTAL",(M8*0.19),0) -> 0 | O8: =M8*1.19 -> 87116749 | P8: =M8/S8 -> 79228.736 | Q8: =IF(L8="TOTAL",(P8*0.19),0) -> 0 | R8: =P8*1.19 -> 94282.196 | S8: =INDEX(FX!$D$3:$O$19,MATCH(B8,FX!$B$3:$B$32,0),MATCH(D8,FX!$D$2:$O$2,0)) -> 924 | T8: Monthly Commission | U8: Provision (Based on External Report) | V8: Invoice | W8: =VLOOKUP(I8,Map!$F$18:$H$51,3,0) -> Variable | X8: AP Completed | Y8: =VLOOKUP(L8,Map!$C$18:$D$29,2,0) -> DFT | Z8: 73207352 | AA8: =IF(Y8="TOTAL",(Z8*0.19),0) -> 0 | AB8: =Z8*1.19 -> 87116749 | AC8: =Z8/S8 -> 79228.736 | AD8: =IF(Y8="TOTAL",(AC8*0.19),0) -> 0 | AE8: =AC8*1.19 -> 94282.196
B9: 2026 | C9: Jun21 to Jul20 | D9: JUL | E9: JUL (Provision) | F9: AUG | G9: 46230 | H9: 478270 | I9: FALABELLA (DIRECT) | J9: =IFERROR(VLOOKUP(I9,Map!$F$18:$G$56,2,0),"Add in Map") -> 3P | K9: =VLOOKUP(L9,Map!$C$18:$D$29,2,0) -> DVT | L9: VCC | M9: 145831.38 | N9: =IF(L9="TOTAL",(M9*0.19),0) -> 0 | O9: =M9*1.19 -> 173539.34 | P9: =M9/S9 -> 157.82617 | Q9: =IF(L9="TOTAL",(P9*0.19),0) -> 0 | R9: =P9*1.19 -> 187.81314 | S9: =INDEX(FX!$D$3:$O$19,MATCH(B9,FX!$B$3:$B$32,0),MATCH(D9,FX!$D$2:$O$2,0)) -> 924 | T9: Monthly Commission | U9: Provision (Based on External Report) | V9: Invoice | W9: =VLOOKUP(I9,Map!$F$18:$H$51,3,0) -> Variable | X9: AP Completed | Y9: =VLOOKUP(L9,Map!$C$18:$D$29,2,0) -> DVT | Z9: 145831.38 | AA9: =IF(Y9="TOTAL",(Z9*0.19),0) -> 0 | AB9: =Z9*1.19 -> 173539.34 | AC9: =Z9/S9 -> 157.82617 | AD9: =IF(Y9="TOTAL",(AC9*0.19),0) -> 0 | AE9: =AC9*1.19 -> 187.81314
B10: 2026 | C10: Jun21 to Jul20 | D10: JUL | E10: JUL (Provision) | F10: AUG | G10: 46230 | H10: 478270 | I10: FALABELLA (DIRECT) | J10: =IFERROR(VLOOKUP(I10,Map!$F$18:$G$56,2,0),"Add in Map") -> 3P | K10: =VLOOKUP(L10,Map!$C$18:$D$29,2,0) -> GLT | L10: Television | M10: 34707868 | N10: =IF(L10="TOTAL",(M10*0.19),0) -> 0 | O10: =M10*1.19 -> 41302363 | P10: =M10/S10 -> 37562.628 | Q10: =IF(L10="TOTAL",(P10*0.19),0) -> 0 | R10: =P10*1.19 -> 44699.527 | S10: =INDEX(FX!$D$3:$O$19,MATCH(B10,FX!$B$3:$B$32,0),MATCH(D10,FX!$D$2:$O$2,0)) -> 924 | T10: Monthly Commission | U10: Provision (Based on External Report) | V10: Invoice | W10: =VLOOKUP(I10,Map!$F$18:$H$51,3,0) -> Variable | X10: AP Completed | Y10: =VLOOKUP(L10,Map!$C$18:$D$29,2,0) -> GLT | Z10: 34707868 | AA10: =IF(Y10="TOTAL",(Z10*0.19),0) -> 0 | AB10: =Z10*1.19 -> 41302363 | AC10: =Z10/S10 -> 37562.628 | AD10: =IF(Y10="TOTAL",(AC10*0.19),0) -> 0 | AE10: =AC10*1.19 -> 44699.527
B11: 2026 | C11: Jun21 to Jul20 | D11: JUL | E11: JUL (Provision) | F11: AUG | G11: 46230 | H11: 478270 | I11: FALABELLA (DIRECT) | J11: =IFERROR(VLOOKUP(I11,Map!$F$18:$G$56,2,0),"Add in Map") -> 3P | K11: =VLOOKUP(L11,Map!$C$18:$D$29,2,0) -> PNT | L11: Audio | M11: 2187470.7 | N11: =IF(L11="TOTAL",(M11*0.19),0) -> 0 | O11: =M11*1.19 -> 2603090.1 | P11: =M11/S11 -> 2367.3925 | Q11: =IF(L11="TOTAL",(P11*0.19),0) -> 0 | R11: =P11*1.19 -> 2817.1971 | S11: =INDEX(FX!$D$3:$O$19,MATCH(B11,FX!$B$3:$B$32,0),MATCH(D11,FX!$D$2:$O$2,0)) -> 924 | T11: Monthly Commission | U11: Provision (Based on External Report) | V11: Invoice | W11: =VLOOKUP(I11,Map!$F$18:$H$51,3,0) -> Variable | X11: AP Completed | Y11: =VLOOKUP(L11,Map!$C$18:$D$29,2,0) -> PNT | Z11: 2187470.7 | AA11: =IF(Y11="TOTAL",(Z11*0.19),0) -> 0 | AB11: =Z11*1.19 -> 2603090.1 | AC11: =Z11/S11 -> 2367.3925 | AD11: =IF(Y11="TOTAL",(AC11*0.19),0) -> 0 | AE11: =AC11*1.19 -> 2817.1971
B12: 2026 | C12: Jun21 to Jul20 | D12: JUL | E12: JUL (Provision) | F12: AUG | G12: 46230 | H12: 478270 | I12: FALABELLA (DIRECT) | J12: =IFERROR(VLOOKUP(I12,Map!$F$18:$G$56,2,0),"Add in Map") -> 3P | K12: =VLOOKUP(L12,Map!$C$18:$D$29,2,0) -> GTT | L12: Monitor | M12: 3645784.5 | N12: =IF(L12="TOTAL",(M12*0.19),0) -> 0 | O12: =M12*1.19 -> 4338483.5 | P12: =M12/S12 -> 3945.6542 | Q12: =IF(L12="TOTAL",(P12*0.19),0) -> 0 | R12: =P12*1.19 -> 4695.3285 | S12: =INDEX(FX!$D$3:$O$19,MATCH(B12,FX!$B$3:$B$32,0),MATCH(D12,FX!$D$2:$O$2,0)) -> 924 | T12: Monthly Commission | U12: Provision (Based on External Report) | V12: Invoice | W12: =VLOOKUP(I12,Map!$F$18:$H$51,3,0) -> Variable | X12: AP Completed | Y12: =VLOOKUP(L12,Map!$C$18:$D$29,2,0) -> GTT | Z12: 3645784.5 | AA12: =IF(Y12="TOTAL",(Z12*0.19),0) -> 0 | AB12: =Z12*1.19 -> 4338483.5 | AC12: =Z12/S12 -> 3945.6542 | AD12: =IF(Y12="TOTAL",(AC12*0.19),0) -> 0 | AE12: =AC12*1.19 -> 4695.3285
B13: 2026 | C13: Jun21 to Jul20 | D13: JUL | E13: JUL (Provision) | F13: AUG | G13: 46230 | H13: 478270 | I13: FALABELLA (DIRECT) | J13: =IFERROR(VLOOKUP(I13,Map!$F$18:$G$56,2,0),"Add in Map") -> 3P | K13: =VLOOKUP(L13,Map!$C$18:$D$29,2,0) -> DGT | L13: RAC | M13: 1020819.6 | N13: =IF(L13="TOTAL",(M13*0.19),0) -> 0 | O13: =M13*1.19 -> 1214775.4 | P13: =M13/S13 -> 1104.7832 | Q13: =IF(L13="TOTAL",(P13*0.19),0) -> 0 | R13: =P13*1.19 -> 1314.692 | S13: =INDEX(FX!$D$3:$O$19,MATCH(B13,FX!$B$3:$B$32,0),MATCH(D13,FX!$D$2:$O$2,0)) -> 924 | T13: Monthly Commission | U13: Provision (Based on External Report) | V13: Invoice | W13: =VLOOKUP(I13,Map!$F$18:$H$51,3,0) -> Variable | X13: AP Completed | Y13: =VLOOKUP(L13,Map!$C$18:$D$29,2,0) -> DGT | Z13: 1020819.6 | AA13: =IF(Y13="TOTAL",(Z13*0.19),0) -> 0 | AB13: =Z13*1.19 -> 1214775.4 | AC13: =Z13/S13 -> 1104.7832 | AD13: =IF(Y13="TOTAL",(AC13*0.19),0) -> 0 | AE13: =AC13*1.19 -> 1314.692
B14: 2026 | C14: Jun21 to Jul20 | D14: JUL | E14: JUL (Provision) | F14: AUG | G14: 46230 | H14: 478270 | I14: FALABELLA (DIRECT) | J14: =IFERROR(VLOOKUP(I14,Map!$F$18:$G$56,2,0),"Add in Map") -> 3P | K14: =VLOOKUP(L14,Map!$C$18:$D$29,2,0) -> DLT | L14: Air Cleaner | M14: 291662.76 | N14: =IF(L14="TOTAL",(M14*0.19),0) -> 0 | O14: =M14*1.19 -> 347078.68 | P14: =M14/S14 -> 315.65233 | Q14: =IF(L14="TOTAL",(P14*0.19),0) -> 0 | R14: =P14*1.19 -> 375.62628 | S14: =INDEX(FX!$D$3:$O$19,MATCH(B14,FX!$B$3:$B$32,0),MATCH(D14,FX!$D$2:$O$2,0)) -> 924 | T14: Monthly Commission | U14: Provision (Based on External Report) | V14: Invoice | W14: =VLOOKUP(I14,Map!$F$18:$H$51,3,0) -> Variable | X14: AP Completed | Y14: =VLOOKUP(L14,Map!$C$18:$D$29,2,0) -> DLT | Z14: 291662.76 | AA14: =IF(Y14="TOTAL",(Z14*0.19),0) -> 0 | AB14: =Z14*1.19 -> 347078.68 | AC14: =Z14/S14 -> 315.65233 | AD14: =IF(Y14="TOTAL",(AC14*0.19),0) -> 0 | AE14: =AC14*1.19 -> 375.62628
B15: 2026 | C15: Jun21 to Jul20 | D15: JUL | E15: JUL (Provision) | F15: AUG | G15: 46230 | H15: 478270 | I15: FALABELLA (DIRECT) | J15: =IFERROR(VLOOKUP(I15,Map!$F$18:$G$56,2,0),"Add in Map") -> 3P | K15: =VLOOKUP(L15,Map!$C$18:$D$29,2,0) -> DMT | L15: SAC | M15: 0 | N15: =IF(L15="TOTAL",(M15*0.19),0) -> 0 | O15: =M15*1.19 -> 0 | P15: 0 | Q15: =IF(L15="TOTAL",(P15*0.19),0) -> 0 | R15: =P15*1.19 -> 0 | S15: =INDEX(FX!$D$3:$O$19,MATCH(B15,FX!$B$3:$B$32,0),MATCH(D15,FX!$D$2:$O$2,0)) -> 924 | T15: Monthly Commission | U15: Provision (Based on External Report) | V15: Invoice | W15: =VLOOKUP(I15,Map!$F$18:$H$51,3,0) -> Variable | X15: AP Completed | Y15: =VLOOKUP(L15,Map!$C$18:$D$29,2,0) -> DMT | Z15: 0 | AA15: =IF(Y15="TOTAL",(Z15*0.19),0) -> 0 | AB15: =Z15*1.19 -> 0 | AC15: =Z15/S15 -> 0 | AD15: =IF(Y15="TOTAL",(AC15*0.19),0) -> 0 | AE15: =AC15*1.19 -> 0
B16: 2026 | C16: Jun21 to Jul20 | D16: JUL | E16: JUL (Provision) | F16: AUG | G16: 46230 | H16: 478270 | I16: FALABELLA (DIRECT) | J16: =IFERROR(VLOOKUP(I16,Map!$F$18:$G$56,2,0),"Add in Map") -> 3P | K16: =VLOOKUP(L16,Map!$C$18:$D$29,2,0) -> TOTAL | L16: TOTAL | M16: =SUM(M5:M15) -> 141164774 | N16: =IF(L16="TOTAL",(M16*0.19),0) -> 26821307 | O16: =M16*1.19 -> 1.6798608e+08 | P16: =M16/S16 -> 152775.73 | Q16: =IF(L16="TOTAL",(P16*0.19),0) -> 29027.389 | R16: =P16*1.19 -> 181803.12 | S16: =INDEX(FX!$D$3:$O$19,MATCH(B16,FX!$B$3:$B$32,0),MATCH(D16,FX!$D$2:$O$2,0)) -> 924 | T16: Monthly Commission | U16: Provision (Based on External Report) | V16: Invoice | W16: =VLOOKUP(I16,Map!$F$18:$H$51,3,0) -> Variable | X16: AP Completed | Y16: =VLOOKUP(L16,Map!$C$18:$D$29,2,0) -> TOTAL | Z16: =SUM(Z5:Z15) -> 141164774 | AA16: =IF(Y16="TOTAL",(Z16*0.19),0) -> 26821307 | AB16: =Z16*1.19 -> 1.6798608e+08 | AC16: =Z16/S16 -> 152775.73 | AD16: =IF(Y16="TOTAL",(AC16*0.19),0) -> 29027.389 | AE16: =AC16*1.19 -> 181803.12 | AF16: http://lg2607.acepta.com/v01/5E0A125A9F4EB54908C00523002399A4BD42D7F9
B17: 2026 | C17: Jun21 to Jul20 | D17: JUL | E17: JUL (Provision) | F17: AUG | G17: 46230 | H17: 456288 | I17: FALABELLA (DIRECT) | J17: =IFERROR(VLOOKUP(I17,Map!$F$18:$G$56,2,0),"Add in Map") -> 3P | K17: =VLOOKUP(L17,Map!$C$18:$D$29,2,0) -> CNT | L17: Refrigeration | M17: -10338484 | N17: =IF(L17="TOTAL",(M17*0.19),0) -> 0 | O17: =M17*1.19 -> -12302795 | P17: =M17/S17 -> -11188.835 | Q17: =IF(L17="TOTAL",(P17*0.19),0) -> 0 | R17: =P17*1.19 -> -13314.714 | S17: =INDEX(FX!$D$3:$O$19,MATCH(B17,FX!$B$3:$B$32,0),MATCH(D17,FX!$D$2:$O$2,0)) -> 924 | T17: Monthly Commission | U17: Provision (Based on External Report) | V17: Credit Note | W17: =VLOOKUP(I17,Map!$F$18:$H$51,3,0) -> Variable | X17: AP Completed | Y17: =VLOOKUP(L17,Map!$C$18:$D$29,2,0) -> CNT | Z17: -10338484 | AA17: =IF(Y17="TOTAL",(Z17*0.19),0) -> 0 | AB17: =Z17*1.19 -> -12302795 | AC17: =Z17/S17 -> -11188.835 | AD17: =IF(Y17="TOTAL",(AC17*0.19),0) -> 0 | AE17: =AC17*1.19 -> -13314.714
B18: 2026 | C18: Jun21 to Jul20 | D18: JUL | E18: JUL (Provision) | F18: AUG | G18: 46230 | H18: 456288 | I18: FALABELLA (DIRECT) | J18: =IFERROR(VLOOKUP(I18,Map!$F$18:$G$56,2,0),"Add in Map") -> 3P | K18: =VLOOKUP(L18,Map!$C$18:$D$29,2,0) -> CVT | L18: Cooking | M18: -122348.92 | N18: =IF(L18="TOTAL",(M18*0.19),0) -> 0 | O18: =M18*1.19 -> -145595.21 | P18: =M18/S18 -> -132.41225 | Q18: =IF(L18="TOTAL",(P18*0.19),0) -> 0 | R18: =P18*1.19 -> -157.57058 | S18: =INDEX(FX!$D$3:$O$19,MATCH(B18,FX!$B$3:$B$32,0),MATCH(D18,FX!$D$2:$O$2,0)) -> 924 | T18: Monthly Commission | U18: Provision (Based on External Report) | V18: Credit Note | W18: =VLOOKUP(I18,Map!$F$18:$H$51,3,0) -> Variable | X18: AP Completed | Y18: =VLOOKUP(L18,Map!$C$18:$D$29,2,0) -> CVT | Z18: -122348.92 | AA18: =IF(Y18="TOTAL",(Z18*0.19),0) -> 0 | AB18: =Z18*1.19 -> -145595.21 | AC18: =Z18/S18 -> -132.41225 | AD18: =IF(Y18="TOTAL",(AC18*0.19),0) -> 0 | AE18: =AC18*1.19 -> -157.57058
B19: 2026 | C19: Jun21 to Jul20 | D19: JUL | E19: JUL (Provision) | F19: AUG | G19: 46230 | H19: 456288 | I19: FALABELLA (DIRECT) | J19: =IFERROR(VLOOKUP(I19,Map!$F$18:$G$56,2,0),"Add in Map") -> 3P | K19: =VLOOKUP(L19,Map!$C$18:$D$29,2,0) -> CDT | L19: Dishwasher | M19: -428221.21 | N19: =IF(L19="TOTAL",(M19*0.19),0) -> 0 | O19: =M19*1.19 -> -509583.24 | P19: =M19/S19 -> -463.44287 | Q19: =IF(L19="TOTAL",(P19*0.19),0) -> 0 | R19: =P19*1.19 -> -551.49701 | S19: =INDEX(FX!$D$3:$O$19,MATCH(B19,FX!$B$3:$B$32,0),MATCH(D19,FX!$D$2:$O$2,0)) -> 924 | T19: Monthly Commission | U19: Provision (Based on External Report) | V19: Credit Note | W19: =VLOOKUP(I19,Map!$F$18:$H$51,3,0) -> Variable | X19: AP Completed | Y19: =VLOOKUP(L19,Map!$C$18:$D$29,2,0) -> CDT | Z19: -428221.21 | AA19: =IF(Y19="TOTAL",(Z19*0.19),0) -> 0 | AB19: =Z19*1.19 -> -509583.24 | AC19: =Z19/S19 -> -463.44287 | AD19: =IF(Y19="TOTAL",(AC19*0.19),0) -> 0 | AE19: =AC19*1.19 -> -551.49701
B20: 2026 | C20: Jun21 to Jul20 | D20: JUL | E20: JUL (Provision) | F20: AUG | G20: 46230 | H20: 456288 | I20: FALABELLA (DIRECT) | J20: =IFERROR(VLOOKUP(I20,Map!$F$18:$G$56,2,0),"Add in Map") -> 3P | K20: =VLOOKUP(L20,Map!$C$18:$D$29,2,0) -> DFT | L20: WM | M20: -30709578 | N20: =IF(L20="TOTAL",(M20*0.19),0) -> 0 | O20: =M20*1.19 -> -36544398 | P20: =M20/S20 -> -33235.474 | Q20: =IF(L20="TOTAL",(P20*0.19),0) -> 0 | R20: =P20*1.19 -> -39550.214 | S20: =INDEX(FX!$D$3:$O$19,MATCH(B20,FX!$B$3:$B$32,0),MATCH(D20,FX!$D$2:$O$2,0)) -> 924 | T20: Monthly Commission | U20: Provision (Based on External Report) | V20: Credit Note | W20: =VLOOKUP(I20,Map!$F$18:$H$51,3,0) -> Variable | X20: AP Completed | Y20: =VLOOKUP(L20,Map!$C$18:$D$29,2,0) -> DFT | Z20: -30709578 | AA20: =IF(Y20="TOTAL",(Z20*0.19),0) -> 0 | AB20: =Z20*1.19 -> -36544398 | AC20: =Z20/S20 -> -33235.474 | AD20: =IF(Y20="TOTAL",(AC20*0.19),0) -> 0 | AE20: =AC20*1.19 -> -39550.214
B21: 2026 | C21: Jun21 to Jul20 | D21: JUL | E21: JUL (Provision) | F21: AUG | G21: 46230 | H21: 456288 | I21: FALABELLA (DIRECT) | J21: =IFERROR(VLOOKUP(I21,Map!$F$18:$G$56,2,0),"Add in Map") -> 3P | K21: =VLOOKUP(L21,Map!$C$18:$D$29,2,0) -> DVT | L21: VCC | M21: -61174.459 | N21: =IF(L21="TOTAL",(M21*0.19),0) -> 0 | O21: =M21*1.19 -> -72797.606 | P21: =M21/S21 -> -66.206124 | Q21: =IF(L21="TOTAL",(P21*0.19),0) -> 0 | R21: =P21*1.19 -> -78.785288 | S21: =INDEX(FX!$D$3:$O$19,MATCH(B21,FX!$B$3:$B$32,0),MATCH(D21,FX!$D$2:$O$2,0)) -> 924 | T21: Monthly Commission | U21: Provision (Based on External Report) | V21: Credit Note | W21: =VLOOKUP(I21,Map!$F$18:$H$51,3,0) -> Variable | X21: AP Completed | Y21: =VLOOKUP(L21,Map!$C$18:$D$29,2,0) -> DVT | Z21: -61174.459 | AA21: =IF(Y21="TOTAL",(Z21*0.19),0) -> 0 | AB21: =Z21*1.19 -> -72797.606 | AC21: =Z21/S21 -> -66.206124 | AD21: =IF(Y21="TOTAL",(AC21*0.19),0) -> 0 | AE21: =AC21*1.19 -> -78.785288
B22: 2026 | C22: Jun21 to Jul20 | D22: JUL | E22: JUL (Provision) | F22: AUG | G22: 46230 | H22: 456288 | I22: FALABELLA (DIRECT) | J22: =IFERROR(VLOOKUP(I22,Map!$F$18:$G$56,2,0),"Add in Map") -> 3P | K22: =VLOOKUP(L22,Map!$C$18:$D$29,2,0) -> GLT | L22: Television | M22: -14559521 | N22: =IF(L22="TOTAL",(M22*0.19),0) -> 0 | O22: =M22*1.19 -> -17325830 | P22: =M22/S22 -> -15757.058 | Q22: =IF(L22="TOTAL",(P22*0.19),0) -> 0 | R22: =P22*1.19 -> -18750.898 | S22: =INDEX(FX!$D$3:$O$19,MATCH(B22,FX!$B$3:$B$32,0),MATCH(D22,FX!$D$2:$O$2,0)) -> 924 | T22: Monthly Commission | U22: Provision (Based on External Report) | V22: Credit Note | W22: =VLOOKUP(I22,Map!$F$18:$H$51,3,0) -> Variable | X22: AP Completed | Y22: =VLOOKUP(L22,Map!$C$18:$D$29,2,0) -> GLT | Z22: -14559521 | AA22: =IF(Y22="TOTAL",(Z22*0.19),0) -> 0 | AB22: =Z22*1.19 -> -17325830 | AC22: =Z22/S22 -> -15757.058 | AD22: =IF(Y22="TOTAL",(AC22*0.19),0) -> 0 | AE22: =AC22*1.19 -> -18750.898
B23: 2026 | C23: Jun21 to Jul20 | D23: JUL | E23: JUL (Provision) | F23: AUG | G23: 46230 | H23: 456288 | I23: FALABELLA (DIRECT) | J23: =IFERROR(VLOOKUP(I23,Map!$F$18:$G$56,2,0),"Add in Map") -> 3P | K23: =VLOOKUP(L23,Map!$C$18:$D$29,2,0) -> PNT | L23: Audio | M23: -917616.88 | N23: =IF(L23="TOTAL",(M23*0.19),0) -> 0 | O23: =M23*1.19 -> -1091964.1 | P23: =M23/S23 -> -993.09186 | Q23: =IF(L23="TOTAL",(P23*0.19),0) -> 0 | R23: =P23*1.19 -> -1181.7793 | S23: =INDEX(FX!$D$3:$O$19,MATCH(B23,FX!$B$3:$B$32,0),MATCH(D23,FX!$D$2:$O$2,0)) -> 924 | T23: Monthly Commission | U23: Provision (Based on External Report) | V23: Credit Note | W23: =VLOOKUP(I23,Map!$F$18:$H$51,3,0) -> Variable | X23: AP Completed | Y23: =VLOOKUP(L23,Map!$C$18:$D$29,2,0) -> PNT | Z23: -917616.88 | AA23: =IF(Y23="TOTAL",(Z23*0.19),0) -> 0 | AB23: =Z23*1.19 -> -1091964.1 | AC23: =Z23/S23 -> -993.09186 | AD23: =IF(Y23="TOTAL",(AC23*0.19),0) -> 0 | AE23: =AC23*1.19 -> -1181.7793
B24: 2026 | C24: Jun21 to Jul20 | D24: JUL | E24: JUL (Provision) | F24: AUG | G24: 46230 | H24: 456288 | I24: FALABELLA (DIRECT) | J24: =IFERROR(VLOOKUP(I24,Map!$F$18:$G$56,2,0),"Add in Map") -> 3P | K24: =VLOOKUP(L24,Map!$C$18:$D$29,2,0) -> GTT | L24: Monitor | M24: -1529361.5 | N24: =IF(L24="TOTAL",(M24*0.19),0) -> 0 | O24: =M24*1.19 -> -1819940.1 | P24: =M24/S24 -> -1655.1531 | Q24: =IF(L24="TOTAL",(P24*0.19),0) -> 0 | R24: =P24*1.19 -> -1969.6322 | S24: =INDEX(FX!$D$3:$O$19,MATCH(B24,FX!$B$3:$B$32,0),MATCH(D24,FX!$D$2:$O$2,0)) -> 924 | T24: Monthly Commission | U24: Provision (Based on External Report) | V24: Credit Note | W24: =VLOOKUP(I24,Map!$F$18:$H$51,3,0) -> Variable | X24: AP Completed | Y24: =VLOOKUP(L24,Map!$C$18:$D$29,2,0) -> GTT | Z24: -1529361.5 | AA24: =IF(Y24="TOTAL",(Z24*0.19),0) -> 0 | AB24: =Z24*1.19 -> -1819940.1 | AC24: =Z24/S24 -> -1655.1531 | AD24: =IF(Y24="TOTAL",(AC24*0.19),0) -> 0 | AE24: =AC24*1.19 -> -1969.6322
B25: 2026 | C25: Jun21 to Jul20 | D25: JUL | E25: JUL (Provision) | F25: AUG | G25: 46230 | H25: 456288 | I25: FALABELLA (DIRECT) | J25: =IFERROR(VLOOKUP(I25,Map!$F$18:$G$56,2,0),"Add in Map") -> 3P | K25: =VLOOKUP(L25,Map!$C$18:$D$29,2,0) -> DGT | L25: RAC | M25: -428221.21 | N25: =IF(L25="TOTAL",(M25*0.19),0) -> 0 | O25: =M25*1.19 -> -509583.24 | P25: =M25/S25 -> -463.44287 | Q25: =IF(L25="TOTAL",(P25*0.19),0) -> 0 | R25: =P25*1.19 -> -551.49701 | S25: =INDEX(FX!$D$3:$O$19,MATCH(B25,FX!$B$3:$B$32,0),MATCH(D25,FX!$D$2:$O$2,0)) -> 924 | T25: Monthly Commission | U25: Provision (Based on External Report) | V25: Credit Note | W25: =VLOOKUP(I25,Map!$F$18:$H$51,3,0) -> Variable | X25: AP Completed | Y25: =VLOOKUP(L25,Map!$C$18:$D$29,2,0) -> DGT | Z25: -428221.21 | AA25: =IF(Y25="TOTAL",(Z25*0.19),0) -> 0 | AB25: =Z25*1.19 -> -509583.24 | AC25: =Z25/S25 -> -463.44287 | AD25: =IF(Y25="TOTAL",(AC25*0.19),0) -> 0 | AE25: =AC25*1.19 -> -551.49701
B26: 2026 | C26: Jun21 to Jul20 | D26: JUL | E26: JUL (Provision) | F26: AUG | G26: 46230 | H26: 456288 | I26: FALABELLA (DIRECT) | J26: =IFERROR(VLOOKUP(I26,Map!$F$18:$G$56,2,0),"Add in Map") -> 3P | K26: =VLOOKUP(L26,Map!$C$18:$D$29,2,0) -> DLT | L26: Air Cleaner | M26: -122348.92 | N26: =IF(L26="TOTAL",(M26*0.19),0) -> 0 | O26: =M26*1.19 -> -145595.21 | P26: =M26/S26 -> -132.41225 | Q26: =IF(L26="TOTAL",(P26*0.19),0) -> 0 | R26: =P26*1.19 -> -157.57058 | S26: =INDEX(FX!$D$3:$O$19,MATCH(B26,FX!$B$3:$B$32,0),MATCH(D26,FX!$D$2:$O$2,0)) -> 924 | T26: Monthly Commission | U26: Provision (Based on External Report) | V26: Credit Note | W26: =VLOOKUP(I26,Map!$F$18:$H$51,3,0) -> Variable | X26: AP Completed | Y26: =VLOOKUP(L26,Map!$C$18:$D$29,2,0) -> DLT | Z26: -122348.92 | AA26: =IF(Y26="TOTAL",(Z26*0.19),0) -> 0 | AB26: =Z26*1.19 -> -145595.21 | AC26: =Z26/S26 -> -132.41225 | AD26: =IF(Y26="TOTAL",(AC26*0.19),0) -> 0 | AE26: =AC26*1.19 -> -157.57058
B27: 2026 | C27: Jun21 to Jul20 | D27: JUL | E27: JUL (Provision) | F27: AUG | G27: 46230 | H27: 456288 | I27: FALABELLA (DIRECT) | J27: =IFERROR(VLOOKUP(I27,Map!$F$18:$G$56,2,0),"Add in Map") -> 3P | K27: =VLOOKUP(L27,Map!$C$18:$D$29,2,0) -> DMT | L27: SAC | M27: 0 | N27: =IF(L27="TOTAL",(M27*0.19),0) -> 0 | O27: =M27*1.19 -> 0 | P27: =M27/S27 -> 0 | Q27: =IF(L27="TOTAL",(P27*0.19),0) -> 0 | R27: =P27*1.19 -> 0 | S27: =INDEX(FX!$D$3:$O$19,MATCH(B27,FX!$B$3:$B$32,0),MATCH(D27,FX!$D$2:$O$2,0)) -> 924 | T27: Monthly Commission | U27: Provision (Based on External Report) | V27: Credit Note | W27: =VLOOKUP(I27,Map!$F$18:$H$51,3,0) -> Variable | X27: AP Completed | Y27: =VLOOKUP(L27,Map!$C$18:$D$29,2,0) -> DMT | Z27: 0 | AA27: =IF(Y27="TOTAL",(Z27*0.19),0) -> 0 | AB27: =Z27*1.19 -> 0 | AC27: =Z27/S27 -> 0 | AD27: =IF(Y27="TOTAL",(AC27*0.19),0) -> 0 | AE27: =AC27*1.19 -> 0
B28: 2026 | C28: Jun21 to Jul20 | D28: JUL | E28: JUL (Provision) | F28: AUG | G28: 46230 | H28: 456288 | I28: FALABELLA (DIRECT) | J28: =IFERROR(VLOOKUP(I28,Map!$F$18:$G$56,2,0),"Add in Map") -> 3P | K28: =VLOOKUP(L28,Map!$C$18:$D$29,2,0) -> TOTAL | L28: TOTAL | M28: =SUM(M17:M27) -> -59216876 | N28: =IF(L28="TOTAL",(M28*0.19),0) -> -11251206 | O28: =M28*1.19 -> -70468082 | P28: =M28/S28 -> -64087.528 | Q28: =IF(L28="TOTAL",(P28*0.19),0) -> -12176.63 | R28: =P28*1.19 -> -76264.158 | S28: =INDEX(FX!$D$3:$O$19,MATCH(B28,FX!$B$3:$B$32,0),MATCH(D28,FX!$D$2:$O$2,0)) -> 924 | T28: Monthly Commission | U28: Provision (Based on External Report) | V28: Credit Note | W28: =VLOOKUP(I28,Map!$F$18:$H$51,3,0) -> Variable | X28: AP Completed | Y28: =VLOOKUP(L28,Map!$C$18:$D$29,2,0) -> TOTAL | Z28: =SUM(Z17:Z27) -> -59216876 | AA28: =IF(Y28="TOTAL",(Z28*0.19),0) -> -11251206 | AB28: =Z28*1.19 -> -70468082 | AC28: =Z28/S28 -> -64087.528 | AD28: =IF(Y28="TOTAL",(AC28*0.19),0) -> -12176.63 | AE28: =AC28*1.19 -> -76264.158 | AF28: http://lg2607.acepta.com/v01/AD2F1E54CFEE4EA8AEAAF32C8EE536D5DD0B56A6
B29: 2026 | C29: Jun27 to Jul15 | D29: JUL | E29: JUL (Provision) | F29: Pending | I29: PARIS (FULLKOM) | J29: =IFERROR(VLOOKUP(I29,Map!$F$18:$G$56,2,0),"Add in Map") -> 3P | K29: =VLOOKUP(L29,Map!$C$18:$D$29,2,0) -> CNT | L29: Refrigeration | M29: 4169389.7 | N29: =IF(L29="TOTAL",(M29*0.19),0) -> 0 | O29: =M29*1.19 -> 4961573.7 | P29: =M29/S29 -> 4512.3265 | Q29: =IF(L29="TOTAL",(P29*0.19),0) -> 0 | R29: =P29*1.19 -> 5369.6685 | S29: =INDEX(FX!$D$3:$O$19,MATCH(B29,FX!$B$3:$B$32,0),MATCH(D29,FX!$D$2:$O$2,0)) -> 924 | T29: Commission (1era Quincena) | U29: Provision (Based on PO, One View) | V29: Invoice | W29: =VLOOKUP(I29,Map!$F$18:$H$51,3,0) -> Variable | X29: Pending | Y29: =VLOOKUP(L29,Map!$C$18:$D$29,2,0) -> CNT | AA29: =IF(Y29="TOTAL",(Z29*0.19),0) -> 0 | AB29: =Z29*1.19 -> 0 | AC29: =Z29/S29 -> 0 | AD29: =IF(Y29="TOTAL",(AC29*0.19),0) -> 0 | AE29: =AC29*1.19 -> 0
B30: 2026 | C30: Jun27 to Jul15 | D30: JUL | E30: JUL (Provision) | F30: Pending | I30: PARIS (FULLKOM) | J30: =IFERROR(VLOOKUP(I30,Map!$F$18:$G$56,2,0),"Add in Map") -> 3P | K30: =VLOOKUP(L30,Map!$C$18:$D$29,2,0) -> CVT | L30: Cooking | M30: 0 | N30: =IF(L30="TOTAL",(M30*0.19),0) -> 0 | O30: =M30*1.19 -> 0 | P30: =M30/S30 -> 0 | Q30: =IF(L30="TOTAL",(P30*0.19),0) -> 0 | R30: =P30*1.19 -> 0 | S30: =INDEX(FX!$D$3:$O$19,MATCH(B30,FX!$B$3:$B$32,0),MATCH(D30,FX!$D$2:$O$2,0)) -> 924 | T30: Commission (1era Quincena) | U30: Provision (Based on PO, One View) | V30: Invoice | W30: =VLOOKUP(I30,Map!$F$18:$H$51,3,0) -> Variable | X30: Pending | Y30: =VLOOKUP(L30,Map!$C$18:$D$29,2,0) -> CVT | AA30: =IF(Y30="TOTAL",(Z30*0.19),0) -> 0 | AB30: =Z30*1.19 -> 0 | AC30: =Z30/S30 -> 0 | AD30: =IF(Y30="TOTAL",(AC30*0.19),0) -> 0 | AE30: =AC30*1.19 -> 0
B31: 2026 | C31: Jun27 to Jul15 | D31: JUL | E31: JUL (Provision) | F31: Pending | I31: PARIS (FULLKOM) | J31: =IFERROR(VLOOKUP(I31,Map!$F$18:$G$56,2,0),"Add in Map") -> 3P | K31: =VLOOKUP(L31,Map!$C$18:$D$29,2,0) -> CDT | L31: Dishwasher | M31: 53453.713 | N31: =IF(L31="TOTAL",(M31*0.19),0) -> 0 | O31: =M31*1.19 -> 63609.919 | P31: =M31/S31 -> 57.850339 | Q31: =IF(L31="TOTAL",(P31*0.19),0) -> 0 | R31: =P31*1.19 -> 68.841904 | S31: =INDEX(FX!$D$3:$O$19,MATCH(B31,FX!$B$3:$B$32,0),MATCH(D31,FX!$D$2:$O$2,0)) -> 924 | T31: Commission (1era Quincena) | U31: Provision (Based on PO, One View) | V31: Invoice | W31: =VLOOKUP(I31,Map!$F$18:$H$51,3,0) -> Variable | X31: Pending | Y31: =VLOOKUP(L31,Map!$C$18:$D$29,2,0) -> CDT | AA31: =IF(Y31="TOTAL",(Z31*0.19),0) -> 0 | AB31: =Z31*1.19 -> 0 | AC31: =Z31/S31 -> 0 | AD31: =IF(Y31="TOTAL",(AC31*0.19),0) -> 0 | AE31: =AC31*1.19 -> 0
B32: 2026 | C32: Jun27 to Jul15 | D32: JUL | E32: JUL (Provision) | F32: Pending | I32: PARIS (FULLKOM) | J32: =IFERROR(VLOOKUP(I32,Map!$F$18:$G$56,2,0),"Add in Map") -> 3P | K32: =VLOOKUP(L32,Map!$C$18:$D$29,2,0) -> DFT | L32: WM | M32: 10049298 | N32: =IF(L32="TOTAL",(M32*0.19),0) -> 0 | O32: =M32*1.19 -> 11958665 | P32: =M32/S32 -> 10875.864 | Q32: =IF(L32="TOTAL",(P32*0.19),0) -> 0 | R32: =P32*1.19 -> 12942.278 | S32: =INDEX(FX!$D$3:$O$19,MATCH(B32,FX!$B$3:$B$32,0),MATCH(D32,FX!$D$2:$O$2,0)) -> 924 | T32: Commission (1era Quincena) | U32: Provision (Based on PO, One View) | V32: Invoice | W32: =VLOOKUP(I32,Map!$F$18:$H$51,3,0) -> Variable | X32: Pending | Y32: =VLOOKUP(L32,Map!$C$18:$D$29,2,0) -> DFT | AA32: =IF(Y32="TOTAL",(Z32*0.19),0) -> 0 | AB32: =Z32*1.19 -> 0 | AC32: =Z32/S32 -> 0 | AD32: =IF(Y32="TOTAL",(AC32*0.19),0) -> 0 | AE32: =AC32*1.19 -> 0
B33: 2026 | C33: Jun27 to Jul15 | D33: JUL | E33: JUL (Provision) | F33: Pending | I33: PARIS (FULLKOM) | J33: =IFERROR(VLOOKUP(I33,Map!$F$18:$G$56,2,0),"Add in Map") -> 3P | K33: =VLOOKUP(L33,Map!$C$18:$D$29,2,0) -> DVT | L33: VCC | M33: 0 | N33: =IF(L33="TOTAL",(M33*0.19),0) -> 0 | O33: =M33*1.19 -> 0 | P33: =M33/S33 -> 0 | Q33: =IF(L33="TOTAL",(P33*0.19),0) -> 0 | R33: =P33*1.19 -> 0 | S33: =INDEX(FX!$D$3:$O$19,MATCH(B33,FX!$B$3:$B$32,0),MATCH(D33,FX!$D$2:$O$2,0)) -> 924 | T33: Commission (1era Quincena) | U33: Provision (Based on PO, One View) | V33: Invoice | W33: =VLOOKUP(I33,Map!$F$18:$H$51,3,0) -> Variable | X33: Pending | Y33: =VLOOKUP(L33,Map!$C$18:$D$29,2,0) -> DVT | AA33: =IF(Y33="TOTAL",(Z33*0.19),0) -> 0 | AB33: =Z33*1.19 -> 0 | AC33: =Z33/S33 -> 0 | AD33: =IF(Y33="TOTAL",(AC33*0.19),0) -> 0 | AE33: =AC33*1.19 -> 0
B34: 2026 | C34: Jun27 to Jul15 | D34: JUL | E34: JUL (Provision) | F34: Pending | I34: PARIS (FULLKOM) | J34: =IFERROR(VLOOKUP(I34,Map!$F$18:$G$56,2,0),"Add in Map") -> 3P | K34: =VLOOKUP(L34,Map!$C$18:$D$29,2,0) -> GLT | L34: Television | M34: 2191602.3 | N34: =IF(L34="TOTAL",(M34*0.19),0) -> 0 | O34: =M34*1.19 -> 2608006.7 | P34: =M34/S34 -> 2371.8639 | Q34: =IF(L34="TOTAL",(P34*0.19),0) -> 0 | R34: =P34*1.19 -> 2822.5181 | S34: =INDEX(FX!$D$3:$O$19,MATCH(B34,FX!$B$3:$B$32,0),MATCH(D34,FX!$D$2:$O$2,0)) -> 924 | T34: Commission (1era Quincena) | U34: Provision (Based on PO, One View) | V34: Invoice | W34: =VLOOKUP(I34,Map!$F$18:$H$51,3,0) -> Variable | X34: Pending | Y34: =VLOOKUP(L34,Map!$C$18:$D$29,2,0) -> GLT | AA34: =IF(Y34="TOTAL",(Z34*0.19),0) -> 0 | AB34: =Z34*1.19 -> 0 | AC34: =Z34/S34 -> 0 | AD34: =IF(Y34="TOTAL",(AC34*0.19),0) -> 0 | AE34: =AC34*1.19 -> 0
B35: 2026 | C35: Jun27 to Jul15 | D35: JUL | E35: JUL (Provision) | F35: Pending | I35: PARIS (FULLKOM) | J35: =IFERROR(VLOOKUP(I35,Map!$F$18:$G$56,2,0),"Add in Map") -> 3P | K35: =VLOOKUP(L35,Map!$C$18:$D$29,2,0) -> PNT | L35: Audio | M35: 374175.99 | N35: =IF(L35="TOTAL",(M35*0.19),0) -> 0 | O35: =M35*1.19 -> 445269.43 | P35: =M35/S35 -> 404.95237 | Q35: =IF(L35="TOTAL",(P35*0.19),0) -> 0 | R35: =P35*1.19 -> 481.89333 | S35: =INDEX(FX!$D$3:$O$19,MATCH(B35,FX!$B$3:$B$32,0),MATCH(D35,FX!$D$2:$O$2,0)) -> 924 | T35: Commission (1era Quincena) | U35: Provision (Based on PO, One View) | V35: Invoice | W35: =VLOOKUP(I35,Map!$F$18:$H$51,3,0) -> Variable | X35: Pending | Y35: =VLOOKUP(L35,Map!$C$18:$D$29,2,0) -> PNT | AA35: =IF(Y35="TOTAL",(Z35*0.19),0) -> 0 | AB35: =Z35*1.19 -> 0 | AC35: =Z35/S35 -> 0 | AD35: =IF(Y35="TOTAL",(AC35*0.19),0) -> 0 | AE35: =AC35*1.19 -> 0
B36: 2026 | C36: Jun27 to Jul15 | D36: JUL | E36: JUL (Provision) | F36: Pending | I36: PARIS (FULLKOM) | J36: =IFERROR(VLOOKUP(I36,Map!$F$18:$G$56,2,0),"Add in Map") -> 3P | K36: =VLOOKUP(L36,Map!$C$18:$D$29,2,0) -> GTT | L36: Monitor | M36: 213814.85 | N36: =IF(L36="TOTAL",(M36*0.19),0) -> 0 | O36: =M36*1.19 -> 254439.68 | P36: =M36/S36 -> 231.40136 | Q36: =IF(L36="TOTAL",(P36*0.19),0) -> 0 | R36: =P36*1.19 -> 275.36761 | S36: =INDEX(FX!$D$3:$O$19,MATCH(B36,FX!$B$3:$B$32,0),MATCH(D36,FX!$D$2:$O$2,0)) -> 924 | T36: Commission (1era Quincena) | U36: Provision (Based on PO, One View) | V36: Invoice | W36: =VLOOKUP(I36,Map!$F$18:$H$51,3,0) -> Variable | X36: Pending | Y36: =VLOOKUP(L36,Map!$C$18:$D$29,2,0) -> GTT | AA36: =IF(Y36="TOTAL",(Z36*0.19),0) -> 0 | AB36: =Z36*1.19 -> 0 | AC36: =Z36/S36 -> 0 | AD36: =IF(Y36="TOTAL",(AC36*0.19),0) -> 0 | AE36: =AC36*1.19 -> 0
B37: 2026 | C37: Jun27 to Jul15 | D37: JUL | E37: JUL (Provision) | F37: Pending | I37: PARIS (FULLKOM) | J37: =IFERROR(VLOOKUP(I37,Map!$F$18:$G$56,2,0),"Add in Map") -> 3P | K37: =VLOOKUP(L37,Map!$C$18:$D$29,2,0) -> DGT | L37: RAC | M37: 160361.14 | N37: =IF(L37="TOTAL",(M37*0.19),0) -> 0 | O37: =M37*1.19 -> 190829.76 | P37: =M37/S37 -> 173.55102 | Q37: =IF(L37="TOTAL",(P37*0.19),0) -> 0 | R37: =P37*1.19 -> 206.52571 | S37: =INDEX(FX!$D$3:$O$19,MATCH(B37,FX!$B$3:$B$32,0),MATCH(D37,FX!$D$2:$O$2,0)) -> 924 | T37: Commission (1era Quincena) | U37: Provision (Based on PO, One View) | V37: Invoice | W37: =VLOOKUP(I37,Map!$F$18:$H$51,3,0) -> Variable | X37: Pending | Y37: =VLOOKUP(L37,Map!$C$18:$D$29,2,0) -> DGT | AA37: =IF(Y37="TOTAL",(Z37*0.19),0) -> 0 | AB37: =Z37*1.19 -> 0 | AC37: =Z37/S37 -> 0 | AD37: =IF(Y37="TOTAL",(AC37*0.19),0) -> 0 | AE37: =AC37*1.19 -> 0
B38: 2026 | C38: Jun27 to Jul15 | D38: JUL | E38: JUL (Provision) | F38: Pending | I38: PARIS (FULLKOM) | J38: =IFERROR(VLOOKUP(I38,Map!$F$18:$G$56,2,0),"Add in Map") -> 3P | K38: =VLOOKUP(L38,Map!$C$18:$D$29,2,0) -> DLT | L38: Air Cleaner | M38: 53453.713 | N38: =IF(L38="TOTAL",(M38*0.19),0) -> 0 | O38: =M38*1.19 -> 63609.919 | P38: =M38/S38 -> 57.850339 | Q38: =IF(L38="TOTAL",(P38*0.19),0) -> 0 | R38: =P38*1.19 -> 68.841904 | S38: =INDEX(FX!$D$3:$O$19,MATCH(B38,FX!$B$3:$B$32,0),MATCH(D38,FX!$D$2:$O$2,0)) -> 924 | T38: Commission (1era Quincena) | U38: Provision (Based on PO, One View) | V38: Invoice | W38: =VLOOKUP(I38,Map!$F$18:$H$51,3,0) -> Variable | X38: Pending | Y38: =VLOOKUP(L38,Map!$C$18:$D$29,2,0) -> DLT | AA38: =IF(Y38="TOTAL",(Z38*0.19),0) -> 0 | AB38: =Z38*1.19 -> 0 | AC38: =Z38/S38 -> 0 | AD38: =IF(Y38="TOTAL",(AC38*0.19),0) -> 0 | AE38: =AC38*1.19 -> 0
B39: 2026 | C39: Jun27 to Jul15 | D39: JUL | E39: JUL (Provision) | F39: Pending | I39: PARIS (FULLKOM) | J39: =IFERROR(VLOOKUP(I39,Map!$F$18:$G$56,2,0),"Add in Map") -> 3P | K39: =VLOOKUP(L39,Map!$C$18:$D$29,2,0) -> DMT | L39: SAC | M39: 0 | N39: =IF(L39="TOTAL",(M39*0.19),0) -> 0 | O39: =M39*1.19 -> 0 | P39: =M39/S39 -> 0 | Q39: =IF(L39="TOTAL",(P39*0.19),0) -> 0 | R39: =P39*1.19 -> 0 | S39: =INDEX(FX!$D$3:$O$19,MATCH(B39,FX!$B$3:$B$32,0),MATCH(D39,FX!$D$2:$O$2,0)) -> 924 | T39: Commission (1era Quincena) | U39: Provision (Based on PO, One View) | V39: Invoice | W39: =VLOOKUP(I39,Map!$F$18:$H$51,3,0) -> Variable | X39: Pending | Y39: =VLOOKUP(L39,Map!$C$18:$D$29,2,0) -> DMT | AA39: =IF(Y39="TOTAL",(Z39*0.19),0) -> 0 | AB39: =Z39*1.19 -> 0 | AC39: =Z39/S39 -> 0 | AD39: =IF(Y39="TOTAL",(AC39*0.19),0) -> 0 | AE39: =AC39*1.19 -> 0
B40: 2026 | C40: Jun27 to Jul15 | D40: JUL | E40: JUL (Provision) | F40: Pending | I40: PARIS (FULLKOM) | J40: =IFERROR(VLOOKUP(I40,Map!$F$18:$G$56,2,0),"Add in Map") -> 3P | K40: =VLOOKUP(L40,Map!$C$18:$D$29,2,0) -> TOTAL | L40: TOTAL | M40: =SUM(M29:M39) -> 17265549 | N40: =IF(L40="TOTAL",(M40*0.19),0) -> 3280454.4 | O40: =M40*1.19 -> 20546004 | P40: =M40/S40 -> 18685.66 | Q40: =IF(L40="TOTAL",(P40*0.19),0) -> 3550.2753 | R40: =P40*1.19 -> 22235.935 | S40: =INDEX(FX!$D$3:$O$19,MATCH(B40,FX!$B$3:$B$32,0),MATCH(D40,FX!$D$2:$O$2,0)) -> 924 | T40: Commission (1era Quincena) | U40: Provision (Based on PO, One View) | V40: Invoice | W40: =VLOOKUP(I40,Map!$F$18:$H$51,3,0) -> Variable | X40: Pending | Y40: =VLOOKUP(L40,Map!$C$18:$D$29,2,0) -> TOTAL | AA40: =IF(Y40="TOTAL",(Z40*0.19),0) -> 0 | AB40: =Z40*1.19 -> 0 | AC40: =Z40/S40 -> 0 | AD40: =IF(Y40="TOTAL",(AC40*0.19),0) -> 0 | AE40: =AC40*1.19 -> 0
B41: 2026 | C41: Jul16 to Jul31 | D41: JUL | E41: JUL (Provision) | F41: Pending | I41: PARIS (FULLKOM) | J41: =IFERROR(VLOOKUP(I41,Map!$F$18:$G$56,2,0),"Add in Map") -> 3P | K41: =VLOOKUP(L41,Map!$C$18:$D$29,2,0) -> CNT | L41: Refrigeration | M41: 4054902.2 | N41: =IF(L41="TOTAL",(M41*0.19),0) -> 0 | O41: =M41*1.19 -> 4825333.7 | P41: =M41/S41 -> 4388.4223 | Q41: =IF(L41="TOTAL",(P41*0.19),0) -> 0 | R41: =P41*1.19 -> 5222.2226 | S41: =INDEX(FX!$D$3:$O$19,MATCH(B41,FX!$B$3:$B$32,0),MATCH(D41,FX!$D$2:$O$2,0)) -> 924 | T41: Commission (2da Quincena) | U41: Provision (Based on PO, One View) | V41: Invoice | W41: =VLOOKUP(I41,Map!$F$18:$H$51,3,0) -> Variable | X41: Pending | Y41: =VLOOKUP(L41,Map!$C$18:$D$29,2,0) -> CNT | AA41: =IF(Y41="TOTAL",(Z41*0.19),0) -> 0 | AB41: =Z41*1.19 -> 0 | AC41: =Z41/S41 -> 0 | AD41: =IF(Y41="TOTAL",(AC41*0.19),0) -> 0 | AE41: =AC41*1.19 -> 0
B42: 2026 | C42: Jul16 to Jul31 | D42: JUL | E42: JUL (Provision) | F42: Pending | I42: PARIS (FULLKOM) | J42: =IFERROR(VLOOKUP(I42,Map!$F$18:$G$56,2,0),"Add in Map") -> 3P | K42: =VLOOKUP(L42,Map!$C$18:$D$29,2,0) -> CVT | L42: Cooking | M42: 0 | N42: =IF(L42="TOTAL",(M42*0.19),0) -> 0 | O42: =M42*1.19 -> 0 | P42: =M42/S42 -> 0 | Q42: =IF(L42="TOTAL",(P42*0.19),0) -> 0 | R42: =P42*1.19 -> 0 | S42: =INDEX(FX!$D$3:$O$19,MATCH(B42,FX!$B$3:$B$32,0),MATCH(D42,FX!$D$2:$O$2,0)) -> 924 | T42: Commission (2da Quincena) | U42: Provision (Based on PO, One View) | V42: Invoice | W42: =VLOOKUP(I42,Map!$F$18:$H$51,3,0) -> Variable | X42: Pending | Y42: =VLOOKUP(L42,Map!$C$18:$D$29,2,0) -> CVT | AA42: =IF(Y42="TOTAL",(Z42*0.19),0) -> 0 | AB42: =Z42*1.19 -> 0 | AC42: =Z42/S42 -> 0 | AD42: =IF(Y42="TOTAL",(AC42*0.19),0) -> 0 | AE42: =AC42*1.19 -> 0
B43: 2026 | C43: Jul16 to Jul31 | D43: JUL | E43: JUL (Provision) | F43: Pending | I43: PARIS (FULLKOM) | J43: =IFERROR(VLOOKUP(I43,Map!$F$18:$G$56,2,0),"Add in Map") -> 3P | K43: =VLOOKUP(L43,Map!$C$18:$D$29,2,0) -> CDT | L43: Dishwasher | M43: 51985.926 | N43: =IF(L43="TOTAL",(M43*0.19),0) -> 0 | O43: =M43*1.19 -> 61863.252 | P43: =M43/S43 -> 56.261825 | Q43: =IF(L43="TOTAL",(P43*0.19),0) -> 0 | R43: =P43*1.19 -> 66.951572 | S43: =INDEX(FX!$D$3:$O$19,MATCH(B43,FX!$B$3:$B$32,0),MATCH(D43,FX!$D$2:$O$2,0)) -> 924 | T43: Commission (2da Quincena) | U43: Provision (Based on PO, One View) | V43: Invoice | W43: =VLOOKUP(I43,Map!$F$18:$H$51,3,0) -> Variable | X43: Pending | Y43: =VLOOKUP(L43,Map!$C$18:$D$29,2,0) -> CDT | AA43: =IF(Y43="TOTAL",(Z43*0.19),0) -> 0 | AB43: =Z43*1.19 -> 0 | AC43: =Z43/S43 -> 0 | AD43: =IF(Y43="TOTAL",(AC43*0.19),0) -> 0 | AE43: =AC43*1.19 -> 0
B44: 2026 | C44: Jul16 to Jul31 | D44: JUL | E44: JUL (Provision) | F44: Pending | I44: PARIS (FULLKOM) | J44: =IFERROR(VLOOKUP(I44,Map!$F$18:$G$56,2,0),"Add in Map") -> 3P | K44: =VLOOKUP(L44,Map!$C$18:$D$29,2,0) -> DFT | L44: WM | M44: 9773354.1 | N44: =IF(L44="TOTAL",(M44*0.19),0) -> 0 | O44: =M44*1.19 -> 11630291 | P44: =M44/S44 -> 10577.223 | Q44: =IF(L44="TOTAL",(P44*0.19),0) -> 0 | R44: =P44*1.19 -> 12586.895 | S44: =INDEX(FX!$D$3:$O$19,MATCH(B44,FX!$B$3:$B$32,0),MATCH(D44,FX!$D$2:$O$2,0)) -> 924 | T44: Commission (2da Quincena) | U44: Provision (Based on PO, One View) | V44: Invoice | W44: =VLOOKUP(I44,Map!$F$18:$H$51,3,0) -> Variable | X44: Pending | Y44: =VLOOKUP(L44,Map!$C$18:$D$29,2,0) -> DFT | AA44: =IF(Y44="TOTAL",(Z44*0.19),0) -> 0 | AB44: =Z44*1.19 -> 0 | AC44: =Z44/S44 -> 0 | AD44: =IF(Y44="TOTAL",(AC44*0.19),0) -> 0 | AE44: =AC44*1.19 -> 0
B45: 2026 | C45: Jul16 to Jul31 | D45: JUL | E45: JUL (Provision) | F45: Pending | I45: PARIS (FULLKOM) | J45: =IFERROR(VLOOKUP(I45,Map!$F$18:$G$56,2,0),"Add in Map") -> 3P | K45: =VLOOKUP(L45,Map!$C$18:$D$29,2,0) -> DVT | L45: VCC | M45: 0 | N45: =IF(L45="TOTAL",(M45*0.19),0) -> 0 | O45: =M45*1.19 -> 0 | P45: =M45/S45 -> 0 | Q45: =IF(L45="TOTAL",(P45*0.19),0) -> 0 | R45: =P45*1.19 -> 0 | S45: =INDEX(FX!$D$3:$O$19,MATCH(B45,FX!$B$3:$B$32,0),MATCH(D45,FX!$D$2:$O$2,0)) -> 924 | T45: Commission (2da Quincena) | U45: Provision (Based on PO, One View) | V45: Invoice | W45: =VLOOKUP(I45,Map!$F$18:$H$51,3,0) -> Variable | X45: Pending | Y45: =VLOOKUP(L45,Map!$C$18:$D$29,2,0) -> DVT | AA45: =IF(Y45="TOTAL",(Z45*0.19),0) -> 0 | AB45: =Z45*1.19 -> 0 | AC45: =Z45/S45 -> 0 | AD45: =IF(Y45="TOTAL",(AC45*0.19),0) -> 0 | AE45: =AC45*1.19 -> 0
B46: 2026 | C46: Jul16 to Jul31 | D46: JUL | E46: JUL (Provision) | F46: Pending | I46: PARIS (FULLKOM) | J46: =IFERROR(VLOOKUP(I46,Map!$F$18:$G$56,2,0),"Add in Map") -> 3P | K46: =VLOOKUP(L46,Map!$C$18:$D$29,2,0) -> GLT | L46: Television | M46: 2131423 | N46: =IF(L46="TOTAL",(M46*0.19),0) -> 0 | O46: =M46*1.19 -> 2536393.3 | P46: =M46/S46 -> 2306.7348 | Q46: =IF(L46="TOTAL",(P46*0.19),0) -> 0 | R46: =P46*1.19 -> 2745.0144 | S46: =INDEX(FX!$D$3:$O$19,MATCH(B46,FX!$B$3:$B$32,0),MATCH(D46,FX!$D$2:$O$2,0)) -> 924 | T46: Commission (2da Quincena) | U46: Provision (Based on PO, One View) | V46: Invoice | W46: =VLOOKUP(I46,Map!$F$18:$H$51,3,0) -> Variable | X46: Pending | Y46: =VLOOKUP(L46,Map!$C$18:$D$29,2,0) -> GLT | AA46: =IF(Y46="TOTAL",(Z46*0.19),0) -> 0 | AB46: =Z46*1.19 -> 0 | AC46: =Z46/S46 -> 0 | AD46: =IF(Y46="TOTAL",(AC46*0.19),0) -> 0 | AE46: =AC46*1.19 -> 0
B47: 2026 | C47: Jul16 to Jul31 | D47: JUL | E47: JUL (Provision) | F47: Pending | I47: PARIS (FULLKOM) | J47: =IFERROR(VLOOKUP(I47,Map!$F$18:$G$56,2,0),"Add in Map") -> 3P | K47: =VLOOKUP(L47,Map!$C$18:$D$29,2,0) -> PNT | L47: Audio | M47: 363901.48 | N47: =IF(L47="TOTAL",(M47*0.19),0) -> 0 | O47: =M47*1.19 -> 433042.77 | P47: =M47/S47 -> 393.83277 | Q47: =IF(L47="TOTAL",(P47*0.19),0) -> 0 | R47: =P47*1.19 -> 468.661 | S47: =INDEX(FX!$D$3:$O$19,MATCH(B47,FX!$B$3:$B$32,0),MATCH(D47,FX!$D$2:$O$2,0)) -> 924 | T47: Commission (2da Quincena) | U47: Provision (Based on PO, One View) | V47: Invoice | W47: =VLOOKUP(I47,Map!$F$18:$H$51,3,0) -> Variable | X47: Pending | Y47: =VLOOKUP(L47,Map!$C$18:$D$29,2,0) -> PNT | AA47: =IF(Y47="TOTAL",(Z47*0.19),0) -> 0 | AB47: =Z47*1.19 -> 0 | AC47: =Z47/S47 -> 0 | AD47: =IF(Y47="TOTAL",(AC47*0.19),0) -> 0 | AE47: =AC47*1.19 -> 0
B48: 2026 | C48: Jul16 to Jul31 | D48: JUL | E48: JUL (Provision) | F48: Pending | I48: PARIS (FULLKOM) | J48: =IFERROR(VLOOKUP(I48,Map!$F$18:$G$56,2,0),"Add in Map") -> 3P | K48: =VLOOKUP(L48,Map!$C$18:$D$29,2,0) -> GTT | L48: Monitor | M48: 207943.7 | N48: =IF(L48="TOTAL",(M48*0.19),0) -> 0 | O48: =M48*1.19 -> 247453.01 | P48: =M48/S48 -> 225.0473 | Q48: =IF(L48="TOTAL",(P48*0.19),0) -> 0 | R48: =P48*1.19 -> 267.80629 | S48: =INDEX(FX!$D$3:$O$19,MATCH(B48,FX!$B$3:$B$32,0),MATCH(D48,FX!$D$2:$O$2,0)) -> 924 | T48: Commission (2da Quincena) | U48: Provision (Based on PO, One View) | V48: Invoice | W48: =VLOOKUP(I48,Map!$F$18:$H$51,3,0) -> Variable | X48: Pending | Y48: =VLOOKUP(L48,Map!$C$18:$D$29,2,0) -> GTT | AA48: =IF(Y48="TOTAL",(Z48*0.19),0) -> 0 | AB48: =Z48*1.19 -> 0 | AC48: =Z48/S48 -> 0 | AD48: =IF(Y48="TOTAL",(AC48*0.19),0) -> 0 | AE48: =AC48*1.19 -> 0
B49: 2026 | C49: Jul16 to Jul31 | D49: JUL | E49: JUL (Provision) | F49: Pending | I49: PARIS (FULLKOM) | J49: =IFERROR(VLOOKUP(I49,Map!$F$18:$G$56,2,0),"Add in Map") -> 3P | K49: =VLOOKUP(L49,Map!$C$18:$D$29,2,0) -> DGT | L49: RAC | M49: 155957.78 | N49: =IF(L49="TOTAL",(M49*0.19),0) -> 0 | O49: =M49*1.19 -> 185589.76 | P49: =M49/S49 -> 168.78547 | Q49: =IF(L49="TOTAL",(P49*0.19),0) -> 0 | R49: =P49*1.19 -> 200.85471 | S49: =INDEX(FX!$D$3:$O$19,MATCH(B49,FX!$B$3:$B$32,0),MATCH(D49,FX!$D$2:$O$2,0)) -> 924 | T49: Commission (2da Quincena) | U49: Provision (Based on PO, One View) | V49: Invoice | W49: =VLOOKUP(I49,Map!$F$18:$H$51,3,0) -> Variable | X49: Pending | Y49: =VLOOKUP(L49,Map!$C$18:$D$29,2,0) -> DGT | AA49: =IF(Y49="TOTAL",(Z49*0.19),0) -> 0 | AB49: =Z49*1.19 -> 0 | AC49: =Z49/S49 -> 0 | AD49: =IF(Y49="TOTAL",(AC49*0.19),0) -> 0 | AE49: =AC49*1.19 -> 0
B50: 2026 | C50: Jul16 to Jul31 | D50: JUL | E50: JUL (Provision) | F50: Pending | I50: PARIS (FULLKOM) | J50: =IFERROR(VLOOKUP(I50,Map!$F$18:$G$56,2,0),"Add in Map") -> 3P | K50: =VLOOKUP(L50,Map!$C$18:$D$29,2,0) -> DLT | L50: Air Cleaner | M50: 51985.926 | N50: =IF(L50="TOTAL",(M50*0.19),0) -> 0 | O50: =M50*1.19 -> 61863.252 | P50: =M50/S50 -> 56.261825 | Q50: =IF(L50="TOTAL",(P50*0.19),0) -> 0 | R50: =P50*1.19 -> 66.951572 | S50: =INDEX(FX!$D$3:$O$19,MATCH(B50,FX!$B$3:$B$32,0),MATCH(D50,FX!$D$2:$O$2,0)) -> 924 | T50: Commission (2da Quincena) | U50: Provision (Based on PO, One View) | V50: Invoice | W50: =VLOOKUP(I50,Map!$F$18:$H$51,3,0) -> Variable | X50: Pending | Y50: =VLOOKUP(L50,Map!$C$18:$D$29,2,0) -> DLT | AA50: =IF(Y50="TOTAL",(Z50*0.19),0) -> 0 | AB50: =Z50*1.19 -> 0 | AC50: =Z50/S50 -> 0 | AD50: =IF(Y50="TOTAL",(AC50*0.19),0) -> 0 | AE50: =AC50*1.19 -> 0
B51: 2026 | C51: Jul16 to Jul31 | D51: JUL | E51: JUL (Provision) | F51: Pending | I51: PARIS (FULLKOM) | J51: =IFERROR(VLOOKUP(I51,Map!$F$18:$G$56,2,0),"Add in Map") -> 3P | K51: =VLOOKUP(L51,Map!$C$18:$D$29,2,0) -> DMT | L51: SAC | M51: 0 | N51: =IF(L51="TOTAL",(M51*0.19),0) -> 0 | O51: =M51*1.19 -> 0 | P51: =M51/S51 -> 0 | Q51: =IF(L51="TOTAL",(P51*0.19),0) -> 0 | R51: =P51*1.19 -> 0 | S51: =INDEX(FX!$D$3:$O$19,MATCH(B51,FX!$B$3:$B$32,0),MATCH(D51,FX!$D$2:$O$2,0)) -> 924 | T51: Commission (2da Quincena) | U51: Provision (Based on PO, One View) | V51: Invoice | W51: =VLOOKUP(I51,Map!$F$18:$H$51,3,0) -> Variable | X51: Pending | Y51: =VLOOKUP(L51,Map!$C$18:$D$29,2,0) -> DMT | AA51: =IF(Y51="TOTAL",(Z51*0.19),0) -> 0 | AB51: =Z51*1.19 -> 0 | AC51: =Z51/S51 -> 0 | AD51: =IF(Y51="TOTAL",(AC51*0.19),0) -> 0 | AE51: =AC51*1.19 -> 0
B52: 2026 | C52: Jul16 to Jul31 | D52: JUL | E52: JUL (Provision) | F52: Pending | I52: PARIS (FULLKOM) | J52: =IFERROR(VLOOKUP(I52,Map!$F$18:$G$56,2,0),"Add in Map") -> 3P | K52: =VLOOKUP(L52,Map!$C$18:$D$29,2,0) -> TOTAL | L52: TOTAL | M52: =SUM(M41:M51) -> 16791454 | N52: =IF(L52="TOTAL",(M52*0.19),0) -> 3190376.3 | O52: =M52*1.19 -> 19981830 | P52: =M52/S52 -> 18172.569 | Q52: =IF(L52="TOTAL",(P52*0.19),0) -> 3452.7882 | R52: =P52*1.19 -> 21625.358 | S52: =INDEX(FX!$D$3:$O$19,MATCH(B52,FX!$B$3:$B$32,0),MATCH(D52,FX!$D$2:$O$2,0)) -> 924 | T52: Commission (2da Quincena) | U52: Provision (Based on PO, One View) | V52: Invoice | W52: =VLOOKUP(I52,Map!$F$18:$H$51,3,0) -> Variable | X52: Pending | Y52: =VLOOKUP(L52,Map!$C$18:$D$29,2,0) -> TOTAL | AA52: =IF(Y52="TOTAL",(Z52*0.19),0) -> 0 | AB52: =Z52*1.19 -> 0 | AC52: =Z52/S52 -> 0 | AD52: =IF(Y52="TOTAL",(AC52*0.19),0) -> 0 | AE52: =AC52*1.19 -> 0
B53: 2026 | C53: 2026 Mar | D53: JUL | E53: JUL (Provision) | F53: Pending | I53: PARIS (FULLKOM) | J53: =IFERROR(VLOOKUP(I53,Map!$F$18:$G$56,2,0),"Add in Map") -> 3P | K53: =VLOOKUP(L53,Map!$C$18:$D$29,2,0) -> CNT | L53: Refrigeration | M53: 5510370.3 | N53: =IF(L53="TOTAL",(M53*0.19),0) -> 0 | O53: =M53*1.19 -> 6557340.7 | P53: =M53/S53 -> 5963.6042 | Q53: =IF(L53="TOTAL",(P53*0.19),0) -> 0 | R53: =P53*1.19 -> 7096.689 | S53: =INDEX(FX!$D$3:$O$19,MATCH(B53,FX!$B$3:$B$32,0),MATCH(D53,FX!$D$2:$O$2,0)) -> 924 | T53: Logistic Cost | U53: Provision (Based on External Report) | V53: Invoice | W53: =VLOOKUP(I53,Map!$F$18:$H$51,3,0) -> Variable | X53: Pending | Y53: =VLOOKUP(L53,Map!$C$18:$D$29,2,0) -> CNT | AA53: =IF(Y53="TOTAL",(Z53*0.19),0) -> 0 | AB53: =Z53*1.19 -> 0 | AC53: =Z53/S53 -> 0 | AD53: =IF(Y53="TOTAL",(AC53*0.19),0) -> 0 | AE53: =AC53*1.19 -> 0
B54: 2026 | C54: 2026 Mar | D54: JUL | E54: JUL (Provision) | F54: Pending | I54: PARIS (FULLKOM) | J54: =IFERROR(VLOOKUP(I54,Map!$F$18:$G$56,2,0),"Add in Map") -> 3P | K54: =VLOOKUP(L54,Map!$C$18:$D$29,2,0) -> CVT | L54: Cooking | M54: 0 | N54: =IF(L54="TOTAL",(M54*0.19),0) -> 0 | O54: =M54*1.19 -> 0 | P54: =M54/S54 -> 0 | Q54: =IF(L54="TOTAL",(P54*0.19),0) -> 0 | R54: =P54*1.19 -> 0 | S54: =INDEX(FX!$D$3:$O$19,MATCH(B54,FX!$B$3:$B$32,0),MATCH(D54,FX!$D$2:$O$2,0)) -> 924 | T54: Logistic Cost | U54: Provision (Based on External Report) | V54: Invoice | W54: =VLOOKUP(I54,Map!$F$18:$H$51,3,0) -> Variable | X54: Pending | Y54: =VLOOKUP(L54,Map!$C$18:$D$29,2,0) -> CVT | AA54: =IF(Y54="TOTAL",(Z54*0.19),0) -> 0 | AB54: =Z54*1.19 -> 0 | AC54: =Z54/S54 -> 0 | AD54: =IF(Y54="TOTAL",(AC54*0.19),0) -> 0 | AE54: =AC54*1.19 -> 0
B55: 2026 | C55: 2026 Mar | D55: JUL | E55: JUL (Provision) | F55: Pending | I55: PARIS (FULLKOM) | J55: =IFERROR(VLOOKUP(I55,Map!$F$18:$G$56,2,0),"Add in Map") -> 3P | K55: =VLOOKUP(L55,Map!$C$18:$D$29,2,0) -> CDT | L55: Dishwasher | M55: 70645.773 | N55: =IF(L55="TOTAL",(M55*0.19),0) -> 0 | O55: =M55*1.19 -> 84068.47 | P55: =M55/S55 -> 76.456464 | Q55: =IF(L55="TOTAL",(P55*0.19),0) -> 0 | R55: =P55*1.19 -> 90.983193 | S55: =INDEX(FX!$D$3:$O$19,MATCH(B55,FX!$B$3:$B$32,0),MATCH(D55,FX!$D$2:$O$2,0)) -> 924 | T55: Logistic Cost | U55: Provision (Based on External Report) | V55: Invoice | W55: =VLOOKUP(I55,Map!$F$18:$H$51,3,0) -> Variable | X55: Pending | Y55: =VLOOKUP(L55,Map!$C$18:$D$29,2,0) -> CDT | AA55: =IF(Y55="TOTAL",(Z55*0.19),0) -> 0 | AB55: =Z55*1.19 -> 0 | AC55: =Z55/S55 -> 0 | AD55: =IF(Y55="TOTAL",(AC55*0.19),0) -> 0 | AE55: =AC55*1.19 -> 0
B56: 2026 | C56: 2026 Mar | D56: JUL | E56: JUL (Provision) | F56: Pending | I56: PARIS (FULLKOM) | J56: =IFERROR(VLOOKUP(I56,Map!$F$18:$G$56,2,0),"Add in Map") -> 3P | K56: =VLOOKUP(L56,Map!$C$18:$D$29,2,0) -> DFT | L56: WM | M56: 13281405 | N56: =IF(L56="TOTAL",(M56*0.19),0) -> 0 | O56: =M56*1.19 -> 15804872 | P56: =M56/S56 -> 14373.815 | Q56: =IF(L56="TOTAL",(P56*0.19),0) -> 0 | R56: =P56*1.19 -> 17104.84 | S56: =INDEX(FX!$D$3:$O$19,MATCH(B56,FX!$B$3:$B$32,0),MATCH(D56,FX!$D$2:$O$2,0)) -> 924 | T56: Logistic Cost | U56: Provision (Based on External Report) | V56: Invoice | W56: =VLOOKUP(I56,Map!$F$18:$H$51,3,0) -> Variable | X56: Pending | Y56: =VLOOKUP(L56,Map!$C$18:$D$29,2,0) -> DFT | AA56: =IF(Y56="TOTAL",(Z56*0.19),0) -> 0 | AB56: =Z56*1.19 -> 0 | AC56: =Z56/S56 -> 0 | AD56: =IF(Y56="TOTAL",(AC56*0.19),0) -> 0 | AE56: =AC56*1.19 -> 0
B57: 2026 | C57: 2026 Mar | D57: JUL | E57: JUL (Provision) | F57: Pending | I57: PARIS (FULLKOM) | J57: =IFERROR(VLOOKUP(I57,Map!$F$18:$G$56,2,0),"Add in Map") -> 3P | K57: =VLOOKUP(L57,Map!$C$18:$D$29,2,0) -> DVT | L57: VCC | M57: 0 | N57: =IF(L57="TOTAL",(M57*0.19),0) -> 0 | O57: =M57*1.19 -> 0 | P57: =M57/S57 -> 0 | Q57: =IF(L57="TOTAL",(P57*0.19),0) -> 0 | R57: =P57*1.19 -> 0 | S57: =INDEX(FX!$D$3:$O$19,MATCH(B57,FX!$B$3:$B$32,0),MATCH(D57,FX!$D$2:$O$2,0)) -> 924 | T57: Logistic Cost | U57: Provision (Based on External Report) | V57: Invoice | W57: =VLOOKUP(I57,Map!$F$18:$H$51,3,0) -> Variable | X57: Pending | Y57: =VLOOKUP(L57,Map!$C$18:$D$29,2,0) -> DVT | AA57: =IF(Y57="TOTAL",(Z57*0.19),0) -> 0 | AB57: =Z57*1.19 -> 0 | AC57: =Z57/S57 -> 0 | AD57: =IF(Y57="TOTAL",(AC57*0.19),0) -> 0 | AE57: =AC57*1.19 -> 0
B58: 2026 | C58: 2026 Mar | D58: JUL | E58: JUL (Provision) | F58: Pending | I58: PARIS (FULLKOM) | J58: =IFERROR(VLOOKUP(I58,Map!$F$18:$G$56,2,0),"Add in Map") -> 3P | K58: =VLOOKUP(L58,Map!$C$18:$D$29,2,0) -> GLT | L58: Television | M58: 2896476.7 | N58: =IF(L58="TOTAL",(M58*0.19),0) -> 0 | O58: =M58*1.19 -> 3446807.3 | P58: =M58/S58 -> 3134.715 | Q58: =IF(L58="TOTAL",(P58*0.19),0) -> 0 | R58: =P58*1.19 -> 3730.3109 | S58: =INDEX(FX!$D$3:$O$19,MATCH(B58,FX!$B$3:$B$32,0),MATCH(D58,FX!$D$2:$O$2,0)) -> 924 | T58: Logistic Cost | U58: Provision (Based on External Report) | V58: Invoice | W58: =VLOOKUP(I58,Map!$F$18:$H$51,3,0) -> Variable | X58: Pending | Y58: =VLOOKUP(L58,Map!$C$18:$D$29,2,0) -> GLT | AA58: =IF(Y58="TOTAL",(Z58*0.19),0) -> 0 | AB58: =Z58*1.19 -> 0 | AC58: =Z58/S58 -> 0 | AD58: =IF(Y58="TOTAL",(AC58*0.19),0) -> 0 | AE58: =AC58*1.19 -> 0
B59: 2026 | C59: 2026 Mar | D59: JUL | E59: JUL (Provision) | F59: Pending | I59: PARIS (FULLKOM) | J59: =IFERROR(VLOOKUP(I59,Map!$F$18:$G$56,2,0),"Add in Map") -> 3P | K59: =VLOOKUP(L59,Map!$C$18:$D$29,2,0) -> PNT | L59: Audio | M59: 494520.41 | N59: =IF(L59="TOTAL",(M59*0.19),0) -> 0 | O59: =M59*1.19 -> 588479.29 | P59: =M59/S59 -> 535.19525 | Q59: =IF(L59="TOTAL",(P59*0.19),0) -> 0 | R59: =P59*1.19 -> 636.88235 | S59: =INDEX(FX!$D$3:$O$19,MATCH(B59,FX!$B$3:$B$32,0),MATCH(D59,FX!$D$2:$O$2,0)) -> 924 | T59: Logistic Cost | U59: Provision (Based on External Report) | V59: Invoice | W59: =VLOOKUP(I59,Map!$F$18:$H$51,3,0) -> Variable | X59: Pending | Y59: =VLOOKUP(L59,Map!$C$18:$D$29,2,0) -> PNT | AA59: =IF(Y59="TOTAL",(Z59*0.19),0) -> 0 | AB59: =Z59*1.19 -> 0 | AC59: =Z59/S59 -> 0 | AD59: =IF(Y59="TOTAL",(AC59*0.19),0) -> 0 | AE59: =AC59*1.19 -> 0
B60: 2026 | C60: 2026 Mar | D60: JUL | E60: JUL (Provision) | F60: Pending | I60: PARIS (FULLKOM) | J60: =IFERROR(VLOOKUP(I60,Map!$F$18:$G$56,2,0),"Add in Map") -> 3P | K60: =VLOOKUP(L60,Map!$C$18:$D$29,2,0) -> GTT | L60: Monitor | M60: 282583.09 | N60: =IF(L60="TOTAL",(M60*0.19),0) -> 0 | O60: =M60*1.19 -> 336273.88 | P60: =M60/S60 -> 305.82586 | Q60: =IF(L60="TOTAL",(P60*0.19),0) -> 0 | R60: =P60*1.19 -> 363.93277 | S60: =INDEX(FX!$D$3:$O$19,MATCH(B60,FX!$B$3:$B$32,0),MATCH(D60,FX!$D$2:$O$2,0)) -> 924 | T60: Logistic Cost | U60: Provision (Based on External Report) | V60: Invoice | W60: =VLOOKUP(I60,Map!$F$18:$H$51,3,0) -> Variable | X60: Pending | Y60: =VLOOKUP(L60,Map!$C$18:$D$29,2,0) -> GTT | AA60: =IF(Y60="TOTAL",(Z60*0.19),0) -> 0 | AB60: =Z60*1.19 -> 0 | AC60: =Z60/S60 -> 0 | AD60: =IF(Y60="TOTAL",(AC60*0.19),0) -> 0 | AE60: =AC60*1.19 -> 0
B61: 2026 | C61: 2026 Mar | D61: JUL | E61: JUL (Provision) | F61: Pending | I61: PARIS (FULLKOM) | J61: =IFERROR(VLOOKUP(I61,Map!$F$18:$G$56,2,0),"Add in Map") -> 3P | K61: =VLOOKUP(L61,Map!$C$18:$D$29,2,0) -> DGT | L61: RAC | M61: 211937.32 | N61: =IF(L61="TOTAL",(M61*0.19),0) -> 0 | O61: =M61*1.19 -> 252205.41 | P61: =M61/S61 -> 229.36939 | Q61: =IF(L61="TOTAL",(P61*0.19),0) -> 0 | R61: =P61*1.19 -> 272.94958 | S61: =INDEX(FX!$D$3:$O$19,MATCH(B61,FX!$B$3:$B$32,0),MATCH(D61,FX!$D$2:$O$2,0)) -> 924 | T61: Logistic Cost | U61: Provision (Based on External Report) | V61: Invoice | W61: =VLOOKUP(I61,Map!$F$18:$H$51,3,0) -> Variable | X61: Pending | Y61: =VLOOKUP(L61,Map!$C$18:$D$29,2,0) -> DGT | AA61: =IF(Y61="TOTAL",(Z61*0.19),0) -> 0 | AB61: =Z61*1.19 -> 0 | AC61: =Z61/S61 -> 0 | AD61: =IF(Y61="TOTAL",(AC61*0.19),0) -> 0 | AE61: =AC61*1.19 -> 0
B62: 2026 | C62: 2026 Mar | D62: JUL | E62: JUL (Provision) | F62: Pending | I62: PARIS (FULLKOM) | J62: =IFERROR(VLOOKUP(I62,Map!$F$18:$G$56,2,0),"Add in Map") -> 3P | K62: =VLOOKUP(L62,Map!$C$18:$D$29,2,0) -> DLT | L62: Air Cleaner | M62: 70645.773 | N62: =IF(L62="TOTAL",(M62*0.19),0) -> 0 | O62: =M62*1.19 -> 84068.47 | P62: =M62/S62 -> 76.456464 | Q62: =IF(L62="TOTAL",(P62*0.19),0) -> 0 | R62: =P62*1.19 -> 90.983193 | S62: =INDEX(FX!$D$3:$O$19,MATCH(B62,FX!$B$3:$B$32,0),MATCH(D62,FX!$D$2:$O$2,0)) -> 924 | T62: Logistic Cost | U62: Provision (Based on External Report) | V62: Invoice | W62: =VLOOKUP(I62,Map!$F$18:$H$51,3,0) -> Variable | X62: Pending | Y62: =VLOOKUP(L62,Map!$C$18:$D$29,2,0) -> DLT | AA62: =IF(Y62="TOTAL",(Z62*0.19),0) -> 0 | AB62: =Z62*1.19 -> 0 | AC62: =Z62/S62 -> 0 | AD62: =IF(Y62="TOTAL",(AC62*0.19),0) -> 0 | AE62: =AC62*1.19 -> 0
B63: 2026 | C63: 2026 Mar | D63: JUL | E63: JUL (Provision) | F63: Pending | I63: PARIS (FULLKOM) | J63: =IFERROR(VLOOKUP(I63,Map!$F$18:$G$56,2,0),"Add in Map") -> 3P | K63: =VLOOKUP(L63,Map!$C$18:$D$29,2,0) -> DMT | L63: SAC | M63: 0 | N63: =IF(L63="TOTAL",(M63*0.19),0) -> 0 | O63: =M63*1.19 -> 0 | P63: =M63/S63 -> 0 | Q63: =IF(L63="TOTAL",(P63*0.19),0) -> 0 | R63: =P63*1.19 -> 0 | S63: =INDEX(FX!$D$3:$O$19,MATCH(B63,FX!$B$3:$B$32,0),MATCH(D63,FX!$D$2:$O$2,0)) -> 924 | T63: Logistic Cost | U63: Provision (Based on External Report) | V63: Invoice | W63: =VLOOKUP(I63,Map!$F$18:$H$51,3,0) -> Variable | X63: Pending | Y63: =VLOOKUP(L63,Map!$C$18:$D$29,2,0) -> DMT | AA63: =IF(Y63="TOTAL",(Z63*0.19),0) -> 0 | AB63: =Z63*1.19 -> 0 | AC63: =Z63/S63 -> 0 | AD63: =IF(Y63="TOTAL",(AC63*0.19),0) -> 0 | AE63: =AC63*1.19 -> 0
B64: 2026 | C64: 2026 Mar | D64: JUL | E64: JUL (Provision) | F64: Pending | I64: PARIS (FULLKOM) | J64: =IFERROR(VLOOKUP(I64,Map!$F$18:$G$56,2,0),"Add in Map") -> 3P | K64: =VLOOKUP(L64,Map!$C$18:$D$29,2,0) -> TOTAL | L64: TOTAL | M64: =SUM(M53:M63) -> 22818585 | N64: =IF(L64="TOTAL",(M64*0.19),0) -> 4335531.1 | O64: =M64*1.19 -> 27154116 | P64: =M64/S64 -> 24695.438 | Q64: =IF(L64="TOTAL",(P64*0.19),0) -> 4692.1332 | R64: =P64*1.19 -> 29387.571 | S64: =INDEX(FX!$D$3:$O$19,MATCH(B64,FX!$B$3:$B$32,0),MATCH(D64,FX!$D$2:$O$2,0)) -> 924 | T64: Logistic Cost | U64: Provision (Based on External Report) | V64: Invoice | W64: =VLOOKUP(I64,Map!$F$18:$H$51,3,0) -> Variable | X64: Pending | Y64: =VLOOKUP(L64,Map!$C$18:$D$29,2,0) -> TOTAL | AA64: =IF(Y64="TOTAL",(Z64*0.19),0) -> 0 | AB64: =Z64*1.19 -> 0 | AC64: =Z64/S64 -> 0 | AD64: =IF(Y64="TOTAL",(AC64*0.19),0) -> 0 | AE64: =AC64*1.19 -> 0
B65: 2026 | C65: 2026 Apr | D65: JUL | E65: JUL (Provision) | F65: Pending | I65: PARIS (FULLKOM) | J65: =IFERROR(VLOOKUP(I65,Map!$F$18:$G$56,2,0),"Add in Map") -> 3P | K65: =VLOOKUP(L65,Map!$C$18:$D$29,2,0) -> CNT | L65: Refrigeration | M65: 2753819.5 | N65: =IF(L65="TOTAL",(M65*0.19),0) -> 0 | O65: =M65*1.19 -> 3277045.2 | P65: =M65/S65 -> 2980.3241 | Q65: =IF(L65="TOTAL",(P65*0.19),0) -> 0 | R65: =P65*1.19 -> 3546.5857 | S65: =INDEX(FX!$D$3:$O$19,MATCH(B65,FX!$B$3:$B$32,0),MATCH(D65,FX!$D$2:$O$2,0)) -> 924 | T65: Logistic Cost | U65: Provision (Based on External Report) | V65: Invoice | W65: =VLOOKUP(I65,Map!$F$18:$H$51,3,0) -> Variable | X65: Pending | Y65: =VLOOKUP(L65,Map!$C$18:$D$29,2,0) -> CNT | AA65: =IF(Y65="TOTAL",(Z65*0.19),0) -> 0 | AB65: =Z65*1.19 -> 0 | AC65: =Z65/S65 -> 0 | AD65: =IF(Y65="TOTAL",(AC65*0.19),0) -> 0 | AE65: =AC65*1.19 -> 0
B66: 2026 | C66: 2026 Apr | D66: JUL | E66: JUL (Provision) | F66: Pending | I66: PARIS (FULLKOM) | J66: =IFERROR(VLOOKUP(I66,Map!$F$18:$G$56,2,0),"Add in Map") -> 3P | K66: =VLOOKUP(L66,Map!$C$18:$D$29,2,0) -> CVT | L66: Cooking | M66: 0 | N66: =IF(L66="TOTAL",(M66*0.19),0) -> 0 | O66: =M66*1.19 -> 0 | P66: =M66/S66 -> 0 | Q66: =IF(L66="TOTAL",(P66*0.19),0) -> 0 | R66: =P66*1.19 -> 0 | S66: =INDEX(FX!$D$3:$O$19,MATCH(B66,FX!$B$3:$B$32,0),MATCH(D66,FX!$D$2:$O$2,0)) -> 924 | T66: Logistic Cost | U66: Provision (Based on External Report) | V66: Invoice | W66: =VLOOKUP(I66,Map!$F$18:$H$51,3,0) -> Variable | X66: Pending | Y66: =VLOOKUP(L66,Map!$C$18:$D$29,2,0) -> CVT | AA66: =IF(Y66="TOTAL",(Z66*0.19),0) -> 0 | AB66: =Z66*1.19 -> 0 | AC66: =Z66/S66 -> 0 | AD66: =IF(Y66="TOTAL",(AC66*0.19),0) -> 0 | AE66: =AC66*1.19 -> 0
B67: 2026 | C67: 2026 Apr | D67: JUL | E67: JUL (Provision) | F67: Pending | I67: PARIS (FULLKOM) | J67: =IFERROR(VLOOKUP(I67,Map!$F$18:$G$56,2,0),"Add in Map") -> 3P | K67: =VLOOKUP(L67,Map!$C$18:$D$29,2,0) -> CDT | L67: Dishwasher | M67: 35305.378 | N67: =IF(L67="TOTAL",(M67*0.19),0) -> 0 | O67: =M67*1.19 -> 42013.399 | P67: =M67/S67 -> 38.209283 | Q67: =IF(L67="TOTAL",(P67*0.19),0) -> 0 | R67: =P67*1.19 -> 45.469047 | S67: =INDEX(FX!$D$3:$O$19,MATCH(B67,FX!$B$3:$B$32,0),MATCH(D67,FX!$D$2:$O$2,0)) -> 924 | T67: Logistic Cost | U67: Provision (Based on External Report) | V67: Invoice | W67: =VLOOKUP(I67,Map!$F$18:$H$51,3,0) -> Variable | X67: Pending | Y67: =VLOOKUP(L67,Map!$C$18:$D$29,2,0) -> CDT | AA67: =IF(Y67="TOTAL",(Z67*0.19),0) -> 0 | AB67: =Z67*1.19 -> 0 | AC67: =Z67/S67 -> 0 | AD67: =IF(Y67="TOTAL",(AC67*0.19),0) -> 0 | AE67: =AC67*1.19 -> 0
B68: 2026 | C68: 2026 Apr | D68: JUL | E68: JUL (Provision) | F68: Pending | I68: PARIS (FULLKOM) | J68: =IFERROR(VLOOKUP(I68,Map!$F$18:$G$56,2,0),"Add in Map") -> 3P | K68: =VLOOKUP(L68,Map!$C$18:$D$29,2,0) -> DFT | L68: WM | M68: 6637411 | N68: =IF(L68="TOTAL",(M68*0.19),0) -> 0 | O68: =M68*1.19 -> 7898519.1 | P68: =M68/S68 -> 7183.3452 | Q68: =IF(L68="TOTAL",(P68*0.19),0) -> 0 | R68: =P68*1.19 -> 8548.1808 | S68: =INDEX(FX!$D$3:$O$19,MATCH(B68,FX!$B$3:$B$32,0),MATCH(D68,FX!$D$2:$O$2,0)) -> 924 | T68: Logistic Cost | U68: Provision (Based on External Report) | V68: Invoice | W68: =VLOOKUP(I68,Map!$F$18:$H$51,3,0) -> Variable | X68: Pending | Y68: =VLOOKUP(L68,Map!$C$18:$D$29,2,0) -> DFT | AA68: =IF(Y68="TOTAL",(Z68*0.19),0) -> 0 | AB68: =Z68*1.19 -> 0 | AC68: =Z68/S68 -> 0 | AD68: =IF(Y68="TOTAL",(AC68*0.19),0) -> 0 | AE68: =AC68*1.19 -> 0
B69: 2026 | C69: 2026 Apr | D69: JUL | E69: JUL (Provision) | F69: Pending | I69: PARIS (FULLKOM) | J69: =IFERROR(VLOOKUP(I69,Map!$F$18:$G$56,2,0),"Add in Map") -> 3P | K69: =VLOOKUP(L69,Map!$C$18:$D$29,2,0) -> DVT | L69: VCC | M69: 0 | N69: =IF(L69="TOTAL",(M69*0.19),0) -> 0 | O69: =M69*1.19 -> 0 | P69: =M69/S69 -> 0 | Q69: =IF(L69="TOTAL",(P69*0.19),0) -> 0 | R69: =P69*1.19 -> 0 | S69: =INDEX(FX!$D$3:$O$19,MATCH(B69,FX!$B$3:$B$32,0),MATCH(D69,FX!$D$2:$O$2,0)) -> 924 | T69: Logistic Cost | U69: Provision (Based on External Report) | V69: Invoice | W69: =VLOOKUP(I69,Map!$F$18:$H$51,3,0) -> Variable | X69: Pending | Y69: =VLOOKUP(L69,Map!$C$18:$D$29,2,0) -> DVT | AA69: =IF(Y69="TOTAL",(Z69*0.19),0) -> 0 | AB69: =Z69*1.19 -> 0 | AC69: =Z69/S69 -> 0 | AD69: =IF(Y69="TOTAL",(AC69*0.19),0) -> 0 | AE69: =AC69*1.19 -> 0
B70: 2026 | C70: 2026 Apr | D70: JUL | E70: JUL (Provision) | F70: Pending | I70: PARIS (FULLKOM) | J70: =IFERROR(VLOOKUP(I70,Map!$F$18:$G$56,2,0),"Add in Map") -> 3P | K70: =VLOOKUP(L70,Map!$C$18:$D$29,2,0) -> GLT | L70: Television | M70: 1447520.5 | N70: =IF(L70="TOTAL",(M70*0.19),0) -> 0 | O70: =M70*1.19 -> 1722549.4 | P70: =M70/S70 -> 1566.5806 | Q70: =IF(L70="TOTAL",(P70*0.19),0) -> 0 | R70: =P70*1.19 -> 1864.2309 | S70: =INDEX(FX!$D$3:$O$19,MATCH(B70,FX!$B$3:$B$32,0),MATCH(D70,FX!$D$2:$O$2,0)) -> 924 | T70: Logistic Cost | U70: Provision (Based on External Report) | V70: Invoice | W70: =VLOOKUP(I70,Map!$F$18:$H$51,3,0) -> Variable | X70: Pending | Y70: =VLOOKUP(L70,Map!$C$18:$D$29,2,0) -> GLT | AA70: =IF(Y70="TOTAL",(Z70*0.19),0) -> 0 | AB70: =Z70*1.19 -> 0 | AC70: =Z70/S70 -> 0 | AD70: =IF(Y70="TOTAL",(AC70*0.19),0) -> 0 | AE70: =AC70*1.19 -> 0
B71: 2026 | C71: 2026 Apr | D71: JUL | E71: JUL (Provision) | F71: Pending | I71: PARIS (FULLKOM) | J71: =IFERROR(VLOOKUP(I71,Map!$F$18:$G$56,2,0),"Add in Map") -> 3P | K71: =VLOOKUP(L71,Map!$C$18:$D$29,2,0) -> PNT | L71: Audio | M71: 247137.64 | N71: =IF(L71="TOTAL",(M71*0.19),0) -> 0 | O71: =M71*1.19 -> 294093.8 | P71: =M71/S71 -> 267.46498 | Q71: =IF(L71="TOTAL",(P71*0.19),0) -> 0 | R71: =P71*1.19 -> 318.28333 | S71: =INDEX(FX!$D$3:$O$19,MATCH(B71,FX!$B$3:$B$32,0),MATCH(D71,FX!$D$2:$O$2,0)) -> 924 | T71: Logistic Cost | U71: Provision (Based on External Report) | V71: Invoice | W71: =VLOOKUP(I71,Map!$F$18:$H$51,3,0) -> Variable | X71: Pending | Y71: =VLOOKUP(L71,Map!$C$18:$D$29,2,0) -> PNT | AA71: =IF(Y71="TOTAL",(Z71*0.19),0) -> 0 | AB71: =Z71*1.19 -> 0 | AC71: =Z71/S71 -> 0 | AD71: =IF(Y71="TOTAL",(AC71*0.19),0) -> 0 | AE71: =AC71*1.19 -> 0
B72: 2026 | C72: 2026 Apr | D72: JUL | E72: JUL (Provision) | F72: Pending | I72: PARIS (FULLKOM) | J72: =IFERROR(VLOOKUP(I72,Map!$F$18:$G$56,2,0),"Add in Map") -> 3P | K72: =VLOOKUP(L72,Map!$C$18:$D$29,2,0) -> GTT | L72: Monitor | M72: 141221.51 | N72: =IF(L72="TOTAL",(M72*0.19),0) -> 0 | O72: =M72*1.19 -> 168053.6 | P72: =M72/S72 -> 152.83713 | Q72: =IF(L72="TOTAL",(P72*0.19),0) -> 0 | R72: =P72*1.19 -> 181.87619 | S72: =INDEX(FX!$D$3:$O$19,MATCH(B72,FX!$B$3:$B$32,0),MATCH(D72,FX!$D$2:$O$2,0)) -> 924 | T72: Logistic Cost | U72: Provision (Based on External Report) | V72: Invoice | W72: =VLOOKUP(I72,Map!$F$18:$H$51,3,0) -> Variable | X72: Pending | Y72: =VLOOKUP(L72,Map!$C$18:$D$29,2,0) -> GTT | AA72: =IF(Y72="TOTAL",(Z72*0.19),0) -> 0 | AB72: =Z72*1.19 -> 0 | AC72: =Z72/S72 -> 0 | AD72: =IF(Y72="TOTAL",(AC72*0.19),0) -> 0 | AE72: =AC72*1.19 -> 0
B73: 2026 | C73: 2026 Apr | D73: JUL | E73: JUL (Provision) | F73: Pending | I73: PARIS (FULLKOM) | J73: =IFERROR(VLOOKUP(I73,Map!$F$18:$G$56,2,0),"Add in Map") -> 3P | K73: =VLOOKUP(L73,Map!$C$18:$D$29,2,0) -> DGT | L73: RAC | M73: 105916.13 | N73: =IF(L73="TOTAL",(M73*0.19),0) -> 0 | O73: =M73*1.19 -> 126040.2 | P73: =M73/S73 -> 114.62785 | Q73: =IF(L73="TOTAL",(P73*0.19),0) -> 0 | R73: =P73*1.19 -> 136.40714 | S73: =INDEX(FX!$D$3:$O$19,MATCH(B73,FX!$B$3:$B$32,0),MATCH(D73,FX!$D$2:$O$2,0)) -> 924 | T73: Logistic Cost | U73: Provision (Based on External Report) | V73: Invoice | W73: =VLOOKUP(I73,Map!$F$18:$H$51,3,0) -> Variable | X73: Pending | Y73: =VLOOKUP(L73,Map!$C$18:$D$29,2,0) -> DGT | AA73: =IF(Y73="TOTAL",(Z73*0.19),0) -> 0 | AB73: =Z73*1.19 -> 0 | AC73: =Z73/S73 -> 0 | AD73: =IF(Y73="TOTAL",(AC73*0.19),0) -> 0 | AE73: =AC73*1.19 -> 0
B74: 2026 | C74: 2026 Apr | D74: JUL | E74: JUL (Provision) | F74: Pending | I74: PARIS (FULLKOM) | J74: =IFERROR(VLOOKUP(I74,Map!$F$18:$G$56,2,0),"Add in Map") -> 3P | K74: =VLOOKUP(L74,Map!$C$18:$D$29,2,0) -> DLT | L74: Air Cleaner | M74: 35305.378 | N74: =IF(L74="TOTAL",(M74*0.19),0) -> 0 | O74: =M74*1.19 -> 42013.399 | P74: =M74/S74 -> 38.209283 | Q74: =IF(L74="TOTAL",(P74*0.19),0) -> 0 | R74: =P74*1.19 -> 45.469047 | S74: =INDEX(FX!$D$3:$O$19,MATCH(B74,FX!$B$3:$B$32,0),MATCH(D74,FX!$D$2:$O$2,0)) -> 924 | T74: Logistic Cost | U74: Provision (Based on External Report) | V74: Invoice | W74: =VLOOKUP(I74,Map!$F$18:$H$51,3,0) -> Variable | X74: Pending | Y74: =VLOOKUP(L74,Map!$C$18:$D$29,2,0) -> DLT | AA74: =IF(Y74="TOTAL",(Z74*0.19),0) -> 0 | AB74: =Z74*1.19 -> 0 | AC74: =Z74/S74 -> 0 | AD74: =IF(Y74="TOTAL",(AC74*0.19),0) -> 0 | AE74: =AC74*1.19 -> 0
B75: 2026 | C75: 2026 Apr | D75: JUL | E75: JUL (Provision) | F75: Pending | I75: PARIS (FULLKOM) | J75: =IFERROR(VLOOKUP(I75,Map!$F$18:$G$56,2,0),"Add in Map") -> 3P | K75: =VLOOKUP(L75,Map!$C$18:$D$29,2,0) -> DMT | L75: SAC | M75: 0 | N75: =IF(L75="TOTAL",(M75*0.19),0) -> 0 | O75: =M75*1.19 -> 0 | P75: =M75/S75 -> 0 | Q75: =IF(L75="TOTAL",(P75*0.19),0) -> 0 | R75: =P75*1.19 -> 0 | S75: =INDEX(FX!$D$3:$O$19,MATCH(B75,FX!$B$3:$B$32,0),MATCH(D75,FX!$D$2:$O$2,0)) -> 924 | T75: Logistic Cost | U75: Provision (Based on External Report) | V75: Invoice | W75: =VLOOKUP(I75,Map!$F$18:$H$51,3,0) -> Variable | X75: Pending | Y75: =VLOOKUP(L75,Map!$C$18:$D$29,2,0) -> DMT | AA75: =IF(Y75="TOTAL",(Z75*0.19),0) -> 0 | AB75: =Z75*1.19 -> 0 | AC75: =Z75/S75 -> 0 | AD75: =IF(Y75="TOTAL",(AC75*0.19),0) -> 0 | AE75: =AC75*1.19 -> 0
B76: 2026 | C76: 2026 Apr | D76: JUL | E76: JUL (Provision) | F76: Pending | I76: PARIS (FULLKOM) | J76: =IFERROR(VLOOKUP(I76,Map!$F$18:$G$56,2,0),"Add in Map") -> 3P | K76: =VLOOKUP(L76,Map!$C$18:$D$29,2,0) -> TOTAL | L76: TOTAL | M76: =SUM(M65:M75) -> 11403637 | N76: =IF(L76="TOTAL",(M76*0.19),0) -> 2166691 | O76: =M76*1.19 -> 13570328 | P76: =M76/S76 -> 12341.598 | Q76: =IF(L76="TOTAL",(P76*0.19),0) -> 2344.9037 | R76: =P76*1.19 -> 14686.502 | S76: =INDEX(FX!$D$3:$O$19,MATCH(B76,FX!$B$3:$B$32,0),MATCH(D76,FX!$D$2:$O$2,0)) -> 924 | T76: Logistic Cost | U76: Provision (Based on External Report) | V76: Invoice | W76: =VLOOKUP(I76,Map!$F$18:$H$51,3,0) -> Variable | X76: Pending | Y76: =VLOOKUP(L76,Map!$C$18:$D$29,2,0) -> TOTAL | AA76: =IF(Y76="TOTAL",(Z76*0.19),0) -> 0 | AB76: =Z76*1.19 -> 0 | AC76: =Z76/S76 -> 0 | AD76: =IF(Y76="TOTAL",(AC76*0.19),0) -> 0 | AE76: =AC76*1.19 -> 0
B77: 2026 | C77: May11 to May 26 | D77: MAY | E77: JUL (Provision) | F77: JUL | G77: 46177 | H77: 3719 | I77: PARIS (FULLKOM) | J77: =IFERROR(VLOOKUP(I77,Map!$F$18:$G$56,2,0),"Add in Map") -> 3P | K77: =VLOOKUP(L77,Map!$C$18:$D$29,2,0) -> CNT | L77: Refrigeration | M77: 2055020.9 | N77: =IF(L77="TOTAL",(M77*0.19),0) -> 0 | O77: =M77*1.19 -> 2445474.8 | P77: =M77/S77 -> 2306.4207 | Q77: =IF(L77="TOTAL",(P77*0.19),0) -> 0 | R77: =P77*1.19 -> 2744.6407 | S77: =INDEX(FX!$D$3:$O$19,MATCH(B77,FX!$B$3:$B$32,0),MATCH(D77,FX!$D$2:$O$2,0)) -> 891 | T77: Commission (2da Quincena) | U77: Provision (Based on External Report) | V77: Invoice | W77: =VLOOKUP(I77,Map!$F$18:$H$51,3,0) -> Variable | X77: AP Completed | Y77: =VLOOKUP(L77,Map!$C$18:$D$29,2,0) -> CNT | AA77: =IF(Y77="TOTAL",(Z77*0.19),0) -> 0 | AB77: =Z77*1.19 -> 0 | AC77: =Z77/S77 -> 0 | AD77: =IF(Y77="TOTAL",(AC77*0.19),0) -> 0 | AE77: =AC77*1.19 -> 0
B78: 2026 | C78: May11 to May 26 | D78: MAY | E78: JUL (Provision) | F78: JUL | G78: 46177 | H78: 3719 | I78: PARIS (FULLKOM) | J78: =IFERROR(VLOOKUP(I78,Map!$F$18:$G$56,2,0),"Add in Map") -> 3P | K78: =VLOOKUP(L78,Map!$C$18:$D$29,2,0) -> CVT | L78: Cooking | M78: 110705.62 | N78: =IF(L78="TOTAL",(M78*0.19),0) -> 0 | O78: =M78*1.19 -> 131739.69 | P78: =M78/S78 -> 124.24874 | Q78: =IF(L78="TOTAL",(P78*0.19),0) -> 0 | R78: =P78*1.19 -> 147.856 | S78: =INDEX(FX!$D$3:$O$19,MATCH(B78,FX!$B$3:$B$32,0),MATCH(D78,FX!$D$2:$O$2,0)) -> 891 | T78: Commission (2da Quincena) | U78: Provision (Based on External Report) | V78: Invoice | W78: =VLOOKUP(I78,Map!$F$18:$H$51,3,0) -> Variable | X78: AP Completed | Y78: =VLOOKUP(L78,Map!$C$18:$D$29,2,0) -> CVT | AA78: =IF(Y78="TOTAL",(Z78*0.19),0) -> 0 | AB78: =Z78*1.19 -> 0 | AC78: =Z78/S78 -> 0 | AD78: =IF(Y78="TOTAL",(AC78*0.19),0) -> 0 | AE78: =AC78*1.19 -> 0
B79: 2026 | C79: May11 to May 26 | D79: MAY | E79: JUL (Provision) | F79: JUL | G79: 46177 | H79: 3719 | I79: PARIS (FULLKOM) | J79: =IFERROR(VLOOKUP(I79,Map!$F$18:$G$56,2,0),"Add in Map") -> 3P | K79: =VLOOKUP(L79,Map!$C$18:$D$29,2,0) -> CDT | L79: Dishwasher | M79: 0 | N79: =IF(L79="TOTAL",(M79*0.19),0) -> 0 | O79: =M79*1.19 -> 0 | P79: =M79/S79 -> 0 | Q79: =IF(L79="TOTAL",(P79*0.19),0) -> 0 | R79: =P79*1.19 -> 0 | S79: =INDEX(FX!$D$3:$O$19,MATCH(B79,FX!$B$3:$B$32,0),MATCH(D79,FX!$D$2:$O$2,0)) -> 891 | T79: Commission (2da Quincena) | U79: Provision (Based on External Report) | V79: Invoice | W79: =VLOOKUP(I79,Map!$F$18:$H$51,3,0) -> Variable | X79: AP Completed | Y79: =VLOOKUP(L79,Map!$C$18:$D$29,2,0) -> CDT | AA79: =IF(Y79="TOTAL",(Z79*0.19),0) -> 0 | AB79: =Z79*1.19 -> 0 | AC79: =Z79/S79 -> 0 | AD79: =IF(Y79="TOTAL",(AC79*0.19),0) -> 0 | AE79: =AC79*1.19 -> 0
B80: 2026 | C80: May11 to May 26 | D80: MAY | E80: JUL (Provision) | F80: JUL | G80: 46177 | H80: 3719 | I80: PARIS (FULLKOM) | J80: =IFERROR(VLOOKUP(I80,Map!$F$18:$G$56,2,0),"Add in Map") -> 3P | K80: =VLOOKUP(L80,Map!$C$18:$D$29,2,0) -> DFT | L80: WM | M80: 6018437.4 | N80: =IF(L80="TOTAL",(M80*0.19),0) -> 0 | O80: =M80*1.19 -> 7161940.5 | P80: =M80/S80 -> 6754.6996 | Q80: =IF(L80="TOTAL",(P80*0.19),0) -> 0 | R80: =P80*1.19 -> 8038.0925 | S80: =INDEX(FX!$D$3:$O$19,MATCH(B80,FX!$B$3:$B$32,0),MATCH(D80,FX!$D$2:$O$2,0)) -> 891 | T80: Commission (2da Quincena) | U80: Provision (Based on External Report) | V80: Invoice | W80: =VLOOKUP(I80,Map!$F$18:$H$51,3,0) -> Variable | X80: AP Completed | Y80: =VLOOKUP(L80,Map!$C$18:$D$29,2,0) -> DFT | AA80: =IF(Y80="TOTAL",(Z80*0.19),0) -> 0 | AB80: =Z80*1.19 -> 0 | AC80: =Z80/S80 -> 0 | AD80: =IF(Y80="TOTAL",(AC80*0.19),0) -> 0 | AE80: =AC80*1.19 -> 0
B81: 2026 | C81: May11 to May 26 | D81: MAY | E81: JUL (Provision) | F81: JUL | G81: 46177 | H81: 3719 | I81: PARIS (FULLKOM) | J81: =IFERROR(VLOOKUP(I81,Map!$F$18:$G$56,2,0),"Add in Map") -> 3P | K81: =VLOOKUP(L81,Map!$C$18:$D$29,2,0) -> DVT | L81: VCC | M81: 0 | N81: =IF(L81="TOTAL",(M81*0.19),0) -> 0 | O81: =M81*1.19 -> 0 | P81: =M81/S81 -> 0 | Q81: =IF(L81="TOTAL",(P81*0.19),0) -> 0 | R81: =P81*1.19 -> 0 | S81: =INDEX(FX!$D$3:$O$19,MATCH(B81,FX!$B$3:$B$32,0),MATCH(D81,FX!$D$2:$O$2,0)) -> 891 | T81: Commission (2da Quincena) | U81: Provision (Based on External Report) | V81: Invoice | W81: =VLOOKUP(I81,Map!$F$18:$H$51,3,0) -> Variable | X81: AP Completed | Y81: =VLOOKUP(L81,Map!$C$18:$D$29,2,0) -> DVT | AA81: =IF(Y81="TOTAL",(Z81*0.19),0) -> 0 | AB81: =Z81*1.19 -> 0 | AC81: =Z81/S81 -> 0 | AD81: =IF(Y81="TOTAL",(AC81*0.19),0) -> 0 | AE81: =AC81*1.19 -> 0
B82: 2026 | C82: May11 to May 26 | D82: MAY | E82: JUL (Provision) | F82: JUL | G82: 46177 | H82: 3719 | I82: PARIS (FULLKOM) | J82: =IFERROR(VLOOKUP(I82,Map!$F$18:$G$56,2,0),"Add in Map") -> 3P | K82: =VLOOKUP(L82,Map!$C$18:$D$29,2,0) -> GLT | L82: Television | M82: 2689893.1 | N82: =IF(L82="TOTAL",(M82*0.19),0) -> 0 | O82: =M82*1.19 -> 3200972.8 | P82: =M82/S82 -> 3018.9597 | Q82: =IF(L82="TOTAL",(P82*0.19),0) -> 0 | R82: =P82*1.19 -> 3592.5621 | S82: =INDEX(FX!$D$3:$O$19,MATCH(B82,FX!$B$3:$B$32,0),MATCH(D82,FX!$D$2:$O$2,0)) -> 891 | T82: Commission (2da Quincena) | U82: Provision (Based on External Report) | V82: Invoice | W82: =VLOOKUP(I82,Map!$F$18:$H$51,3,0) -> Variable | X82: AP Completed | Y82: =VLOOKUP(L82,Map!$C$18:$D$29,2,0) -> GLT | AA82: =IF(Y82="TOTAL",(Z82*0.19),0) -> 0 | AB82: =Z82*1.19 -> 0 | AC82: =Z82/S82 -> 0 | AD82: =IF(Y82="TOTAL",(AC82*0.19),0) -> 0 | AE82: =AC82*1.19 -> 0
B83: 2026 | C83: May11 to May 26 | D83: MAY | E83: JUL (Provision) | F83: JUL | G83: 46177 | H83: 3719 | I83: PARIS (FULLKOM) | J83: =IFERROR(VLOOKUP(I83,Map!$F$18:$G$56,2,0),"Add in Map") -> 3P | K83: =VLOOKUP(L83,Map!$C$18:$D$29,2,0) -> PNT | L83: Audio | M83: 202816.15 | N83: =IF(L83="TOTAL",(M83*0.19),0) -> 0 | O83: =M83*1.19 -> 241351.22 | P83: =M83/S83 -> 227.62755 | Q83: =IF(L83="TOTAL",(P83*0.19),0) -> 0 | R83: =P83*1.19 -> 270.87679 | S83: =INDEX(FX!$D$3:$O$19,MATCH(B83,FX!$B$3:$B$32,0),MATCH(D83,FX!$D$2:$O$2,0)) -> 891 | T83: Commission (2da Quincena) | U83: Provision (Based on External Report) | V83: Invoice | W83: =VLOOKUP(I83,Map!$F$18:$H$51,3,0) -> Variable | X83: AP Completed | Y83: =VLOOKUP(L83,Map!$C$18:$D$29,2,0) -> PNT | AA83: =IF(Y83="TOTAL",(Z83*0.19),0) -> 0 | AB83: =Z83*1.19 -> 0 | AC83: =Z83/S83 -> 0 | AD83: =IF(Y83="TOTAL",(AC83*0.19),0) -> 0 | AE83: =AC83*1.19 -> 0
B84: 2026 | C84: May11 to May 26 | D84: MAY | E84: JUL (Provision) | F84: JUL | G84: 46177 | H84: 3719 | I84: PARIS (FULLKOM) | J84: =IFERROR(VLOOKUP(I84,Map!$F$18:$G$56,2,0),"Add in Map") -> 3P | K84: =VLOOKUP(L84,Map!$C$18:$D$29,2,0) -> GTT | L84: Monitor | M84: 108893.77 | N84: =IF(L84="TOTAL",(M84*0.19),0) -> 0 | O84: =M84*1.19 -> 129583.58 | P84: =M84/S84 -> 122.21523 | Q84: =IF(L84="TOTAL",(P84*0.19),0) -> 0 | R84: =P84*1.19 -> 145.43612 | S84: =INDEX(FX!$D$3:$O$19,MATCH(B84,FX!$B$3:$B$32,0),MATCH(D84,FX!$D$2:$O$2,0)) -> 891 | T84: Commission (2da Quincena) | U84: Provision (Based on External Report) | V84: Invoice | W84: =VLOOKUP(I84,Map!$F$18:$H$51,3,0) -> Variable | X84: AP Completed | Y84: =VLOOKUP(L84,Map!$C$18:$D$29,2,0) -> GTT | AA84: =IF(Y84="TOTAL",(Z84*0.19),0) -> 0 | AB84: =Z84*1.19 -> 0 | AC84: =Z84/S84 -> 0 | AD84: =IF(Y84="TOTAL",(AC84*0.19),0) -> 0 | AE84: =AC84*1.19 -> 0
B85: 2026 | C85: May11 to May 26 | D85: MAY | E85: JUL (Provision) | F85: JUL | G85: 46177 | H85: 3719 | I85: PARIS (FULLKOM) | J85: =IFERROR(VLOOKUP(I85,Map!$F$18:$G$56,2,0),"Add in Map") -> 3P | K85: =VLOOKUP(L85,Map!$C$18:$D$29,2,0) -> DGT | L85: RAC | M85: 54903.209 | N85: =IF(L85="TOTAL",(M85*0.19),0) -> 0 | O85: =M85*1.19 -> 65334.818 | P85: =M85/S85 -> 61.619763 | Q85: =IF(L85="TOTAL",(P85*0.19),0) -> 0 | R85: =P85*1.19 -> 73.327518 | S85: =INDEX(FX!$D$3:$O$19,MATCH(B85,FX!$B$3:$B$32,0),MATCH(D85,FX!$D$2:$O$2,0)) -> 891 | T85: Commission (2da Quincena) | U85: Provision (Based on External Report) | V85: Invoice | W85: =VLOOKUP(I85,Map!$F$18:$H$51,3,0) -> Variable | X85: AP Completed | Y85: =VLOOKUP(L85,Map!$C$18:$D$29,2,0) -> DGT | AA85: =IF(Y85="TOTAL",(Z85*0.19),0) -> 0 | AB85: =Z85*1.19 -> 0 | AC85: =Z85/S85 -> 0 | AD85: =IF(Y85="TOTAL",(AC85*0.19),0) -> 0 | AE85: =AC85*1.19 -> 0
B86: 2026 | C86: May11 to May 26 | D86: MAY | E86: JUL (Provision) | F86: JUL | G86: 46177 | H86: 3719 | I86: PARIS (FULLKOM) | J86: =IFERROR(VLOOKUP(I86,Map!$F$18:$G$56,2,0),"Add in Map") -> 3P | K86: =VLOOKUP(L86,Map!$C$18:$D$29,2,0) -> DLT | L86: Air Cleaner | M86: 16787.885 | N86: =IF(L86="TOTAL",(M86*0.19),0) -> 0 | O86: =M86*1.19 -> 19977.583 | P86: =M86/S86 -> 18.841622 | Q86: =IF(L86="TOTAL",(P86*0.19),0) -> 0 | R86: =P86*1.19 -> 22.42153 | S86: =INDEX(FX!$D$3:$O$19,MATCH(B86,FX!$B$3:$B$32,0),MATCH(D86,FX!$D$2:$O$2,0)) -> 891 | T86: Commission (2da Quincena) | U86: Provision (Based on External Report) | V86: Invoice | W86: =VLOOKUP(I86,Map!$F$18:$H$51,3,0) -> Variable | X86: AP Completed | Y86: =VLOOKUP(L86,Map!$C$18:$D$29,2,0) -> DLT | AA86: =IF(Y86="TOTAL",(Z86*0.19),0) -> 0 | AB86: =Z86*1.19 -> 0 | AC86: =Z86/S86 -> 0 | AD86: =IF(Y86="TOTAL",(AC86*0.19),0) -> 0 | AE86: =AC86*1.19 -> 0
B87: 2026 | C87: May11 to May 26 | D87: MAY | E87: JUL (Provision) | F87: JUL | G87: 46177 | H87: 3719 | I87: PARIS (FULLKOM) | J87: =IFERROR(VLOOKUP(I87,Map!$F$18:$G$56,2,0),"Add in Map") -> 3P | K87: =VLOOKUP(L87,Map!$C$18:$D$29,2,0) -> DMT | L87: SAC | M87: 0 | N87: =IF(L87="TOTAL",(M87*0.19),0) -> 0 | O87: =M87*1.19 -> 0 | P87: =M87/S87 -> 0 | Q87: =IF(L87="TOTAL",(P87*0.19),0) -> 0 | R87: =P87*1.19 -> 0 | S87: =INDEX(FX!$D$3:$O$19,MATCH(B87,FX!$B$3:$B$32,0),MATCH(D87,FX!$D$2:$O$2,0)) -> 891 | T87: Commission (2da Quincena) | U87: Provision (Based on External Report) | V87: Invoice | W87: =VLOOKUP(I87,Map!$F$18:$H$51,3,0) -> Variable | X87: AP Completed | Y87: =VLOOKUP(L87,Map!$C$18:$D$29,2,0) -> DMT | AA87: =IF(Y87="TOTAL",(Z87*0.19),0) -> 0 | AB87: =Z87*1.19 -> 0 | AC87: =Z87/S87 -> 0 | AD87: =IF(Y87="TOTAL",(AC87*0.19),0) -> 0 | AE87: =AC87*1.19 -> 0
B88: 2026 | C88: May11 to May 26 | D88: MAY | E88: JUL (Provision) | F88: JUL | G88: 46177 | H88: 3719 | I88: PARIS (FULLKOM) | J88: =IFERROR(VLOOKUP(I88,Map!$F$18:$G$56,2,0),"Add in Map") -> 3P | K88: =VLOOKUP(L88,Map!$C$18:$D$29,2,0) -> TOTAL | L88: TOTAL | M88: =SUM(M77:M87) -> 11257458 | N88: =IF(L88="TOTAL",(M88*0.19),0) -> 2138917 | O88: =M88*1.19 -> 13396375 | P88: =M88/S88 -> 12634.633 | Q88: =IF(L88="TOTAL",(P88*0.19),0) -> 2400.5803 | R88: =P88*1.19 -> 15035.213 | S88: =INDEX(FX!$D$3:$O$19,MATCH(B88,FX!$B$3:$B$32,0),MATCH(D88,FX!$D$2:$O$2,0)) -> 891 | T88: Commission (2da Quincena) | U88: Provision (Based on External Report) | V88: Invoice | W88: =VLOOKUP(I88,Map!$F$18:$H$51,3,0) -> Variable | X88: AP Completed | Y88: =VLOOKUP(L88,Map!$C$18:$D$29,2,0) -> TOTAL | AA88: =IF(Y88="TOTAL",(Z88*0.19),0) -> 0 | AB88: =Z88*1.19 -> 0 | AC88: =Z88/S88 -> 0 | AD88: =IF(Y88="TOTAL",(AC88*0.19),0) -> 0 | AE88: =AC88*1.19 -> 0
B89: 2026 | C89: May 27 to Jun 10 | D89: JUN | E89: JUL (Provision) | F89: JUL | G89: 46218 | H89: 3864 | I89: PARIS (FULLKOM) | J89: =IFERROR(VLOOKUP(I89,Map!$F$18:$G$56,2,0),"Add in Map") -> 3P | K89: =VLOOKUP(L89,Map!$C$18:$D$29,2,0) -> CNT | L89: Refrigeration | M89: 8616450.4 | N89: =IF(L89="TOTAL",(M89*0.19),0) -> 0 | O89: =M89*1.19 -> 10253576 | P89: =M89/S89 -> 9335.2658 | Q89: =IF(L89="TOTAL",(P89*0.19),0) -> 0 | R89: =P89*1.19 -> 11108.966 | S89: =INDEX(FX!$D$3:$O$19,MATCH(B89,FX!$B$3:$B$32,0),MATCH(D89,FX!$D$2:$O$2,0)) -> 923 | T89: Commission (1era Quincena) | U89: Provision (Based on External Report) | V89: Invoice | W89: =VLOOKUP(I89,Map!$F$18:$H$51,3,0) -> Variable | X89: AP Completed | Y89: =VLOOKUP(L89,Map!$C$18:$D$29,2,0) -> CNT | Z89: 6586062 | AA89: =IF(Y89="TOTAL",(Z89*0.19),0) -> 0 | AB89: =Z89*1.19 -> 7837413.8 | AC89: =Z89/S89 -> 7135.4951 | AD89: =IF(Y89="TOTAL",(AC89*0.19),0) -> 0 | AE89: =AC89*1.19 -> 8491.2392
B90: 2026 | C90: May 27 to Jun 10 | D90: JUN | E90: JUL (Provision) | F90: JUL | G90: 46218 | H90: 3864 | I90: PARIS (FULLKOM) | J90: =IFERROR(VLOOKUP(I90,Map!$F$18:$G$56,2,0),"Add in Map") -> 3P | K90: =VLOOKUP(L90,Map!$C$18:$D$29,2,0) -> CVT | L90: Cooking | M90: 209438.61 | N90: =IF(L90="TOTAL",(M90*0.19),0) -> 0 | O90: =M90*1.19 -> 249231.95 | P90: =M90/S90 -> 226.91074 | Q90: =IF(L90="TOTAL",(P90*0.19),0) -> 0 | R90: =P90*1.19 -> 270.02378 | S90: =INDEX(FX!$D$3:$O$19,MATCH(B90,FX!$B$3:$B$32,0),MATCH(D90,FX!$D$2:$O$2,0)) -> 923 | T90: Commission (1era Quincena) | U90: Provision (Based on External Report) | V90: Invoice | W90: =VLOOKUP(I90,Map!$F$18:$H$51,3,0) -> Variable | X90: AP Completed | Y90: =VLOOKUP(L90,Map!$C$18:$D$29,2,0) -> CVT | Z90: 160086.3 | AA90: =IF(Y90="TOTAL",(Z90*0.19),0) -> 0 | AB90: =Z90*1.19 -> 190502.7 | AC90: =Z90/S90 -> 173.44128 | AD90: =IF(Y90="TOTAL",(AC90*0.19),0) -> 0 | AE90: =AC90*1.19 -> 206.39512
B91: 2026 | C91: May 27 to Jun 10 | D91: JUN | E91: JUL (Provision) | F91: JUL | G91: 46218 | H91: 3864 | I91: PARIS (FULLKOM) | J91: =IFERROR(VLOOKUP(I91,Map!$F$18:$G$56,2,0),"Add in Map") -> 3P | K91: =VLOOKUP(L91,Map!$C$18:$D$29,2,0) -> CDT | L91: Dishwasher | M91: 215621.91 | N91: =IF(L91="TOTAL",(M91*0.19),0) -> 0 | O91: =M91*1.19 -> 256590.07 | P91: =M91/S91 -> 233.60987 | Q91: =IF(L91="TOTAL",(P91*0.19),0) -> 0 | R91: =P91*1.19 -> 277.99575 | S91: =INDEX(FX!$D$3:$O$19,MATCH(B91,FX!$B$3:$B$32,0),MATCH(D91,FX!$D$2:$O$2,0)) -> 923 | T91: Commission (1era Quincena) | U91: Provision (Based on External Report) | V91: Invoice | W91: =VLOOKUP(I91,Map!$F$18:$H$51,3,0) -> Variable | X91: AP Completed | Y91: =VLOOKUP(L91,Map!$C$18:$D$29,2,0) -> CDT | Z91: 164812.56 | AA91: =IF(Y91="TOTAL",(Z91*0.19),0) -> 0 | AB91: =Z91*1.19 -> 196126.95 | AC91: =Z91/S91 -> 178.56182 | AD91: =IF(Y91="TOTAL",(AC91*0.19),0) -> 0 | AE91: =AC91*1.19 -> 212.48857
B92: 2026 | C92: May 27 to Jun 10 | D92: JUN | E92: JUL (Provision) | F92: JUL | G92: 46218 | H92: 3864 | I92: PARIS (FULLKOM) | J92: =IFERROR(VLOOKUP(I92,Map!$F$18:$G$56,2,0),"Add in Map") -> 3P | K92: =VLOOKUP(L92,Map!$C$18:$D$29,2,0) -> DFT | L92: WM | M92: 17970338 | N92: =IF(L92="TOTAL",(M92*0.19),0) -> 0 | O92: =M92*1.19 -> 21384702 | P92: =M92/S92 -> 19469.488 | Q92: =IF(L92="TOTAL",(P92*0.19),0) -> 0 | R92: =P92*1.19 -> 23168.691 | S92: =INDEX(FX!$D$3:$O$19,MATCH(B92,FX!$B$3:$B$32,0),MATCH(D92,FX!$D$2:$O$2,0)) -> 923 | T92: Commission (1era Quincena) | U92: Provision (Based on External Report) | V92: Invoice | W92: =VLOOKUP(I92,Map!$F$18:$H$51,3,0) -> Variable | X92: AP Completed | Y92: =VLOOKUP(L92,Map!$C$18:$D$29,2,0) -> DFT | Z92: 13735791 | AA92: =IF(Y92="TOTAL",(Z92*0.19),0) -> 0 | AB92: =Z92*1.19 -> 16345591 | AC92: =Z92/S92 -> 14881.68 | AD92: =IF(Y92="TOTAL",(AC92*0.19),0) -> 0 | AE92: =AC92*1.19 -> 17709.199
B93: 2026 | C93: May 27 to Jun 10 | D93: JUN | E93: JUL (Provision) | F93: JUL | G93: 46218 | H93: 3864 | I93: PARIS (FULLKOM) | J93: =IFERROR(VLOOKUP(I93,Map!$F$18:$G$56,2,0),"Add in Map") -> 3P | K93: =VLOOKUP(L93,Map!$C$18:$D$29,2,0) -> DVT | L93: VCC | M93: 0 | N93: =IF(L93="TOTAL",(M93*0.19),0) -> 0 | O93: =M93*1.19 -> 0 | P93: =M93/S93 -> 0 | Q93: =IF(L93="TOTAL",(P93*0.19),0) -> 0 | R93: =P93*1.19 -> 0 | S93: =INDEX(FX!$D$3:$O$19,MATCH(B93,FX!$B$3:$B$32,0),MATCH(D93,FX!$D$2:$O$2,0)) -> 923 | T93: Commission (1era Quincena) | U93: Provision (Based on External Report) | V93: Invoice | W93: =VLOOKUP(I93,Map!$F$18:$H$51,3,0) -> Variable | X93: AP Completed | Y93: =VLOOKUP(L93,Map!$C$18:$D$29,2,0) -> DVT | Z93: 0 | AA93: =IF(Y93="TOTAL",(Z93*0.19),0) -> 0 | AB93: =Z93*1.19 -> 0 | AC93: =Z93/S93 -> 0 | AD93: =IF(Y93="TOTAL",(AC93*0.19),0) -> 0 | AE93: =AC93*1.19 -> 0
B94: 2026 | C94: May 27 to Jun 10 | D94: JUN | E94: JUL (Provision) | F94: JUL | G94: 46218 | H94: 3864 | I94: PARIS (FULLKOM) | J94: =IFERROR(VLOOKUP(I94,Map!$F$18:$G$56,2,0),"Add in Map") -> 3P | K94: =VLOOKUP(L94,Map!$C$18:$D$29,2,0) -> GLT | L94: Television | M94: 11677468 | N94: =IF(L94="TOTAL",(M94*0.19),0) -> 0 | O94: =M94*1.19 -> 13896187 | P94: =M94/S94 -> 12651.645 | Q94: =IF(L94="TOTAL",(P94*0.19),0) -> 0 | R94: =P94*1.19 -> 15055.457 | S94: =INDEX(FX!$D$3:$O$19,MATCH(B94,FX!$B$3:$B$32,0),MATCH(D94,FX!$D$2:$O$2,0)) -> 923 | T94: Commission (1era Quincena) | U94: Provision (Based on External Report) | V94: Invoice | W94: =VLOOKUP(I94,Map!$F$18:$H$51,3,0) -> Variable | X94: AP Completed | Y94: =VLOOKUP(L94,Map!$C$18:$D$29,2,0) -> GLT | Z94: 8925778.7 | AA94: =IF(Y94="TOTAL",(Z94*0.19),0) -> 0 | AB94: =Z94*1.19 -> 10621677 | AC94: =Z94/S94 -> 9670.3994 | AD94: =IF(Y94="TOTAL",(AC94*0.19),0) -> 0 | AE94: =AC94*1.19 -> 11507.775
B95: 2026 | C95: May 27 to Jun 10 | D95: JUN | E95: JUL (Provision) | F95: JUL | G95: 46218 | H95: 3864 | I95: PARIS (FULLKOM) | J95: =IFERROR(VLOOKUP(I95,Map!$F$18:$G$56,2,0),"Add in Map") -> 3P | K95: =VLOOKUP(L95,Map!$C$18:$D$29,2,0) -> PNT | L95: Audio | M95: 1267068.1 | N95: =IF(L95="TOTAL",(M95*0.19),0) -> 0 | O95: =M95*1.19 -> 1507811 | P95: =M95/S95 -> 1372.7715 | Q95: =IF(L95="TOTAL",(P95*0.19),0) -> 0 | R95: =P95*1.19 -> 1633.5981 | S95: =INDEX(FX!$D$3:$O$19,MATCH(B95,FX!$B$3:$B$32,0),MATCH(D95,FX!$D$2:$O$2,0)) -> 923 | T95: Commission (1era Quincena) | U95: Provision (Based on External Report) | V95: Invoice | W95: =VLOOKUP(I95,Map!$F$18:$H$51,3,0) -> Variable | X95: AP Completed | Y95: =VLOOKUP(L95,Map!$C$18:$D$29,2,0) -> PNT | Z95: 968494.98 | AA95: =IF(Y95="TOTAL",(Z95*0.19),0) -> 0 | AB95: =Z95*1.19 -> 1152509 | AC95: =Z95/S95 -> 1049.2903 | AD95: =IF(Y95="TOTAL",(AC95*0.19),0) -> 0 | AE95: =AC95*1.19 -> 1248.6555
B96: 2026 | C96: May 27 to Jun 10 | D96: JUN | E96: JUL (Provision) | F96: JUL | G96: 46218 | H96: 3864 | I96: PARIS (FULLKOM) | J96: =IFERROR(VLOOKUP(I96,Map!$F$18:$G$56,2,0),"Add in Map") -> 3P | K96: =VLOOKUP(L96,Map!$C$18:$D$29,2,0) -> GTT | L96: Monitor | M96: 776356.33 | N96: =IF(L96="TOTAL",(M96*0.19),0) -> 0 | O96: =M96*1.19 -> 923864.03 | P96: =M96/S96 -> 841.12278 | Q96: =IF(L96="TOTAL",(P96*0.19),0) -> 0 | R96: =P96*1.19 -> 1000.9361 | S96: =INDEX(FX!$D$3:$O$19,MATCH(B96,FX!$B$3:$B$32,0),MATCH(D96,FX!$D$2:$O$2,0)) -> 923 | T96: Commission (1era Quincena) | U96: Provision (Based on External Report) | V96: Invoice | W96: =VLOOKUP(I96,Map!$F$18:$H$51,3,0) -> Variable | X96: AP Completed | Y96: =VLOOKUP(L96,Map!$C$18:$D$29,2,0) -> GTT | Z96: 593415 | AA96: =IF(Y96="TOTAL",(Z96*0.19),0) -> 0 | AB96: =Z96*1.19 -> 706163.85 | AC96: =Z96/S96 -> 642.91982 | AD96: =IF(Y96="TOTAL",(AC96*0.19),0) -> 0 | AE96: =AC96*1.19 -> 765.07459
B97: 2026 | C97: May 27 to Jun 10 | D97: JUN | E97: JUL (Provision) | F97: JUL | G97: 46218 | H97: 3864 | I97: PARIS (FULLKOM) | J97: =IFERROR(VLOOKUP(I97,Map!$F$18:$G$56,2,0),"Add in Map") -> 3P | K97: =VLOOKUP(L97,Map!$C$18:$D$29,2,0) -> DGT | L97: RAC | M97: 691665.26 | N97: =IF(L97="TOTAL",(M97*0.19),0) -> 0 | O97: =M97*1.19 -> 823081.66 | P97: =M97/S97 -> 749.36648 | Q97: =IF(L97="TOTAL",(P97*0.19),0) -> 0 | R97: =P97*1.19 -> 891.74611 | S97: =INDEX(FX!$D$3:$O$19,MATCH(B97,FX!$B$3:$B$32,0),MATCH(D97,FX!$D$2:$O$2,0)) -> 923 | T97: Commission (1era Quincena) | U97: Provision (Based on External Report) | V97: Invoice | W97: =VLOOKUP(I97,Map!$F$18:$H$51,3,0) -> Variable | X97: AP Completed | Y97: =VLOOKUP(L97,Map!$C$18:$D$29,2,0) -> DGT | Z97: 528680.62 | AA97: =IF(Y97="TOTAL",(Z97*0.19),0) -> 0 | AB97: =Z97*1.19 -> 629129.93 | AC97: =Z97/S97 -> 572.78507 | AD97: =IF(Y97="TOTAL",(AC97*0.19),0) -> 0 | AE97: =AC97*1.19 -> 681.61423
B98: 2026 | C98: May 27 to Jun 10 | D98: JUN | E98: JUL (Provision) | F98: JUL | G98: 46218 | H98: 3864 | I98: PARIS (FULLKOM) | J98: =IFERROR(VLOOKUP(I98,Map!$F$18:$G$56,2,0),"Add in Map") -> 3P | K98: =VLOOKUP(L98,Map!$C$18:$D$29,2,0) -> DLT | L98: Air Cleaner | M98: 156247.61 | N98: =IF(L98="TOTAL",(M98*0.19),0) -> 0 | O98: =M98*1.19 -> 185934.66 | P98: =M98/S98 -> 169.28235 | Q98: =IF(L98="TOTAL",(P98*0.19),0) -> 0 | R98: =P98*1.19 -> 201.446 | S98: =INDEX(FX!$D$3:$O$19,MATCH(B98,FX!$B$3:$B$32,0),MATCH(D98,FX!$D$2:$O$2,0)) -> 923 | T98: Commission (1era Quincena) | U98: Provision (Based on External Report) | V98: Invoice | W98: =VLOOKUP(I98,Map!$F$18:$H$51,3,0) -> Variable | X98: AP Completed | Y98: =VLOOKUP(L98,Map!$C$18:$D$29,2,0) -> DLT | Z98: 119429.28 | AA98: =IF(Y98="TOTAL",(Z98*0.19),0) -> 0 | AB98: =Z98*1.19 -> 142120.84 | AC98: =Z98/S98 -> 129.3925 | AD98: =IF(Y98="TOTAL",(AC98*0.19),0) -> 0 | AE98: =AC98*1.19 -> 153.97708
B99: 2026 | C99: May 27 to Jun 10 | D99: JUN | E99: JUL (Provision) | F99: JUL | G99: 46218 | H99: 3864 | I99: PARIS (FULLKOM) | J99: =IFERROR(VLOOKUP(I99,Map!$F$18:$G$56,2,0),"Add in Map") -> 3P | K99: =VLOOKUP(L99,Map!$C$18:$D$29,2,0) -> DMT | L99: SAC | M99: 0 | N99: =IF(L99="TOTAL",(M99*0.19),0) -> 0 | O99: =M99*1.19 -> 0 | P99: =M99/S99 -> 0 | Q99: =IF(L99="TOTAL",(P99*0.19),0) -> 0 | R99: =P99*1.19 -> 0 | S99: =INDEX(FX!$D$3:$O$19,MATCH(B99,FX!$B$3:$B$32,0),MATCH(D99,FX!$D$2:$O$2,0)) -> 923 | T99: Commission (1era Quincena) | U99: Provision (Based on External Report) | V99: Invoice | W99: =VLOOKUP(I99,Map!$F$18:$H$51,3,0) -> Variable | X99: AP Completed | Y99: =VLOOKUP(L99,Map!$C$18:$D$29,2,0) -> DMT | Z99: 0 | AA99: =IF(Y99="TOTAL",(Z99*0.19),0) -> 0 | AB99: =Z99*1.19 -> 0 | AC99: =Z99/S99 -> 0 | AD99: =IF(Y99="TOTAL",(AC99*0.19),0) -> 0 | AE99: =AC99*1.19 -> 0
B100: 2026 | C100: May 27 to Jun 10 | D100: JUN | E100: JUL (Provision) | F100: JUL | G100: 46218 | H100: 3864 | I100: PARIS (FULLKOM) | J100: =IFERROR(VLOOKUP(I100,Map!$F$18:$G$56,2,0),"Add in Map") -> 3P | K100: =VLOOKUP(L100,Map!$C$18:$D$29,2,0) -> TOTAL | L100: TOTAL | M100: =SUM(M89:M99) -> 41580654 | N100: =IF(L100="TOTAL",(M100*0.19),0) -> 7900324.3 | O100: =M100*1.19 -> 49480978 | P100: =M100/S100 -> 45049.463 | Q100: =IF(L100="TOTAL",(P100*0.19),0) -> 8559.3979 | R100: =P100*1.19 -> 53608.861 | S100: =INDEX(FX!$D$3:$O$19,MATCH(B100,FX!$B$3:$B$32,0),MATCH(D100,FX!$D$2:$O$2,0)) -> 923 | T100: Commission (1era Quincena) | U100: Provision (Based on External Report) | V100: Invoice | W100: =VLOOKUP(I100,Map!$F$18:$H$51,3,0) -> Variable | X100: AP Completed | Y100: =VLOOKUP(L100,Map!$C$18:$D$29,2,0) -> TOTAL | Z100: =SUM(Z89:Z99) -> 31782550 | AA100: =IF(Y100="TOTAL",(Z100*0.19),0) -> 6038684.5 | AB100: =Z100*1.19 -> 37821234 | AC100: =Z100/S100 -> 34433.965 | AD100: =IF(Y100="TOTAL",(AC100*0.19),0) -> 6542.4534 | AE100: =AC100*1.19 -> 40976.419
B101: 2026 | C101: Jun 10 to Jun 26 | D101: JUN | E101: JUL (Provision) | F101: JUL | G101: 46218 | H101: 3867 | I101: PARIS (FULLKOM) | J101: =IFERROR(VLOOKUP(I101,Map!$F$18:$G$56,2,0),"Add in Map") -> 3P | K101: =VLOOKUP(L101,Map!$C$18:$D$29,2,0) -> CNT | L101: Refrigeration | N101: =IF(L101="TOTAL",(M101*0.19),0) -> 0 | O101: =M101*1.19 -> 0 | P101: =M101/S101 -> 0 | Q101: =IF(L101="TOTAL",(P101*0.19),0) -> 0 | R101: =P101*1.19 -> 0 | S101: =INDEX(FX!$D$3:$O$19,MATCH(B101,FX!$B$3:$B$32,0),MATCH(D101,FX!$D$2:$O$2,0)) -> 923 | T101: Commission (2da Quincena) | U101: Provision (Based on PO, One View) | V101: Invoice | W101: =VLOOKUP(I101,Map!$F$18:$H$51,3,0) -> Variable | X101: AP Completed | Y101: =VLOOKUP(L101,Map!$C$18:$D$29,2,0) -> CNT | Z101: 2811915.1 | AA101: =IF(Y101="TOTAL",(Z101*0.19),0) -> 0 | AB101: =Z101*1.19 -> 3346178.9 | AC101: =Z101/S101 -> 3046.4952 | AD101: =IF(Y101="TOTAL",(AC101*0.19),0) -> 0 | AE101: =AC101*1.19 -> 3625.3293
B102: 2026 | C102: Jun 10 to Jun 26 | D102: JUN | E102: JUL (Provision) | F102: JUL | G102: 46218 | H102: 3867 | I102: PARIS (FULLKOM) | J102: =IFERROR(VLOOKUP(I102,Map!$F$18:$G$56,2,0),"Add in Map") -> 3P | K102: =VLOOKUP(L102,Map!$C$18:$D$29,2,0) -> CVT | L102: Cooking | N102: =IF(L102="TOTAL",(M102*0.19),0) -> 0 | O102: =M102*1.19 -> 0 | P102: =M102/S102 -> 0 | Q102: =IF(L102="TOTAL",(P102*0.19),0) -> 0 | R102: =P102*1.19 -> 0 | S102: =INDEX(FX!$D$3:$O$19,MATCH(B102,FX!$B$3:$B$32,0),MATCH(D102,FX!$D$2:$O$2,0)) -> 923 | T102: Commission (2da Quincena) | U102: Provision (Based on PO, One View) | V102: Invoice | W102: =VLOOKUP(I102,Map!$F$18:$H$51,3,0) -> Variable | X102: AP Completed | Y102: =VLOOKUP(L102,Map!$C$18:$D$29,2,0) -> CVT | Z102: 68348.747 | AA102: =IF(Y102="TOTAL",(Z102*0.19),0) -> 0 | AB102: =Z102*1.19 -> 81335.009 | AC102: =Z102/S102 -> 74.050647 | AD102: =IF(Y102="TOTAL",(AC102*0.19),0) -> 0 | AE102: =AC102*1.19 -> 88.12027
...

Sheet Master 1_BU v2
D2: Incluir al final toda la info de Map2
B4: Year | C4: Cut Date | D4: Invoice Received | E4: Impact Month | F4: Invoice Registered | G4: Invoice Date | H4: Invoice Number | I4: Customer | J4: OBS/3P | K4: BU | L4: Division | M4: Invoice Net Amt (CLP) | N4: VAT (CLP) | O4: Total Amt (CLP) | P4: Invoice Net Amt (USD) | Q4: VAT (USD) | R4: Total Amt (USD) | S4: FX Rate | T4: Commission Type | U4: Provision | V4: Doc Type | W4: Variable /Fixed | X4: Invoice Status | Y4: BU | Z4: Provision Net Amt (CLP) | AA4: Provision VAT (CLP) | AB4: Provision Amt (CLP) | AC4: Provision Net Amt (USD) | AD4: Provision VAT (USD) | AE4: Provision Amt (USD) | AF4: Invoice URL
B5: 2026 | C5: JUN 21 to JUL 20 | D5: JUL | E5: JUL (Provision) | F5: AUG | G5: 46230 | H5: 478270 | I5: FALABELLA (DIRECT) | J5: =IFERROR(VLOOKUP(I5,Map!$F$18:$G$56,2,0),"Add in Map") -> 3P | K5: =VLOOKUP(L5,Map!$C$18:$D$29,2,0) -> CNT | L5: Refrigeration | M5: 24645503 | N5: =IF(L5="TOTAL",(M5*0.19),0) -> 0 | O5: =M5*1.19 -> 29328148 | P5: =M5/S5 -> 26672.622 | Q5: =IF(L5="TOTAL",(P5*0.19),0) -> 0 | R5: =P5*1.19 -> 31740.42 | S5: =INDEX(FX!$D$3:$O$19,MATCH(B5,FX!$B$3:$B$32,0),MATCH(D5,FX!$D$2:$O$2,0)) -> 924 | T5: Monthly Commission | U5: Provision (Based on External Report) | V5: Invoice | W5: =VLOOKUP(I5,Map!$F$18:$H$51,3,0) -> Variable | X5: AP Completed | Y5: =VLOOKUP(L5,Map!$C$18:$D$29,2,0) -> CNT | Z5: 24645503 | AA5: =IF(Y5="TOTAL",(Z5*0.19),0) -> 0 | AB5: =Z5*1.19 -> 29328148 | AC5: =Z5/S5 -> 26672.622 | AD5: =IF(Y5="TOTAL",(AC5*0.19),0) -> 0 | AE5: =AC5*1.19 -> 31740.42
B6: 2026 | C6: JUN 21 to JUL 20 | D6: JUL | E6: JUL (Provision) | F6: AUG | G6: 46230 | H6: 478270 | I6: FALABELLA (DIRECT) | J6: =IFERROR(VLOOKUP(I6,Map!$F$18:$G$56,2,0),"Add in Map") -> 3P | K6: =VLOOKUP(L6,Map!$C$18:$D$29,2,0) -> CVT | L6: Cooking | M6: 291662.76 | N6: =IF(L6="TOTAL",(M6*0.19),0) -> 0 | O6: =M6*1.19 -> 347078.68 | P6: =M6/S6 -> 315.65233 | Q6: =IF(L6="TOTAL",(P6*0.19),0) -> 0 | R6: =P6*1.19 -> 375.62628 | S6: =INDEX(FX!$D$3:$O$19,MATCH(B6,FX!$B$3:$B$32,0),MATCH(D6,FX!$D$2:$O$2,0)) -> 924 | T6: Monthly Commission | U6: Provision (Based on External Report) | V6: Invoice | W6: =VLOOKUP(I6,Map!$F$18:$H$51,3,0) -> Variable | X6: AP Completed | Y6: =VLOOKUP(L6,Map!$C$18:$D$29,2,0) -> CVT | Z6: 291662.76 | AA6: =IF(Y6="TOTAL",(Z6*0.19),0) -> 0 | AB6: =Z6*1.19 -> 347078.68 | AC6: =Z6/S6 -> 315.65233 | AD6: =IF(Y6="TOTAL",(AC6*0.19),0) -> 0 | AE6: =AC6*1.19 -> 375.62628
B7: 2026 | C7: JUN 21 to JUL 20 | D7: JUL | E7: JUL (Provision) | F7: AUG | G7: 46230 | H7: 478270 | I7: FALABELLA (DIRECT) | J7: =IFERROR(VLOOKUP(I7,Map!$F$18:$G$56,2,0),"Add in Map") -> 3P | K7: =VLOOKUP(L7,Map!$C$18:$D$29,2,0) -> CDT | L7: Dishwasher | M7: 1020819.6 | N7: =IF(L7="TOTAL",(M7*0.19),0) -> 0 | O7: =M7*1.19 -> 1214775.4 | P7: =M7/S7 -> 1104.7832 | Q7: =IF(L7="TOTAL",(P7*0.19),0) -> 0 | R7: =P7*1.19 -> 1314.692 | S7: =INDEX(FX!$D$3:$O$19,MATCH(B7,FX!$B$3:$B$32,0),MATCH(D7,FX!$D$2:$O$2,0)) -> 924 | T7: Monthly Commission | U7: Provision (Based on External Report) | V7: Invoice | W7: =VLOOKUP(I7,Map!$F$18:$H$51,3,0) -> Variable | X7: AP Completed | Y7: =VLOOKUP(L7,Map!$C$18:$D$29,2,0) -> CDT | Z7: 1020819.6 | AA7: =IF(Y7="TOTAL",(Z7*0.19),0) -> 0 | AB7: =Z7*1.19 -> 1214775.4 | AC7: =Z7/S7 -> 1104.7832 | AD7: =IF(Y7="TOTAL",(AC7*0.19),0) -> 0 | AE7: =AC7*1.19 -> 1314.692
B8: 2026 | C8: JUN 21 to JUL 20 | D8: JUL | E8: JUL (Provision) | F8: AUG | G8: 46230 | H8: 478270 | I8: FALABELLA (DIRECT) | J8: =IFERROR(VLOOKUP(I8,Map!$F$18:$G$56,2,0),"Add in Map") -> 3P | K8: =VLOOKUP(L8,Map!$C$18:$D$29,2,0) -> DFT | L8: WM | M8: 73207352 | N8: =IF(L8="TOTAL",(M8*0.19),0) -> 0 | O8: =M8*1.19 -> 87116749 | P8: =M8/S8 -> 79228.736 | Q8: =IF(L8="TOTAL",(P8*0.19),0) -> 0 | R8: =P8*1.19 -> 94282.196 | S8: =INDEX(FX!$D$3:$O$19,MATCH(B8,FX!$B$3:$B$32,0),MATCH(D8,FX!$D$2:$O$2,0)) -> 924 | T8: Monthly Commission | U8: Provision (Based on External Report) | V8: Invoice | W8: =VLOOKUP(I8,Map!$F$18:$H$51,3,0) -> Variable | X8: AP Completed | Y8: =VLOOKUP(L8,Map!$C$18:$D$29,2,0) -> DFT | Z8: 73207352 | AA8: =IF(Y8="TOTAL",(Z8*0.19),0) -> 0 | AB8: =Z8*1.19 -> 87116749 | AC8: =Z8/S8 -> 79228.736 | AD8: =IF(Y8="TOTAL",(AC8*0.19),0) -> 0 | AE8: =AC8*1.19 -> 94282.196
B9: 2026 | C9: JUN 21 to JUL 20 | D9: JUL | E9: JUL (Provision) | F9: AUG | G9: 46230 | H9: 478270 | I9: FALABELLA (DIRECT) | J9: =IFERROR(VLOOKUP(I9,Map!$F$18:$G$56,2,0),"Add in Map") -> 3P | K9: =VLOOKUP(L9,Map!$C$18:$D$29,2,0) -> DVT | L9: VCC | M9: 145831.38 | N9: =IF(L9="TOTAL",(M9*0.19),0) -> 0 | O9: =M9*1.19 -> 173539.34 | P9: =M9/S9 -> 157.82617 | Q9: =IF(L9="TOTAL",(P9*0.19),0) -> 0 | R9: =P9*1.19 -> 187.81314 | S9: =INDEX(FX!$D$3:$O$19,MATCH(B9,FX!$B$3:$B$32,0),MATCH(D9,FX!$D$2:$O$2,0)) -> 924 | T9: Monthly Commission | U9: Provision (Based on External Report) | V9: Invoice | W9: =VLOOKUP(I9,Map!$F$18:$H$51,3,0) -> Variable | X9: AP Completed | Y9: =VLOOKUP(L9,Map!$C$18:$D$29,2,0) -> DVT | Z9: 145831.38 | AA9: =IF(Y9="TOTAL",(Z9*0.19),0) -> 0 | AB9: =Z9*1.19 -> 173539.34 | AC9: =Z9/S9 -> 157.82617 | AD9: =IF(Y9="TOTAL",(AC9*0.19),0) -> 0 | AE9: =AC9*1.19 -> 187.81314
B10: 2026 | C10: JUN 21 to JUL 20 | D10: JUL | E10: JUL (Provision) | F10: AUG | G10: 46230 | H10: 478270 | I10: FALABELLA (DIRECT) | J10: =IFERROR(VLOOKUP(I10,Map!$F$18:$G$56,2,0),"Add in Map") -> 3P | K10: =VLOOKUP(L10,Map!$C$18:$D$29,2,0) -> GLT | L10: Television | M10: 34707868 | N10: =IF(L10="TOTAL",(M10*0.19),0) -> 0 | O10: =M10*1.19 -> 41302363 | P10: =M10/S10 -> 37562.628 | Q10: =IF(L10="TOTAL",(P10*0.19),0) -> 0 | R10: =P10*1.19 -> 44699.527 | S10: =INDEX(FX!$D$3:$O$19,MATCH(B10,FX!$B$3:$B$32,0),MATCH(D10,FX!$D$2:$O$2,0)) -> 924 | T10: Monthly Commission | U10: Provision (Based on External Report) | V10: Invoice | W10: =VLOOKUP(I10,Map!$F$18:$H$51,3,0) -> Variable | X10: AP Completed | Y10: =VLOOKUP(L10,Map!$C$18:$D$29,2,0) -> GLT | Z10: 34707868 | AA10: =IF(Y10="TOTAL",(Z10*0.19),0) -> 0 | AB10: =Z10*1.19 -> 41302363 | AC10: =Z10/S10 -> 37562.628 | AD10: =IF(Y10="TOTAL",(AC10*0.19),0) -> 0 | AE10: =AC10*1.19 -> 44699.527
B11: 2026 | C11: JUN 21 to JUL 20 | D11: JUL | E11: JUL (Provision) | F11: AUG | G11: 46230 | H11: 478270 | I11: FALABELLA (DIRECT) | J11: =IFERROR(VLOOKUP(I11,Map!$F$18:$G$56,2,0),"Add in Map") -> 3P | K11: =VLOOKUP(L11,Map!$C$18:$D$29,2,0) -> PNT | L11: Audio | M11: 2187470.7 | N11: =IF(L11="TOTAL",(M11*0.19),0) -> 0 | O11: =M11*1.19 -> 2603090.1 | P11: =M11/S11 -> 2367.3925 | Q11: =IF(L11="TOTAL",(P11*0.19),0) -> 0 | R11: =P11*1.19 -> 2817.1971 | S11: =INDEX(FX!$D$3:$O$19,MATCH(B11,FX!$B$3:$B$32,0),MATCH(D11,FX!$D$2:$O$2,0)) -> 924 | T11: Monthly Commission | U11: Provision (Based on External Report) | V11: Invoice | W11: =VLOOKUP(I11,Map!$F$18:$H$51,3,0) -> Variable | X11: AP Completed | Y11: =VLOOKUP(L11,Map!$C$18:$D$29,2,0) -> PNT | Z11: 2187470.7 | AA11: =IF(Y11="TOTAL",(Z11*0.19),0) -> 0 | AB11: =Z11*1.19 -> 2603090.1 | AC11: =Z11/S11 -> 2367.3925 | AD11: =IF(Y11="TOTAL",(AC11*0.19),0) -> 0 | AE11: =AC11*1.19 -> 2817.1971
B12: 2026 | C12: JUN 21 to JUL 20 | D12: JUL | E12: JUL (Provision) | F12: AUG | G12: 46230 | H12: 478270 | I12: FALABELLA (DIRECT) | J12: =IFERROR(VLOOKUP(I12,Map!$F$18:$G$56,2,0),"Add in Map") -> 3P | K12: =VLOOKUP(L12,Map!$C$18:$D$29,2,0) -> GTT | L12: Monitor | M12: 3645784.5 | N12: =IF(L12="TOTAL",(M12*0.19),0) -> 0 | O12: =M12*1.19 -> 4338483.5 | P12: =M12/S12 -> 3945.6542 | Q12: =IF(L12="TOTAL",(P12*0.19),0) -> 0 | R12: =P12*1.19 -> 4695.3285 | S12: =INDEX(FX!$D$3:$O$19,MATCH(B12,FX!$B$3:$B$32,0),MATCH(D12,FX!$D$2:$O$2,0)) -> 924 | T12: Monthly Commission | U12: Provision (Based on External Report) | V12: Invoice | W12: =VLOOKUP(I12,Map!$F$18:$H$51,3,0) -> Variable | X12: AP Completed | Y12: =VLOOKUP(L12,Map!$C$18:$D$29,2,0) -> GTT | Z12: 3645784.5 | AA12: =IF(Y12="TOTAL",(Z12*0.19),0) -> 0 | AB12: =Z12*1.19 -> 4338483.5 | AC12: =Z12/S12 -> 3945.6542 | AD12: =IF(Y12="TOTAL",(AC12*0.19),0) -> 0 | AE12: =AC12*1.19 -> 4695.3285
B13: 2026 | C13: JUN 21 to JUL 20 | D13: JUL | E13: JUL (Provision) | F13: AUG | G13: 46230 | H13: 478270 | I13: FALABELLA (DIRECT) | J13: =IFERROR(VLOOKUP(I13,Map!$F$18:$G$56,2,0),"Add in Map") -> 3P | K13: =VLOOKUP(L13,Map!$C$18:$D$29,2,0) -> DGT | L13: RAC | M13: 1020819.6 | N13: =IF(L13="TOTAL",(M13*0.19),0) -> 0 | O13: =M13*1.19 -> 1214775.4 | P13: =M13/S13 -> 1104.7832 | Q13: =IF(L13="TOTAL",(P13*0.19),0) -> 0 | R13: =P13*1.19 -> 1314.692 | S13: =INDEX(FX!$D$3:$O$19,MATCH(B13,FX!$B$3:$B$32,0),MATCH(D13,FX!$D$2:$O$2,0)) -> 924 | T13: Monthly Commission | U13: Provision (Based on External Report) | V13: Invoice | W13: =VLOOKUP(I13,Map!$F$18:$H$51,3,0) -> Variable | X13: AP Completed | Y13: =VLOOKUP(L13,Map!$C$18:$D$29,2,0) -> DGT | Z13: 1020819.6 | AA13: =IF(Y13="TOTAL",(Z13*0.19),0) -> 0 | AB13: =Z13*1.19 -> 1214775.4 | AC13: =Z13/S13 -> 1104.7832 | AD13: =IF(Y13="TOTAL",(AC13*0.19),0) -> 0 | AE13: =AC13*1.19 -> 1314.692
B14: 2026 | C14: JUN 21 to JUL 20 | D14: JUL | E14: JUL (Provision) | F14: AUG | G14: 46230 | H14: 478270 | I14: FALABELLA (DIRECT) | J14: =IFERROR(VLOOKUP(I14,Map!$F$18:$G$56,2,0),"Add in Map") -> 3P | K14: =VLOOKUP(L14,Map!$C$18:$D$29,2,0) -> DLT | L14: Air Cleaner | M14: 291662.76 | N14: =IF(L14="TOTAL",(M14*0.19),0) -> 0 | O14: =M14*1.19 -> 347078.68 | P14: =M14/S14 -> 315.65233 | Q14: =IF(L14="TOTAL",(P14*0.19),0) -> 0 | R14: =P14*1.19 -> 375.62628 | S14: =INDEX(FX!$D$3:$O$19,MATCH(B14,FX!$B$3:$B$32,0),MATCH(D14,FX!$D$2:$O$2,0)) -> 924 | T14: Monthly Commission | U14: Provision (Based on External Report) | V14: Invoice | W14: =VLOOKUP(I14,Map!$F$18:$H$51,3,0) -> Variable | X14: AP Completed | Y14: =VLOOKUP(L14,Map!$C$18:$D$29,2,0) -> DLT | Z14: 291662.76 | AA14: =IF(Y14="TOTAL",(Z14*0.19),0) -> 0 | AB14: =Z14*1.19 -> 347078.68 | AC14: =Z14/S14 -> 315.65233 | AD14: =IF(Y14="TOTAL",(AC14*0.19),0) -> 0 | AE14: =AC14*1.19 -> 375.62628
B15: 2026 | C15: JUN 21 to JUL 20 | D15: JUL | E15: JUL (Provision) | F15: AUG | G15: 46230 | H15: 478270 | I15: FALABELLA (DIRECT) | J15: =IFERROR(VLOOKUP(I15,Map!$F$18:$G$56,2,0),"Add in Map") -> 3P | K15: =VLOOKUP(L15,Map!$C$18:$D$29,2,0) -> DMT | L15: SAC | M15: 0 | N15: =IF(L15="TOTAL",(M15*0.19),0) -> 0 | O15: =M15*1.19 -> 0 | P15: 0 | Q15: =IF(L15="TOTAL",(P15*0.19),0) -> 0 | R15: =P15*1.19 -> 0 | S15: =INDEX(FX!$D$3:$O$19,MATCH(B15,FX!$B$3:$B$32,0),MATCH(D15,FX!$D$2:$O$2,0)) -> 924 | T15: Monthly Commission | U15: Provision (Based on External Report) | V15: Invoice | W15: =VLOOKUP(I15,Map!$F$18:$H$51,3,0) -> Variable | X15: AP Completed | Y15: =VLOOKUP(L15,Map!$C$18:$D$29,2,0) -> DMT | Z15: 0 | AA15: =IF(Y15="TOTAL",(Z15*0.19),0) -> 0 | AB15: =Z15*1.19 -> 0 | AC15: =Z15/S15 -> 0 | AD15: =IF(Y15="TOTAL",(AC15*0.19),0) -> 0 | AE15: =AC15*1.19 -> 0
B16: 2026 | C16: JUN 21 to JUL 20 | D16: JUL | E16: JUL (Provision) | F16: AUG | G16: 46230 | H16: 478270 | I16: FALABELLA (DIRECT) | J16: =IFERROR(VLOOKUP(I16,Map!$F$18:$G$56,2,0),"Add in Map") -> 3P | K16: =VLOOKUP(L16,Map!$C$18:$D$29,2,0) -> TOTAL | L16: TOTAL | M16: =SUM(M5:M15) -> 141164774 | N16: =IF(L16="TOTAL",(M16*0.19),0) -> 26821307 | O16: =M16*1.19 -> 1.6798608e+08 | P16: =M16/S16 -> 152775.73 | Q16: =IF(L16="TOTAL",(P16*0.19),0) -> 29027.389 | R16: =P16*1.19 -> 181803.12 | S16: =INDEX(FX!$D$3:$O$19,MATCH(B16,FX!$B$3:$B$32,0),MATCH(D16,FX!$D$2:$O$2,0)) -> 924 | T16: Monthly Commission | U16: Provision (Based on External Report) | V16: Invoice | W16: =VLOOKUP(I16,Map!$F$18:$H$51,3,0) -> Variable | X16: AP Completed | Y16: =VLOOKUP(L16,Map!$C$18:$D$29,2,0) -> TOTAL | Z16: =SUM(Z5:Z15) -> 141164774 | AA16: =IF(Y16="TOTAL",(Z16*0.19),0) -> 26821307 | AB16: =Z16*1.19 -> 1.6798608e+08 | AC16: =Z16/S16 -> 152775.73 | AD16: =IF(Y16="TOTAL",(AC16*0.19),0) -> 29027.389 | AE16: =AC16*1.19 -> 181803.12 | AF16: http://lg2607.acepta.com/v01/5E0A125A9F4EB54908C00523002399A4BD42D7F9
B17: 2026 | C17: JUN 21 to JUL 20 | D17: JUL | E17: JUL (Provision) | F17: AUG | G17: 46230 | H17: 456288 | I17: FALABELLA (DIRECT) | J17: =IFERROR(VLOOKUP(I17,Map!$F$18:$G$56,2,0),"Add in Map") -> 3P | K17: =VLOOKUP(L17,Map!$C$18:$D$29,2,0) -> CNT | L17: Refrigeration | M17: -10338484 | N17: =IF(L17="TOTAL",(M17*0.19),0) -> 0 | O17: =M17*1.19 -> -12302795 | P17: =M17/S17 -> -11188.835 | Q17: =IF(L17="TOTAL",(P17*0.19),0) -> 0 | R17: =P17*1.19 -> -13314.714 | S17: =INDEX(FX!$D$3:$O$19,MATCH(B17,FX!$B$3:$B$32,0),MATCH(D17,FX!$D$2:$O$2,0)) -> 924 | T17: Monthly Commission | U17: Provision (Based on External Report) | V17: Credit Note | W17: =VLOOKUP(I17,Map!$F$18:$H$51,3,0) -> Variable | X17: AP Completed | Y17: =VLOOKUP(L17,Map!$C$18:$D$29,2,0) -> CNT | Z17: -10338484 | AA17: =IF(Y17="TOTAL",(Z17*0.19),0) -> 0 | AB17: =Z17*1.19 -> -12302795 | AC17: =Z17/S17 -> -11188.835 | AD17: =IF(Y17="TOTAL",(AC17*0.19),0) -> 0 | AE17: =AC17*1.19 -> -13314.714
B18: 2026 | C18: JUN 21 to JUL 20 | D18: JUL | E18: JUL (Provision) | F18: AUG | G18: 46230 | H18: 456288 | I18: FALABELLA (DIRECT) | J18: =IFERROR(VLOOKUP(I18,Map!$F$18:$G$56,2,0),"Add in Map") -> 3P | K18: =VLOOKUP(L18,Map!$C$18:$D$29,2,0) -> CVT | L18: Cooking | M18: -122348.92 | N18: =IF(L18="TOTAL",(M18*0.19),0) -> 0 | O18: =M18*1.19 -> -145595.21 | P18: =M18/S18 -> -132.41225 | Q18: =IF(L18="TOTAL",(P18*0.19),0) -> 0 | R18: =P18*1.19 -> -157.57058 | S18: =INDEX(FX!$D$3:$O$19,MATCH(B18,FX!$B$3:$B$32,0),MATCH(D18,FX!$D$2:$O$2,0)) -> 924 | T18: Monthly Commission | U18: Provision (Based on External Report) | V18: Credit Note | W18: =VLOOKUP(I18,Map!$F$18:$H$51,3,0) -> Variable | X18: AP Completed | Y18: =VLOOKUP(L18,Map!$C$18:$D$29,2,0) -> CVT | Z18: -122348.92 | AA18: =IF(Y18="TOTAL",(Z18*0.19),0) -> 0 | AB18: =Z18*1.19 -> -145595.21 | AC18: =Z18/S18 -> -132.41225 | AD18: =IF(Y18="TOTAL",(AC18*0.19),0) -> 0 | AE18: =AC18*1.19 -> -157.57058
B19: 2026 | C19: JUN 21 to JUL 20 | D19: JUL | E19: JUL (Provision) | F19: AUG | G19: 46230 | H19: 456288 | I19: FALABELLA (DIRECT) | J19: =IFERROR(VLOOKUP(I19,Map!$F$18:$G$56,2,0),"Add in Map") -> 3P | K19: =VLOOKUP(L19,Map!$C$18:$D$29,2,0) -> CDT | L19: Dishwasher | M19: -428221.21 | N19: =IF(L19="TOTAL",(M19*0.19),0) -> 0 | O19: =M19*1.19 -> -509583.24 | P19: =M19/S19 -> -463.44287 | Q19: =IF(L19="TOTAL",(P19*0.19),0) -> 0 | R19: =P19*1.19 -> -551.49701 | S19: =INDEX(FX!$D$3:$O$19,MATCH(B19,FX!$B$3:$B$32,0),MATCH(D19,FX!$D$2:$O$2,0)) -> 924 | T19: Monthly Commission | U19: Provision (Based on External Report) | V19: Credit Note | W19: =VLOOKUP(I19,Map!$F$18:$H$51,3,0) -> Variable | X19: AP Completed | Y19: =VLOOKUP(L19,Map!$C$18:$D$29,2,0) -> CDT | Z19: -428221.21 | AA19: =IF(Y19="TOTAL",(Z19*0.19),0) -> 0 | AB19: =Z19*1.19 -> -509583.24 | AC19: =Z19/S19 -> -463.44287 | AD19: =IF(Y19="TOTAL",(AC19*0.19),0) -> 0 | AE19: =AC19*1.19 -> -551.49701
B20: 2026 | C20: JUN 21 to JUL 20 | D20: JUL | E20: JUL (Provision) | F20: AUG | G20: 46230 | H20: 456288 | I20: FALABELLA (DIRECT) | J20: =IFERROR(VLOOKUP(I20,Map!$F$18:$G$56,2,0),"Add in Map") -> 3P | K20: =VLOOKUP(L20,Map!$C$18:$D$29,2,0) -> DFT | L20: WM | M20: -30709578 | N20: =IF(L20="TOTAL",(M20*0.19),0) -> 0 | O20: =M20*1.19 -> -36544398 | P20: =M20/S20 -> -33235.474 | Q20: =IF(L20="TOTAL",(P20*0.19),0) -> 0 | R20: =P20*1.19 -> -39550.214 | S20: =INDEX(FX!$D$3:$O$19,MATCH(B20,FX!$B$3:$B$32,0),MATCH(D20,FX!$D$2:$O$2,0)) -> 924 | T20: Monthly Commission | U20: Provision (Based on External Report) | V20: Credit Note | W20: =VLOOKUP(I20,Map!$F$18:$H$51,3,0) -> Variable | X20: AP Completed | Y20: =VLOOKUP(L20,Map!$C$18:$D$29,2,0) -> DFT | Z20: -30709578 | AA20: =IF(Y20="TOTAL",(Z20*0.19),0) -> 0 | AB20: =Z20*1.19 -> -36544398 | AC20: =Z20/S20 -> -33235.474 | AD20: =IF(Y20="TOTAL",(AC20*0.19),0) -> 0 | AE20: =AC20*1.19 -> -39550.214
B21: 2026 | C21: JUN 21 to JUL 20 | D21: JUL | E21: JUL (Provision) | F21: AUG | G21: 46230 | H21: 456288 | I21: FALABELLA (DIRECT) | J21: =IFERROR(VLOOKUP(I21,Map!$F$18:$G$56,2,0),"Add in Map") -> 3P | K21: =VLOOKUP(L21,Map!$C$18:$D$29,2,0) -> DVT | L21: VCC | M21: -61174.459 | N21: =IF(L21="TOTAL",(M21*0.19),0) -> 0 | O21: =M21*1.19 -> -72797.606 | P21: =M21/S21 -> -66.206124 | Q21: =IF(L21="TOTAL",(P21*0.19),0) -> 0 | R21: =P21*1.19 -> -78.785288 | S21: =INDEX(FX!$D$3:$O$19,MATCH(B21,FX!$B$3:$B$32,0),MATCH(D21,FX!$D$2:$O$2,0)) -> 924 | T21: Monthly Commission | U21: Provision (Based on External Report) | V21: Credit Note | W21: =VLOOKUP(I21,Map!$F$18:$H$51,3,0) -> Variable | X21: AP Completed | Y21: =VLOOKUP(L21,Map!$C$18:$D$29,2,0) -> DVT | Z21: -61174.459 | AA21: =IF(Y21="TOTAL",(Z21*0.19),0) -> 0 | AB21: =Z21*1.19 -> -72797.606 | AC21: =Z21/S21 -> -66.206124 | AD21: =IF(Y21="TOTAL",(AC21*0.19),0) -> 0 | AE21: =AC21*1.19 -> -78.785288
B22: 2026 | C22: JUN 21 to JUL 20 | D22: JUL | E22: JUL (Provision) | F22: AUG | G22: 46230 | H22: 456288 | I22: FALABELLA (DIRECT) | J22: =IFERROR(VLOOKUP(I22,Map!$F$18:$G$56,2,0),"Add in Map") -> 3P | K22: =VLOOKUP(L22,Map!$C$18:$D$29,2,0) -> GLT | L22: Television | M22: -14559521 | N22: =IF(L22="TOTAL",(M22*0.19),0) -> 0 | O22: =M22*1.19 -> -17325830 | P22: =M22/S22 -> -15757.058 | Q22: =IF(L22="TOTAL",(P22*0.19),0) -> 0 | R22: =P22*1.19 -> -18750.898 | S22: =INDEX(FX!$D$3:$O$19,MATCH(B22,FX!$B$3:$B$32,0),MATCH(D22,FX!$D$2:$O$2,0)) -> 924 | T22: Monthly Commission | U22: Provision (Based on External Report) | V22: Credit Note | W22: =VLOOKUP(I22,Map!$F$18:$H$51,3,0) -> Variable | X22: AP Completed | Y22: =VLOOKUP(L22,Map!$C$18:$D$29,2,0) -> GLT | Z22: -14559521 | AA22: =IF(Y22="TOTAL",(Z22*0.19),0) -> 0 | AB22: =Z22*1.19 -> -17325830 | AC22: =Z22/S22 -> -15757.058 | AD22: =IF(Y22="TOTAL",(AC22*0.19),0) -> 0 | AE22: =AC22*1.19 -> -18750.898
B23: 2026 | C23: JUN 21 to JUL 20 | D23: JUL | E23: JUL (Provision) | F23: AUG | G23: 46230 | H23: 456288 | I23: FALABELLA (DIRECT) | J23: =IFERROR(VLOOKUP(I23,Map!$F$18:$G$56,2,0),"Add in Map") -> 3P | K23: =VLOOKUP(L23,Map!$C$18:$D$29,2,0) -> PNT | L23: Audio | M23: -917616.88 | N23: =IF(L23="TOTAL",(M23*0.19),0) -> 0 | O23: =M23*1.19 -> -1091964.1 | P23: =M23/S23 -> -993.09186 | Q23: =IF(L23="TOTAL",(P23*0.19),0) -> 0 | R23: =P23*1.19 -> -1181.7793 | S23: =INDEX(FX!$D$3:$O$19,MATCH(B23,FX!$B$3:$B$32,0),MATCH(D23,FX!$D$2:$O$2,0)) -> 924 | T23: Monthly Commission | U23: Provision (Based on External Report) | V23: Credit Note | W23: =VLOOKUP(I23,Map!$F$18:$H$51,3,0) -> Variable | X23: AP Completed | Y23: =VLOOKUP(L23,Map!$C$18:$D$29,2,0) -> PNT | Z23: -917616.88 | AA23: =IF(Y23="TOTAL",(Z23*0.19),0) -> 0 | AB23: =Z23*1.19 -> -1091964.1 | AC23: =Z23/S23 -> -993.09186 | AD23: =IF(Y23="TOTAL",(AC23*0.19),0) -> 0 | AE23: =AC23*1.19 -> -1181.7793
B24: 2026 | C24: JUN 21 to JUL 20 | D24: JUL | E24: JUL (Provision) | F24: AUG | G24: 46230 | H24: 456288 | I24: FALABELLA (DIRECT) | J24: =IFERROR(VLOOKUP(I24,Map!$F$18:$G$56,2,0),"Add in Map") -> 3P | K24: =VLOOKUP(L24,Map!$C$18:$D$29,2,0) -> GTT | L24: Monitor | M24: -1529361.5 | N24: =IF(L24="TOTAL",(M24*0.19),0) -> 0 | O24: =M24*1.19 -> -1819940.1 | P24: =M24/S24 -> -1655.1531 | Q24: =IF(L24="TOTAL",(P24*0.19),0) -> 0 | R24: =P24*1.19 -> -1969.6322 | S24: =INDEX(FX!$D$3:$O$19,MATCH(B24,FX!$B$3:$B$32,0),MATCH(D24,FX!$D$2:$O$2,0)) -> 924 | T24: Monthly Commission | U24: Provision (Based on External Report) | V24: Credit Note | W24: =VLOOKUP(I24,Map!$F$18:$H$51,3,0) -> Variable | X24: AP Completed | Y24: =VLOOKUP(L24,Map!$C$18:$D$29,2,0) -> GTT | Z24: -1529361.5 | AA24: =IF(Y24="TOTAL",(Z24*0.19),0) -> 0 | AB24: =Z24*1.19 -> -1819940.1 | AC24: =Z24/S24 -> -1655.1531 | AD24: =IF(Y24="TOTAL",(AC24*0.19),0) -> 0 | AE24: =AC24*1.19 -> -1969.6322
B25: 2026 | C25: JUN 21 to JUL 20 | D25: JUL | E25: JUL (Provision) | F25: AUG | G25: 46230 | H25: 456288 | I25: FALABELLA (DIRECT) | J25: =IFERROR(VLOOKUP(I25,Map!$F$18:$G$56,2,0),"Add in Map") -> 3P | K25: =VLOOKUP(L25,Map!$C$18:$D$29,2,0) -> DGT | L25: RAC | M25: -428221.21 | N25: =IF(L25="TOTAL",(M25*0.19),0) -> 0 | O25: =M25*1.19 -> -509583.24 | P25: =M25/S25 -> -463.44287 | Q25: =IF(L25="TOTAL",(P25*0.19),0) -> 0 | R25: =P25*1.19 -> -551.49701 | S25: =INDEX(FX!$D$3:$O$19,MATCH(B25,FX!$B$3:$B$32,0),MATCH(D25,FX!$D$2:$O$2,0)) -> 924 | T25: Monthly Commission | U25: Provision (Based on External Report) | V25: Credit Note | W25: =VLOOKUP(I25,Map!$F$18:$H$51,3,0) -> Variable | X25: AP Completed | Y25: =VLOOKUP(L25,Map!$C$18:$D$29,2,0) -> DGT | Z25: -428221.21 | AA25: =IF(Y25="TOTAL",(Z25*0.19),0) -> 0 | AB25: =Z25*1.19 -> -509583.24 | AC25: =Z25/S25 -> -463.44287 | AD25: =IF(Y25="TOTAL",(AC25*0.19),0) -> 0 | AE25: =AC25*1.19 -> -551.49701
B26: 2026 | C26: JUN 21 to JUL 20 | D26: JUL | E26: JUL (Provision) | F26: AUG | G26: 46230 | H26: 456288 | I26: FALABELLA (DIRECT) | J26: =IFERROR(VLOOKUP(I26,Map!$F$18:$G$56,2,0),"Add in Map") -> 3P | K26: =VLOOKUP(L26,Map!$C$18:$D$29,2,0) -> DLT | L26: Air Cleaner | M26: -122348.92 | N26: =IF(L26="TOTAL",(M26*0.19),0) -> 0 | O26: =M26*1.19 -> -145595.21 | P26: =M26/S26 -> -132.41225 | Q26: =IF(L26="TOTAL",(P26*0.19),0) -> 0 | R26: =P26*1.19 -> -157.57058 | S26: =INDEX(FX!$D$3:$O$19,MATCH(B26,FX!$B$3:$B$32,0),MATCH(D26,FX!$D$2:$O$2,0)) -> 924 | T26: Monthly Commission | U26: Provision (Based on External Report) | V26: Credit Note | W26: =VLOOKUP(I26,Map!$F$18:$H$51,3,0) -> Variable | X26: AP Completed | Y26: =VLOOKUP(L26,Map!$C$18:$D$29,2,0) -> DLT | Z26: -122348.92 | AA26: =IF(Y26="TOTAL",(Z26*0.19),0) -> 0 | AB26: =Z26*1.19 -> -145595.21 | AC26: =Z26/S26 -> -132.41225 | AD26: =IF(Y26="TOTAL",(AC26*0.19),0) -> 0 | AE26: =AC26*1.19 -> -157.57058
B27: 2026 | C27: JUN 21 to JUL 20 | D27: JUL | E27: JUL (Provision) | F27: AUG | G27: 46230 | H27: 456288 | I27: FALABELLA (DIRECT) | J27: =IFERROR(VLOOKUP(I27,Map!$F$18:$G$56,2,0),"Add in Map") -> 3P | K27: =VLOOKUP(L27,Map!$C$18:$D$29,2,0) -> DMT | L27: SAC | M27: 0 | N27: =IF(L27="TOTAL",(M27*0.19),0) -> 0 | O27: =M27*1.19 -> 0 | P27: =M27/S27 -> 0 | Q27: =IF(L27="TOTAL",(P27*0.19),0) -> 0 | R27: =P27*1.19 -> 0 | S27: =INDEX(FX!$D$3:$O$19,MATCH(B27,FX!$B$3:$B$32,0),MATCH(D27,FX!$D$2:$O$2,0)) -> 924 | T27: Monthly Commission | U27: Provision (Based on External Report) | V27: Credit Note | W27: =VLOOKUP(I27,Map!$F$18:$H$51,3,0) -> Variable | X27: AP Completed | Y27: =VLOOKUP(L27,Map!$C$18:$D$29,2,0) -> DMT | Z27: 0 | AA27: =IF(Y27="TOTAL",(Z27*0.19),0) -> 0 | AB27: =Z27*1.19 -> 0 | AC27: =Z27/S27 -> 0 | AD27: =IF(Y27="TOTAL",(AC27*0.19),0) -> 0 | AE27: =AC27*1.19 -> 0
B28: 2026 | C28: JUN 21 to JUL 20 | D28: JUL | E28: JUL (Provision) | F28: AUG | G28: 46230 | H28: 456288 | I28: FALABELLA (DIRECT) | J28: =IFERROR(VLOOKUP(I28,Map!$F$18:$G$56,2,0),"Add in Map") -> 3P | K28: =VLOOKUP(L28,Map!$C$18:$D$29,2,0) -> TOTAL | L28: TOTAL | M28: =SUM(M17:M27) -> -59216876 | N28: =IF(L28="TOTAL",(M28*0.19),0) -> -11251206 | O28: =M28*1.19 -> -70468082 | P28: =M28/S28 -> -64087.528 | Q28: =IF(L28="TOTAL",(P28*0.19),0) -> -12176.63 | R28: =P28*1.19 -> -76264.158 | S28: =INDEX(FX!$D$3:$O$19,MATCH(B28,FX!$B$3:$B$32,0),MATCH(D28,FX!$D$2:$O$2,0)) -> 924 | T28: Monthly Commission | U28: Provision (Based on External Report) | V28: Credit Note | W28: =VLOOKUP(I28,Map!$F$18:$H$51,3,0) -> Variable | X28: AP Completed | Y28: =VLOOKUP(L28,Map!$C$18:$D$29,2,0) -> TOTAL | Z28: =SUM(Z17:Z27) -> -59216876 | AA28: =IF(Y28="TOTAL",(Z28*0.19),0) -> -11251206 | AB28: =Z28*1.19 -> -70468082 | AC28: =Z28/S28 -> -64087.528 | AD28: =IF(Y28="TOTAL",(AC28*0.19),0) -> -12176.63 | AE28: =AC28*1.19 -> -76264.158 | AF28: http://lg2607.acepta.com/v01/AD2F1E54CFEE4EA8AEAAF32C8EE536D5DD0B56A6
B29: 2026 | C29: MAY 21 to JUN 20 | D29: JUN | E29: JUL (Provision) | F29: AUG | G29: 46196 | H29: 473180 | I29: FALABELLA (DIRECT) | J29: =IFERROR(VLOOKUP(I29,Map!$F$18:$G$56,2,0),"Add in Map") -> 3P | K29: =VLOOKUP(L29,Map!$C$18:$D$29,2,0) -> CNT | L29: Refrigeration | M29: 46857021 | N29: =IF(L29="TOTAL",(M29*0.19),0) -> 0 | O29: =M29*1.19 -> 55759855 | P29: =M29/S29 -> 50766.004 | Q29: =IF(L29="TOTAL",(P29*0.19),0) -> 0 | R29: =P29*1.19 -> 60411.544 | S29: =INDEX(FX!$D$3:$O$19,MATCH(B29,FX!$B$3:$B$32,0),MATCH(D29,FX!$D$2:$O$2,0)) -> 923 | T29: Monthly Commission | U29: Provision (Based on External Report) | V29: Invoice | W29: =VLOOKUP(I29,Map!$F$18:$H$51,3,0) -> Variable | X29: AP Completed | Y29: =VLOOKUP(L29,Map!$C$18:$D$29,2,0) -> CNT | AA29: =IF(Y29="TOTAL",(Z29*0.19),0) -> 0 | AB29: =Z29*1.19 -> 0 | AC29: =Z29/S29 -> 0 | AD29: =IF(Y29="TOTAL",(AC29*0.19),0) -> 0 | AE29: =AC29*1.19 -> 0
B30: 2026 | C30: MAY 21 to JUN 20 | D30: JUN | E30: JUL (Provision) | F30: AUG | G30: 46196 | H30: 473180 | I30: FALABELLA (DIRECT) | J30: =IFERROR(VLOOKUP(I30,Map!$F$18:$G$56,2,0),"Add in Map") -> 3P | K30: =VLOOKUP(L30,Map!$C$18:$D$29,2,0) -> CVT | L30: Cooking | M30: 955756.65 | N30: =IF(L30="TOTAL",(M30*0.19),0) -> 0 | O30: =M30*1.19 -> 1137350.4 | P30: =M30/S30 -> 1035.4893 | Q30: =IF(L30="TOTAL",(P30*0.19),0) -> 0 | R30: =P30*1.19 -> 1232.2323 | S30: =INDEX(FX!$D$3:$O$19,MATCH(B30,FX!$B$3:$B$32,0),MATCH(D30,FX!$D$2:$O$2,0)) -> 923 | T30: Monthly Commission | U30: Provision (Based on External Report) | V30: Invoice | W30: =VLOOKUP(I30,Map!$F$18:$H$51,3,0) -> Variable | X30: AP Completed | Y30: =VLOOKUP(L30,Map!$C$18:$D$29,2,0) -> CVT | AA30: =IF(Y30="TOTAL",(Z30*0.19),0) -> 0 | AB30: =Z30*1.19 -> 0 | AC30: =Z30/S30 -> 0 | AD30: =IF(Y30="TOTAL",(AC30*0.19),0) -> 0 | AE30: =AC30*1.19 -> 0
B31: 2026 | C31: MAY 21 to JUN 20 | D31: JUN | E31: JUL (Provision) | F31: AUG | G31: 46196 | H31: 473180 | I31: FALABELLA (DIRECT) | J31: =IFERROR(VLOOKUP(I31,Map!$F$18:$G$56,2,0),"Add in Map") -> 3P | K31: =VLOOKUP(L31,Map!$C$18:$D$29,2,0) -> CDT | L31: Dishwasher | M31: 3929528.6 | N31: =IF(L31="TOTAL",(M31*0.19),0) -> 0 | O31: =M31*1.19 -> 4676139.1 | P31: =M31/S31 -> 4257.3441 | Q31: =IF(L31="TOTAL",(P31*0.19),0) -> 0 | R31: =P31*1.19 -> 5066.2395 | S31: =INDEX(FX!$D$3:$O$19,MATCH(B31,FX!$B$3:$B$32,0),MATCH(D31,FX!$D$2:$O$2,0)) -> 923 | T31: Monthly Commission | U31: Provision (Based on External Report) | V31: Invoice | W31: =VLOOKUP(I31,Map!$F$18:$H$51,3,0) -> Variable | X31: AP Completed | Y31: =VLOOKUP(L31,Map!$C$18:$D$29,2,0) -> CDT | AA31: =IF(Y31="TOTAL",(Z31*0.19),0) -> 0 | AB31: =Z31*1.19 -> 0 | AC31: =Z31/S31 -> 0 | AD31: =IF(Y31="TOTAL",(AC31*0.19),0) -> 0 | AE31: =AC31*1.19 -> 0
B32: 2026 | C32: MAY 21 to JUN 20 | D32: JUN | E32: JUL (Provision) | F32: AUG | G32: 46196 | H32: 473180 | I32: FALABELLA (DIRECT) | J32: =IFERROR(VLOOKUP(I32,Map!$F$18:$G$56,2,0),"Add in Map") -> 3P | K32: =VLOOKUP(L32,Map!$C$18:$D$29,2,0) -> DFT | L32: WM | M32: 1.0146909e+08 | N32: =IF(L32="TOTAL",(M32*0.19),0) -> 0 | O32: =M32*1.19 -> 1.2074822e+08 | P32: =M32/S32 -> 109934.01 | Q32: =IF(L32="TOTAL",(P32*0.19),0) -> 0 | R32: =P32*1.19 -> 130821.47 | S32: =INDEX(FX!$D$3:$O$19,MATCH(B32,FX!$B$3:$B$32,0),MATCH(D32,FX!$D$2:$O$2,0)) -> 923 | T32: Monthly Commission | U32: Provision (Based on External Report) | V32: Invoice | W32: =VLOOKUP(I32,Map!$F$18:$H$51,3,0) -> Variable | X32: AP Completed | Y32: =VLOOKUP(L32,Map!$C$18:$D$29,2,0) -> DFT | AA32: =IF(Y32="TOTAL",(Z32*0.19),0) -> 0 | AB32: =Z32*1.19 -> 0 | AC32: =Z32/S32 -> 0 | AD32: =IF(Y32="TOTAL",(AC32*0.19),0) -> 0 | AE32: =AC32*1.19 -> 0
B33: 2026 | C33: MAY 21 to JUN 20 | D33: JUN | E33: JUL (Provision) | F33: AUG | G33: 46196 | H33: 473180 | I33: FALABELLA (DIRECT) | J33: =IFERROR(VLOOKUP(I33,Map!$F$18:$G$56,2,0),"Add in Map") -> 3P | K33: =VLOOKUP(L33,Map!$C$18:$D$29,2,0) -> DVT | L33: VCC | M33: 444230.15 | N33: =IF(L33="TOTAL",(M33*0.19),0) -> 0 | O33: =M33*1.19 -> 528633.88 | P33: =M33/S33 -> 481.28944 | Q33: =IF(L33="TOTAL",(P33*0.19),0) -> 0 | R33: =P33*1.19 -> 572.73443 | S33: =INDEX(FX!$D$3:$O$19,MATCH(B33,FX!$B$3:$B$32,0),MATCH(D33,FX!$D$2:$O$2,0)) -> 923 | T33: Monthly Commission | U33: Provision (Based on External Report) | V33: Invoice | W33: =VLOOKUP(I33,Map!$F$18:$H$51,3,0) -> Variable | X33: AP Completed | Y33: =VLOOKUP(L33,Map!$C$18:$D$29,2,0) -> DVT | AA33: =IF(Y33="TOTAL",(Z33*0.19),0) -> 0 | AB33: =Z33*1.19 -> 0 | AC33: =Z33/S33 -> 0 | AD33: =IF(Y33="TOTAL",(AC33*0.19),0) -> 0 | AE33: =AC33*1.19 -> 0
B34: 2026 | C34: MAY 21 to JUN 20 | D34: JUN | E34: JUL (Provision) | F34: AUG | G34: 46196 | H34: 473180 | I34: FALABELLA (DIRECT) | J34: =IFERROR(VLOOKUP(I34,Map!$F$18:$G$56,2,0),"Add in Map") -> 3P | K34: =VLOOKUP(L34,Map!$C$18:$D$29,2,0) -> GLT | L34: Television | M34: 80299365 | N34: =IF(L34="TOTAL",(M34*0.19),0) -> 0 | O34: =M34*1.19 -> 95556245 | P34: =M34/S34 -> 86998.229 | Q34: =IF(L34="TOTAL",(P34*0.19),0) -> 0 | R34: =P34*1.19 -> 103527.89 | S34: =INDEX(FX!$D$3:$O$19,MATCH(B34,FX!$B$3:$B$32,0),MATCH(D34,FX!$D$2:$O$2,0)) -> 923 | T34: Monthly Commission | U34: Provision (Based on External Report) | V34: Invoice | W34: =VLOOKUP(I34,Map!$F$18:$H$51,3,0) -> Variable | X34: AP Completed | Y34: =VLOOKUP(L34,Map!$C$18:$D$29,2,0) -> GLT | AA34: =IF(Y34="TOTAL",(Z34*0.19),0) -> 0 | AB34: =Z34*1.19 -> 0 | AC34: =Z34/S34 -> 0 | AD34: =IF(Y34="TOTAL",(AC34*0.19),0) -> 0 | AE34: =AC34*1.19 -> 0
B35: 2026 | C35: MAY 21 to JUN 20 | D35: JUN | E35: JUL (Provision) | F35: AUG | G35: 46196 | H35: 473180 | I35: FALABELLA (DIRECT) | J35: =IFERROR(VLOOKUP(I35,Map!$F$18:$G$56,2,0),"Add in Map") -> 3P | K35: =VLOOKUP(L35,Map!$C$18:$D$29,2,0) -> PNT | L35: Audio | M35: 4357553.2 | N35: =IF(L35="TOTAL",(M35*0.19),0) -> 0 | O35: =M35*1.19 -> 5185488.3 | P35: =M35/S35 -> 4721.0761 | Q35: =IF(L35="TOTAL",(P35*0.19),0) -> 0 | R35: =P35*1.19 -> 5618.0805 | S35: =INDEX(FX!$D$3:$O$19,MATCH(B35,FX!$B$3:$B$32,0),MATCH(D35,FX!$D$2:$O$2,0)) -> 923 | T35: Monthly Commission | U35: Provision (Based on External Report) | V35: Invoice | W35: =VLOOKUP(I35,Map!$F$18:$H$51,3,0) -> Variable | X35: AP Completed | Y35: =VLOOKUP(L35,Map!$C$18:$D$29,2,0) -> PNT | AA35: =IF(Y35="TOTAL",(Z35*0.19),0) -> 0 | AB35: =Z35*1.19 -> 0 | AC35: =Z35/S35 -> 0 | AD35: =IF(Y35="TOTAL",(AC35*0.19),0) -> 0 | AE35: =AC35*1.19 -> 0
B36: 2026 | C36: MAY 21 to JUN 20 | D36: JUN | E36: JUL (Provision) | F36: AUG | G36: 46196 | H36: 473180 | I36: FALABELLA (DIRECT) | J36: =IFERROR(VLOOKUP(I36,Map!$F$18:$G$56,2,0),"Add in Map") -> 3P | K36: =VLOOKUP(L36,Map!$C$18:$D$29,2,0) -> GTT | L36: Monitor | M36: 8665554.5 | N36: =IF(L36="TOTAL",(M36*0.19),0) -> 0 | O36: =M36*1.19 -> 10312010 | P36: =M36/S36 -> 9388.4664 | Q36: =IF(L36="TOTAL",(P36*0.19),0) -> 0 | R36: =P36*1.19 -> 11172.275 | S36: =INDEX(FX!$D$3:$O$19,MATCH(B36,FX!$B$3:$B$32,0),MATCH(D36,FX!$D$2:$O$2,0)) -> 923 | T36: Monthly Commission | U36: Provision (Based on External Report) | V36: Invoice | W36: =VLOOKUP(I36,Map!$F$18:$H$51,3,0) -> Variable | X36: AP Completed | Y36: =VLOOKUP(L36,Map!$C$18:$D$29,2,0) -> GTT | AA36: =IF(Y36="TOTAL",(Z36*0.19),0) -> 0 | AB36: =Z36*1.19 -> 0 | AC36: =Z36/S36 -> 0 | AD36: =IF(Y36="TOTAL",(AC36*0.19),0) -> 0 | AE36: =AC36*1.19 -> 0
B37: 2026 | C37: MAY 21 to JUN 20 | D37: JUN | E37: JUL (Provision) | F37: AUG | G37: 46196 | H37: 473180 | I37: FALABELLA (DIRECT) | J37: =IFERROR(VLOOKUP(I37,Map!$F$18:$G$56,2,0),"Add in Map") -> 3P | K37: =VLOOKUP(L37,Map!$C$18:$D$29,2,0) -> DGT | L37: RAC | M37: 3213667.7 | N37: =IF(L37="TOTAL",(M37*0.19),0) -> 0 | O37: =M37*1.19 -> 3824264.6 | P37: =M37/S37 -> 3481.7635 | Q37: =IF(L37="TOTAL",(P37*0.19),0) -> 0 | R37: =P37*1.19 -> 4143.2986 | S37: =INDEX(FX!$D$3:$O$19,MATCH(B37,FX!$B$3:$B$32,0),MATCH(D37,FX!$D$2:$O$2,0)) -> 923 | T37: Monthly Commission | U37: Provision (Based on External Report) | V37: Invoice | W37: =VLOOKUP(I37,Map!$F$18:$H$51,3,0) -> Variable | X37: AP Completed | Y37: =VLOOKUP(L37,Map!$C$18:$D$29,2,0) -> DGT | AA37: =IF(Y37="TOTAL",(Z37*0.19),0) -> 0 | AB37: =Z37*1.19 -> 0 | AC37: =Z37/S37 -> 0 | AD37: =IF(Y37="TOTAL",(AC37*0.19),0) -> 0 | AE37: =AC37*1.19 -> 0
B38: 2026 | C38: MAY 21 to JUN 20 | D38: JUN | E38: JUL (Provision) | F38: AUG | G38: 46196 | H38: 473180 | I38: FALABELLA (DIRECT) | J38: =IFERROR(VLOOKUP(I38,Map!$F$18:$G$56,2,0),"Add in Map") -> 3P | K38: =VLOOKUP(L38,Map!$C$18:$D$29,2,0) -> DLT | L38: Air Cleaner | M38: 1618812.9 | N38: =IF(L38="TOTAL",(M38*0.19),0) -> 0 | O38: =M38*1.19 -> 1926387.4 | P38: =M38/S38 -> 1753.8601 | Q38: =IF(L38="TOTAL",(P38*0.19),0) -> 0 | R38: =P38*1.19 -> 2087.0936 | S38: =INDEX(FX!$D$3:$O$19,MATCH(B38,FX!$B$3:$B$32,0),MATCH(D38,FX!$D$2:$O$2,0)) -> 923 | T38: Monthly Commission | U38: Provision (Based on External Report) | V38: Invoice | W38: =VLOOKUP(I38,Map!$F$18:$H$51,3,0) -> Variable | X38: AP Completed | Y38: =VLOOKUP(L38,Map!$C$18:$D$29,2,0) -> DLT | AA38: =IF(Y38="TOTAL",(Z38*0.19),0) -> 0 | AB38: =Z38*1.19 -> 0 | AC38: =Z38/S38 -> 0 | AD38: =IF(Y38="TOTAL",(AC38*0.19),0) -> 0 | AE38: =AC38*1.19 -> 0
B39: 2026 | C39: MAY 21 to JUN 20 | D39: JUN | E39: JUL (Provision) | F39: AUG | G39: 46196 | H39: 473180 | I39: FALABELLA (DIRECT) | J39: =IFERROR(VLOOKUP(I39,Map!$F$18:$G$56,2,0),"Add in Map") -> 3P | K39: =VLOOKUP(L39,Map!$C$18:$D$29,2,0) -> DMT | L39: SAC | M39: 0 | N39: =IF(L39="TOTAL",(M39*0.19),0) -> 0 | O39: =M39*1.19 -> 0 | P39: =M39/S39 -> 0 | Q39: =IF(L39="TOTAL",(P39*0.19),0) -> 0 | R39: =P39*1.19 -> 0 | S39: =INDEX(FX!$D$3:$O$19,MATCH(B39,FX!$B$3:$B$32,0),MATCH(D39,FX!$D$2:$O$2,0)) -> 923 | T39: Monthly Commission | U39: Provision (Based on External Report) | V39: Invoice | W39: =VLOOKUP(I39,Map!$F$18:$H$51,3,0) -> Variable | X39: AP Completed | Y39: =VLOOKUP(L39,Map!$C$18:$D$29,2,0) -> DMT | AA39: =IF(Y39="TOTAL",(Z39*0.19),0) -> 0 | AB39: =Z39*1.19 -> 0 | AC39: =Z39/S39 -> 0 | AD39: =IF(Y39="TOTAL",(AC39*0.19),0) -> 0 | AE39: =AC39*1.19 -> 0
B40: 2026 | C40: MAY 21 to JUN 20 | D40: JUN | E40: JUL (Provision) | F40: AUG | G40: 46196 | H40: 473180 | I40: FALABELLA (DIRECT) | J40: =IFERROR(VLOOKUP(I40,Map!$F$18:$G$56,2,0),"Add in Map") -> 3P | K40: =VLOOKUP(L40,Map!$C$18:$D$29,2,0) -> TOTAL | L40: TOTAL | M40: =SUM(M29:M39) -> 2.5181058e+08 | N40: =IF(L40="TOTAL",(M40*0.19),0) -> 47844011 | O40: =M40*1.19 -> 2.9965459e+08 | P40: =M40/S40 -> 272817.53 | Q40: =IF(L40="TOTAL",(P40*0.19),0) -> 51835.331 | R40: =P40*1.19 -> 324652.86 | S40: =INDEX(FX!$D$3:$O$19,MATCH(B40,FX!$B$3:$B$32,0),MATCH(D40,FX!$D$2:$O$2,0)) -> 923 | T40: Monthly Commission | U40: Provision (Based on External Report) | V40: Invoice | W40: =VLOOKUP(I40,Map!$F$18:$H$51,3,0) -> Variable | X40: AP Completed | Y40: =VLOOKUP(L40,Map!$C$18:$D$29,2,0) -> TOTAL | AA40: =IF(Y40="TOTAL",(Z40*0.19),0) -> 0 | AB40: =Z40*1.19 -> 0 | AC40: =Z40/S40 -> 0 | AD40: =IF(Y40="TOTAL",(AC40*0.19),0) -> 0 | AE40: =AC40*1.19 -> 0
B41: 2026 | C41: MAY 21 to JUN 20 | D41: JUN | E41: JUL (Provision) | F41: AUG | G41: 46196 | H41: 432245 | I41: FALABELLA (DIRECT) | J41: =IFERROR(VLOOKUP(I41,Map!$F$18:$G$56,2,0),"Add in Map") -> 3P | K41: =VLOOKUP(L41,Map!$C$18:$D$29,2,0) -> CNT | L41: Refrigeration | M41: -18530453 | N41: =IF(L41="TOTAL",(M41*0.19),0) -> 0 | O41: =M41*1.19 -> -22051239 | P41: =M41/S41 -> -20076.33 | Q41: =IF(L41="TOTAL",(P41*0.19),0) -> 0 | R41: =P41*1.19 -> -23890.833 | S41: =INDEX(FX!$D$3:$O$19,MATCH(B41,FX!$B$3:$B$32,0),MATCH(D41,FX!$D$2:$O$2,0)) -> 923 | T41: Monthly Commission | U41: Provision (Based on External Report) | V41: Credit Note | W41: =VLOOKUP(I41,Map!$F$18:$H$51,3,0) -> Variable | X41: AP Completed | Y41: =VLOOKUP(L41,Map!$C$18:$D$29,2,0) -> CNT | AA41: =IF(Y41="TOTAL",(Z41*0.19),0) -> 0 | AB41: =Z41*1.19 -> 0 | AC41: =Z41/S41 -> 0 | AD41: =IF(Y41="TOTAL",(AC41*0.19),0) -> 0 | AE41: =AC41*1.19 -> 0
B42: 2026 | C42: MAY 21 to JUN 20 | D42: JUN | E42: JUL (Provision) | F42: AUG | G42: 46196 | H42: 432245 | I42: FALABELLA (DIRECT) | J42: =IFERROR(VLOOKUP(I42,Map!$F$18:$G$56,2,0),"Add in Map") -> 3P | K42: =VLOOKUP(L42,Map!$C$18:$D$29,2,0) -> CVT | L42: Cooking | M42: -377971.18 | N42: =IF(L42="TOTAL",(M42*0.19),0) -> 0 | O42: =M42*1.19 -> -449785.7 | P42: =M42/S42 -> -409.5029 | Q42: =IF(L42="TOTAL",(P42*0.19),0) -> 0 | R42: =P42*1.19 -> -487.30845 | S42: =INDEX(FX!$D$3:$O$19,MATCH(B42,FX!$B$3:$B$32,0),MATCH(D42,FX!$D$2:$O$2,0)) -> 923 | T42: Monthly Commission | U42: Provision (Based on External Report) | V42: Credit Note | W42: =VLOOKUP(I42,Map!$F$18:$H$51,3,0) -> Variable | X42: AP Completed | Y42: =VLOOKUP(L42,Map!$C$18:$D$29,2,0) -> CVT | AA42: =IF(Y42="TOTAL",(Z42*0.19),0) -> 0 | AB42: =Z42*1.19 -> 0 | AC42: =Z42/S42 -> 0 | AD42: =IF(Y42="TOTAL",(AC42*0.19),0) -> 0 | AE42: =AC42*1.19 -> 0
B43: 2026 | C43: MAY 21 to JUN 20 | D43: JUN | E43: JUL (Provision) | F43: AUG | G43: 46196 | H43: 432245 | I43: FALABELLA (DIRECT) | J43: =IFERROR(VLOOKUP(I43,Map!$F$18:$G$56,2,0),"Add in Map") -> 3P | K43: =VLOOKUP(L43,Map!$C$18:$D$29,2,0) -> CDT | L43: Dishwasher | M43: -1554002.9 | N43: =IF(L43="TOTAL",(M43*0.19),0) -> 0 | O43: =M43*1.19 -> -1849263.4 | P43: =M43/S43 -> -1683.6434 | Q43: =IF(L43="TOTAL",(P43*0.19),0) -> 0 | R43: =P43*1.19 -> -2003.5357 | S43: =INDEX(FX!$D$3:$O$19,MATCH(B43,FX!$B$3:$B$32,0),MATCH(D43,FX!$D$2:$O$2,0)) -> 923 | T43: Monthly Commission | U43: Provision (Based on External Report) | V43: Credit Note | W43: =VLOOKUP(I43,Map!$F$18:$H$51,3,0) -> Variable | X43: AP Completed | Y43: =VLOOKUP(L43,Map!$C$18:$D$29,2,0) -> CDT | AA43: =IF(Y43="TOTAL",(Z43*0.19),0) -> 0 | AB43: =Z43*1.19 -> 0 | AC43: =Z43/S43 -> 0 | AD43: =IF(Y43="TOTAL",(AC43*0.19),0) -> 0 | AE43: =AC43*1.19 -> 0
B44: 2026 | C44: MAY 21 to JUN 20 | D44: JUN | E44: JUL (Provision) | F44: AUG | G44: 46196 | H44: 432245 | I44: FALABELLA (DIRECT) | J44: =IFERROR(VLOOKUP(I44,Map!$F$18:$G$56,2,0),"Add in Map") -> 3P | K44: =VLOOKUP(L44,Map!$C$18:$D$29,2,0) -> DFT | L44: WM | M44: -40127779 | N44: =IF(L44="TOTAL",(M44*0.19),0) -> 0 | O44: =M44*1.19 -> -47752057 | P44: =M44/S44 -> -43475.384 | Q44: =IF(L44="TOTAL",(P44*0.19),0) -> 0 | R44: =P44*1.19 -> -51735.707 | S44: =INDEX(FX!$D$3:$O$19,MATCH(B44,FX!$B$3:$B$32,0),MATCH(D44,FX!$D$2:$O$2,0)) -> 923 | T44: Monthly Commission | U44: Provision (Based on External Report) | V44: Credit Note | W44: =VLOOKUP(I44,Map!$F$18:$H$51,3,0) -> Variable | X44: AP Completed | Y44: =VLOOKUP(L44,Map!$C$18:$D$29,2,0) -> DFT | AA44: =IF(Y44="TOTAL",(Z44*0.19),0) -> 0 | AB44: =Z44*1.19 -> 0 | AC44: =Z44/S44 -> 0 | AD44: =IF(Y44="TOTAL",(AC44*0.19),0) -> 0 | AE44: =AC44*1.19 -> 0
B45: 2026 | C45: MAY 21 to JUN 20 | D45: JUN | E45: JUL (Provision) | F45: AUG | G45: 46196 | H45: 432245 | I45: FALABELLA (DIRECT) | J45: =IFERROR(VLOOKUP(I45,Map!$F$18:$G$56,2,0),"Add in Map") -> 3P | K45: =VLOOKUP(L45,Map!$C$18:$D$29,2,0) -> DVT | L45: VCC | M45: -175678.81 | N45: =IF(L45="TOTAL",(M45*0.19),0) -> 0 | O45: =M45*1.19 -> -209057.79 | P45: =M45/S45 -> -190.33458 | Q45: =IF(L45="TOTAL",(P45*0.19),0) -> 0 | R45: =P45*1.19 -> -226.49815 | S45: =INDEX(FX!$D$3:$O$19,MATCH(B45,FX!$B$3:$B$32,0),MATCH(D45,FX!$D$2:$O$2,0)) -> 923 | T45: Monthly Commission | U45: Provision (Based on External Report) | V45: Credit Note | W45: =VLOOKUP(I45,Map!$F$18:$H$51,3,0) -> Variable | X45: AP Completed | Y45: =VLOOKUP(L45,Map!$C$18:$D$29,2,0) -> DVT | AA45: =IF(Y45="TOTAL",(Z45*0.19),0) -> 0 | AB45: =Z45*1.19 -> 0 | AC45: =Z45/S45 -> 0 | AD45: =IF(Y45="TOTAL",(AC45*0.19),0) -> 0 | AE45: =AC45*1.19 -> 0
B46: 2026 | C46: MAY 21 to JUN 20 | D46: JUN | E46: JUL (Provision) | F46: AUG | G46: 46196 | H46: 432245 | I46: FALABELLA (DIRECT) | J46: =IFERROR(VLOOKUP(I46,Map!$F$18:$G$56,2,0),"Add in Map") -> 3P | K46: =VLOOKUP(L46,Map!$C$18:$D$29,2,0) -> GLT | L46: Television | M46: -31755830 | N46: =IF(L46="TOTAL",(M46*0.19),0) -> 0 | O46: =M46*1.19 -> -37789438 | P46: =M46/S46 -> -34405.016 | Q46: =IF(L46="TOTAL",(P46*0.19),0) -> 0 | R46: =P46*1.19 -> -40941.969 | S46: =INDEX(FX!$D$3:$O$19,MATCH(B46,FX!$B$3:$B$32,0),MATCH(D46,FX!$D$2:$O$2,0)) -> 923 | T46: Monthly Commission | U46: Provision (Based on External Report) | V46: Credit Note | W46: =VLOOKUP(I46,Map!$F$18:$H$51,3,0) -> Variable | X46: AP Completed | Y46: =VLOOKUP(L46,Map!$C$18:$D$29,2,0) -> GLT | AA46: =IF(Y46="TOTAL",(Z46*0.19),0) -> 0 | AB46: =Z46*1.19 -> 0 | AC46: =Z46/S46 -> 0 | AD46: =IF(Y46="TOTAL",(AC46*0.19),0) -> 0 | AE46: =AC46*1.19 -> 0
B47: 2026 | C47: MAY 21 to JUN 20 | D47: JUN | E47: JUL (Provision) | F47: AUG | G47: 46196 | H47: 432245 | I47: FALABELLA (DIRECT) | J47: =IFERROR(VLOOKUP(I47,Map!$F$18:$G$56,2,0),"Add in Map") -> 3P | K47: =VLOOKUP(L47,Map!$C$18:$D$29,2,0) -> PNT | L47: Audio | M47: -1723272.9 | N47: =IF(L47="TOTAL",(M47*0.19),0) -> 0 | O47: =M47*1.19 -> -2050694.7 | P47: =M47/S47 -> -1867.0346 | Q47: =IF(L47="TOTAL",(P47*0.19),0) -> 0 | R47: =P47*1.19 -> -2221.7711 | S47: =INDEX(FX!$D$3:$O$19,MATCH(B47,FX!$B$3:$B$32,0),MATCH(D47,FX!$D$2:$O$2,0)) -> 923 | T47: Monthly Commission | U47: Provision (Based on External Report) | V47: Credit Note | W47: =VLOOKUP(I47,Map!$F$18:$H$51,3,0) -> Variable | X47: AP Completed | Y47: =VLOOKUP(L47,Map!$C$18:$D$29,2,0) -> PNT | AA47: =IF(Y47="TOTAL",(Z47*0.19),0) -> 0 | AB47: =Z47*1.19 -> 0 | AC47: =Z47/S47 -> 0 | AD47: =IF(Y47="TOTAL",(AC47*0.19),0) -> 0 | AE47: =AC47*1.19 -> 0
B48: 2026 | C48: MAY 21 to JUN 20 | D48: JUN | E48: JUL (Provision) | F48: AUG | G48: 46196 | H48: 432245 | I48: FALABELLA (DIRECT) | J48: =IFERROR(VLOOKUP(I48,Map!$F$18:$G$56,2,0),"Add in Map") -> 3P | K48: =VLOOKUP(L48,Map!$C$18:$D$29,2,0) -> GTT | L48: Monitor | M48: -3426949.6 | N48: =IF(L48="TOTAL",(M48*0.19),0) -> 0 | O48: =M48*1.19 -> -4078070 | P48: =M48/S48 -> -3712.8381 | Q48: =IF(L48="TOTAL",(P48*0.19),0) -> 0 | R48: =P48*1.19 -> -4418.2773 | S48: =INDEX(FX!$D$3:$O$19,MATCH(B48,FX!$B$3:$B$32,0),MATCH(D48,FX!$D$2:$O$2,0)) -> 923 | T48: Monthly Commission | U48: Provision (Based on External Report) | V48: Credit Note | W48: =VLOOKUP(I48,Map!$F$18:$H$51,3,0) -> Variable | X48: AP Completed | Y48: =VLOOKUP(L48,Map!$C$18:$D$29,2,0) -> GTT | AA48: =IF(Y48="TOTAL",(Z48*0.19),0) -> 0 | AB48: =Z48*1.19 -> 0 | AC48: =Z48/S48 -> 0 | AD48: =IF(Y48="TOTAL",(AC48*0.19),0) -> 0 | AE48: =AC48*1.19 -> 0
B49: 2026 | C49: MAY 21 to JUN 20 | D49: JUN | E49: JUL (Provision) | F49: AUG | G49: 46196 | H49: 432245 | I49: FALABELLA (DIRECT) | J49: =IFERROR(VLOOKUP(I49,Map!$F$18:$G$56,2,0),"Add in Map") -> 3P | K49: =VLOOKUP(L49,Map!$C$18:$D$29,2,0) -> DGT | L49: RAC | M49: -1270902.8 | N49: =IF(L49="TOTAL",(M49*0.19),0) -> 0 | O49: =M49*1.19 -> -1512374.3 | P49: =M49/S49 -> -1376.9261 | Q49: =IF(L49="TOTAL",(P49*0.19),0) -> 0 | R49: =P49*1.19 -> -1638.542 | S49: =INDEX(FX!$D$3:$O$19,MATCH(B49,FX!$B$3:$B$32,0),MATCH(D49,FX!$D$2:$O$2,0)) -> 923 | T49: Monthly Commission | U49: Provision (Based on External Report) | V49: Credit Note | W49: =VLOOKUP(I49,Map!$F$18:$H$51,3,0) -> Variable | X49: AP Completed | Y49: =VLOOKUP(L49,Map!$C$18:$D$29,2,0) -> DGT | AA49: =IF(Y49="TOTAL",(Z49*0.19),0) -> 0 | AB49: =Z49*1.19 -> 0 | AC49: =Z49/S49 -> 0 | AD49: =IF(Y49="TOTAL",(AC49*0.19),0) -> 0 | AE49: =AC49*1.19 -> 0
B50: 2026 | C50: MAY 21 to JUN 20 | D50: JUN | E50: JUL (Provision) | F50: AUG | G50: 46196 | H50: 432245 | I50: FALABELLA (DIRECT) | J50: =IFERROR(VLOOKUP(I50,Map!$F$18:$G$56,2,0),"Add in Map") -> 3P | K50: =VLOOKUP(L50,Map!$C$18:$D$29,2,0) -> DLT | L50: Air Cleaner | M50: -640188.71 | N50: =IF(L50="TOTAL",(M50*0.19),0) -> 0 | O50: =M50*1.19 -> -761824.57 | P50: =M50/S50 -> -693.59557 | Q50: =IF(L50="TOTAL",(P50*0.19),0) -> 0 | R50: =P50*1.19 -> -825.37873 | S50: =INDEX(FX!$D$3:$O$19,MATCH(B50,FX!$B$3:$B$32,0),MATCH(D50,FX!$D$2:$O$2,0)) -> 923 | T50: Monthly Commission | U50: Provision (Based on External Report) | V50: Credit Note | W50: =VLOOKUP(I50,Map!$F$18:$H$51,3,0) -> Variable | X50: AP Completed | Y50: =VLOOKUP(L50,Map!$C$18:$D$29,2,0) -> DLT | AA50: =IF(Y50="TOTAL",(Z50*0.19),0) -> 0 | AB50: =Z50*1.19 -> 0 | AC50: =Z50/S50 -> 0 | AD50: =IF(Y50="TOTAL",(AC50*0.19),0) -> 0 | AE50: =AC50*1.19 -> 0
B51: 2026 | C51: MAY 21 to JUN 20 | D51: JUN | E51: JUL (Provision) | F51: AUG | G51: 46196 | H51: 432245 | I51: FALABELLA (DIRECT) | J51: =IFERROR(VLOOKUP(I51,Map!$F$18:$G$56,2,0),"Add in Map") -> 3P | K51: =VLOOKUP(L51,Map!$C$18:$D$29,2,0) -> DMT | L51: SAC | N51: =IF(L51="TOTAL",(M51*0.19),0) -> 0 | O51: =M51*1.19 -> 0 | P51: =M51/S51 -> 0 | Q51: =IF(L51="TOTAL",(P51*0.19),0) -> 0 | R51: =P51*1.19 -> 0 | S51: =INDEX(FX!$D$3:$O$19,MATCH(B51,FX!$B$3:$B$32,0),MATCH(D51,FX!$D$2:$O$2,0)) -> 923 | T51: Monthly Commission | U51: Provision (Based on External Report) | V51: Credit Note | W51: =VLOOKUP(I51,Map!$F$18:$H$51,3,0) -> Variable | X51: AP Completed | Y51: =VLOOKUP(L51,Map!$C$18:$D$29,2,0) -> DMT | AA51: =IF(Y51="TOTAL",(Z51*0.19),0) -> 0 | AB51: =Z51*1.19 -> 0 | AC51: =Z51/S51 -> 0 | AD51: =IF(Y51="TOTAL",(AC51*0.19),0) -> 0 | AE51: =AC51*1.19 -> 0
B52: 2026 | C52: MAY 21 to JUN 20 | D52: JUN | E52: JUL (Provision) | F52: AUG | G52: 46196 | H52: 432245 | I52: FALABELLA (DIRECT) | J52: =IFERROR(VLOOKUP(I52,Map!$F$18:$G$56,2,0),"Add in Map") -> 3P | K52: =VLOOKUP(L52,Map!$C$18:$D$29,2,0) -> TOTAL | L52: TOTAL | M52: =SUM(M41:M51) -> -99583029 | N52: =IF(L52="TOTAL",(M52*0.19),0) -> -18920776 | O52: =M52*1.19 -> -1.185038e+08 | P52: =M52/S52 -> -107890.61 | Q52: =IF(L52="TOTAL",(P52*0.19),0) -> -20499.215 | R52: =P52*1.19 -> -128389.82 | S52: =INDEX(FX!$D$3:$O$19,MATCH(B52,FX!$B$3:$B$32,0),MATCH(D52,FX!$D$2:$O$2,0)) -> 923 | T52: Monthly Commission | U52: Provision (Based on External Report) | V52: Credit Note | W52: =VLOOKUP(I52,Map!$F$18:$H$51,3,0) -> Variable | X52: AP Completed | Y52: =VLOOKUP(L52,Map!$C$18:$D$29,2,0) -> TOTAL | AA52: =IF(Y52="TOTAL",(Z52*0.19),0) -> 0 | AB52: =Z52*1.19 -> 0 | AC52: =Z52/S52 -> 0 | AD52: =IF(Y52="TOTAL",(AC52*0.19),0) -> 0 | AE52: =AC52*1.19 -> 0
B53: 2026 | C53: MAY 11 to 26 | D53: MAY | E53: JUL (Provision) | F53: JUL | G53: 46177 | H53: 3719 | I53: PARIS (FULLKOM) | J53: =IFERROR(VLOOKUP(I53,Map!$F$18:$G$56,2,0),"Add in Map") -> 3P | K53: =VLOOKUP(L53,Map!$C$18:$D$29,2,0) -> CNT | L53: Refrigeration | M53: 2055020.9 | N53: =IF(L53="TOTAL",(M53*0.19),0) -> 0 | O53: =M53*1.19 -> 2445474.8 | P53: =M53/S53 -> 2306.4207 | Q53: =IF(L53="TOTAL",(P53*0.19),0) -> 0 | R53: =P53*1.19 -> 2744.6407 | S53: =INDEX(FX!$D$3:$O$19,MATCH(B53,FX!$B$3:$B$32,0),MATCH(D53,FX!$D$2:$O$2,0)) -> 891 | T53: Commission (2da Quincena) | U53: Provision (Based on External Report) | V53: Invoice | W53: =VLOOKUP(I53,Map!$F$18:$H$51,3,0) -> Variable | X53: AP Completed | Y53: =VLOOKUP(L53,Map!$C$18:$D$29,2,0) -> CNT | AA53: =IF(Y53="TOTAL",(Z53*0.19),0) -> 0 | AB53: =Z53*1.19 -> 0 | AC53: =Z53/S53 -> 0 | AD53: =IF(Y53="TOTAL",(AC53*0.19),0) -> 0 | AE53: =AC53*1.19 -> 0
B54: 2026 | C54: MAY 11 to 26 | D54: MAY | E54: JUL (Provision) | F54: JUL | G54: 46177 | H54: 3719 | I54: PARIS (FULLKOM) | J54: =IFERROR(VLOOKUP(I54,Map!$F$18:$G$56,2,0),"Add in Map") -> 3P | K54: =VLOOKUP(L54,Map!$C$18:$D$29,2,0) -> CVT | L54: Cooking | M54: 110705.62 | N54: =IF(L54="TOTAL",(M54*0.19),0) -> 0 | O54: =M54*1.19 -> 131739.69 | P54: =M54/S54 -> 124.24874 | Q54: =IF(L54="TOTAL",(P54*0.19),0) -> 0 | R54: =P54*1.19 -> 147.856 | S54: =INDEX(FX!$D$3:$O$19,MATCH(B54,FX!$B$3:$B$32,0),MATCH(D54,FX!$D$2:$O$2,0)) -> 891 | T54: Commission (2da Quincena) | U54: Provision (Based on External Report) | V54: Invoice | W54: =VLOOKUP(I54,Map!$F$18:$H$51,3,0) -> Variable | X54: AP Completed | Y54: =VLOOKUP(L54,Map!$C$18:$D$29,2,0) -> CVT | AA54: =IF(Y54="TOTAL",(Z54*0.19),0) -> 0 | AB54: =Z54*1.19 -> 0 | AC54: =Z54/S54 -> 0 | AD54: =IF(Y54="TOTAL",(AC54*0.19),0) -> 0 | AE54: =AC54*1.19 -> 0
B55: 2026 | C55: MAY 11 to 26 | D55: MAY | E55: JUL (Provision) | F55: JUL | G55: 46177 | H55: 3719 | I55: PARIS (FULLKOM) | J55: =IFERROR(VLOOKUP(I55,Map!$F$18:$G$56,2,0),"Add in Map") -> 3P | K55: =VLOOKUP(L55,Map!$C$18:$D$29,2,0) -> CDT | L55: Dishwasher | M55: 0 | N55: =IF(L55="TOTAL",(M55*0.19),0) -> 0 | O55: =M55*1.19 -> 0 | P55: =M55/S55 -> 0 | Q55: =IF(L55="TOTAL",(P55*0.19),0) -> 0 | R55: =P55*1.19 -> 0 | S55: =INDEX(FX!$D$3:$O$19,MATCH(B55,FX!$B$3:$B$32,0),MATCH(D55,FX!$D$2:$O$2,0)) -> 891 | T55: Commission (2da Quincena) | U55: Provision (Based on External Report) | V55: Invoice | W55: =VLOOKUP(I55,Map!$F$18:$H$51,3,0) -> Variable | X55: AP Completed | Y55: =VLOOKUP(L55,Map!$C$18:$D$29,2,0) -> CDT | AA55: =IF(Y55="TOTAL",(Z55*0.19),0) -> 0 | AB55: =Z55*1.19 -> 0 | AC55: =Z55/S55 -> 0 | AD55: =IF(Y55="TOTAL",(AC55*0.19),0) -> 0 | AE55: =AC55*1.19 -> 0
B56: 2026 | C56: MAY 11 to 26 | D56: MAY | E56: JUL (Provision) | F56: JUL | G56: 46177 | H56: 3719 | I56: PARIS (FULLKOM) | J56: =IFERROR(VLOOKUP(I56,Map!$F$18:$G$56,2,0),"Add in Map") -> 3P | K56: =VLOOKUP(L56,Map!$C$18:$D$29,2,0) -> DFT | L56: WM | M56: 6018437.4 | N56: =IF(L56="TOTAL",(M56*0.19),0) -> 0 | O56: =M56*1.19 -> 7161940.5 | P56: =M56/S56 -> 6754.6996 | Q56: =IF(L56="TOTAL",(P56*0.19),0) -> 0 | R56: =P56*1.19 -> 8038.0925 | S56: =INDEX(FX!$D$3:$O$19,MATCH(B56,FX!$B$3:$B$32,0),MATCH(D56,FX!$D$2:$O$2,0)) -> 891 | T56: Commission (2da Quincena) | U56: Provision (Based on External Report) | V56: Invoice | W56: =VLOOKUP(I56,Map!$F$18:$H$51,3,0) -> Variable | X56: AP Completed | Y56: =VLOOKUP(L56,Map!$C$18:$D$29,2,0) -> DFT | AA56: =IF(Y56="TOTAL",(Z56*0.19),0) -> 0 | AB56: =Z56*1.19 -> 0 | AC56: =Z56/S56 -> 0 | AD56: =IF(Y56="TOTAL",(AC56*0.19),0) -> 0 | AE56: =AC56*1.19 -> 0
B57: 2026 | C57: MAY 11 to 26 | D57: MAY | E57: JUL (Provision) | F57: JUL | G57: 46177 | H57: 3719 | I57: PARIS (FULLKOM) | J57: =IFERROR(VLOOKUP(I57,Map!$F$18:$G$56,2,0),"Add in Map") -> 3P | K57: =VLOOKUP(L57,Map!$C$18:$D$29,2,0) -> DVT | L57: VCC | M57: 0 | N57: =IF(L57="TOTAL",(M57*0.19),0) -> 0 | O57: =M57*1.19 -> 0 | P57: =M57/S57 -> 0 | Q57: =IF(L57="TOTAL",(P57*0.19),0) -> 0 | R57: =P57*1.19 -> 0 | S57: =INDEX(FX!$D$3:$O$19,MATCH(B57,FX!$B$3:$B$32,0),MATCH(D57,FX!$D$2:$O$2,0)) -> 891 | T57: Commission (2da Quincena) | U57: Provision (Based on External Report) | V57: Invoice | W57: =VLOOKUP(I57,Map!$F$18:$H$51,3,0) -> Variable | X57: AP Completed | Y57: =VLOOKUP(L57,Map!$C$18:$D$29,2,0) -> DVT | AA57: =IF(Y57="TOTAL",(Z57*0.19),0) -> 0 | AB57: =Z57*1.19 -> 0 | AC57: =Z57/S57 -> 0 | AD57: =IF(Y57="TOTAL",(AC57*0.19),0) -> 0 | AE57: =AC57*1.19 -> 0
B58: 2026 | C58: MAY 11 to 26 | D58: MAY | E58: JUL (Provision) | F58: JUL | G58: 46177 | H58: 3719 | I58: PARIS (FULLKOM) | J58: =IFERROR(VLOOKUP(I58,Map!$F$18:$G$56,2,0),"Add in Map") -> 3P | K58: =VLOOKUP(L58,Map!$C$18:$D$29,2,0) -> GLT | L58: Television | M58: 2689893.1 | N58: =IF(L58="TOTAL",(M58*0.19),0) -> 0 | O58: =M58*1.19 -> 3200972.8 | P58: =M58/S58 -> 3018.9597 | Q58: =IF(L58="TOTAL",(P58*0.19),0) -> 0 | R58: =P58*1.19 -> 3592.5621 | S58: =INDEX(FX!$D$3:$O$19,MATCH(B58,FX!$B$3:$B$32,0),MATCH(D58,FX!$D$2:$O$2,0)) -> 891 | T58: Commission (2da Quincena) | U58: Provision (Based on External Report) | V58: Invoice | W58: =VLOOKUP(I58,Map!$F$18:$H$51,3,0) -> Variable | X58: AP Completed | Y58: =VLOOKUP(L58,Map!$C$18:$D$29,2,0) -> GLT | AA58: =IF(Y58="TOTAL",(Z58*0.19),0) -> 0 | AB58: =Z58*1.19 -> 0 | AC58: =Z58/S58 -> 0 | AD58: =IF(Y58="TOTAL",(AC58*0.19),0) -> 0 | AE58: =AC58*1.19 -> 0
B59: 2026 | C59: MAY 11 to 26 | D59: MAY | E59: JUL (Provision) | F59: JUL | G59: 46177 | H59: 3719 | I59: PARIS (FULLKOM) | J59: =IFERROR(VLOOKUP(I59,Map!$F$18:$G$56,2,0),"Add in Map") -> 3P | K59: =VLOOKUP(L59,Map!$C$18:$D$29,2,0) -> PNT | L59: Audio | M59: 202816.15 | N59: =IF(L59="TOTAL",(M59*0.19),0) -> 0 | O59: =M59*1.19 -> 241351.22 | P59: =M59/S59 -> 227.62755 | Q59: =IF(L59="TOTAL",(P59*0.19),0) -> 0 | R59: =P59*1.19 -> 270.87679 | S59: =INDEX(FX!$D$3:$O$19,MATCH(B59,FX!$B$3:$B$32,0),MATCH(D59,FX!$D$2:$O$2,0)) -> 891 | T59: Commission (2da Quincena) | U59: Provision (Based on External Report) | V59: Invoice | W59: =VLOOKUP(I59,Map!$F$18:$H$51,3,0) -> Variable | X59: AP Completed | Y59: =VLOOKUP(L59,Map!$C$18:$D$29,2,0) -> PNT | AA59: =IF(Y59="TOTAL",(Z59*0.19),0) -> 0 | AB59: =Z59*1.19 -> 0 | AC59: =Z59/S59 -> 0 | AD59: =IF(Y59="TOTAL",(AC59*0.19),0) -> 0 | AE59: =AC59*1.19 -> 0
B60: 2026 | C60: MAY 11 to 26 | D60: MAY | E60: JUL (Provision) | F60: JUL | G60: 46177 | H60: 3719 | I60: PARIS (FULLKOM) | J60: =IFERROR(VLOOKUP(I60,Map!$F$18:$G$56,2,0),"Add in Map") -> 3P | K60: =VLOOKUP(L60,Map!$C$18:$D$29,2,0) -> GTT | L60: Monitor | M60: 108893.77 | N60: =IF(L60="TOTAL",(M60*0.19),0) -> 0 | O60: =M60*1.19 -> 129583.58 | P60: =M60/S60 -> 122.21523 | Q60: =IF(L60="TOTAL",(P60*0.19),0) -> 0 | R60: =P60*1.19 -> 145.43612 | S60: =INDEX(FX!$D$3:$O$19,MATCH(B60,FX!$B$3:$B$32,0),MATCH(D60,FX!$D$2:$O$2,0)) -> 891 | T60: Commission (2da Quincena) | U60: Provision (Based on External Report) | V60: Invoice | W60: =VLOOKUP(I60,Map!$F$18:$H$51,3,0) -> Variable | X60: AP Completed | Y60: =VLOOKUP(L60,Map!$C$18:$D$29,2,0) -> GTT | AA60: =IF(Y60="TOTAL",(Z60*0.19),0) -> 0 | AB60: =Z60*1.19 -> 0 | AC60: =Z60/S60 -> 0 | AD60: =IF(Y60="TOTAL",(AC60*0.19),0) -> 0 | AE60: =AC60*1.19 -> 0
B61: 2026 | C61: MAY 11 to 26 | D61: MAY | E61: JUL (Provision) | F61: JUL | G61: 46177 | H61: 3719 | I61: PARIS (FULLKOM) | J61: =IFERROR(VLOOKUP(I61,Map!$F$18:$G$56,2,0),"Add in Map") -> 3P | K61: =VLOOKUP(L61,Map!$C$18:$D$29,2,0) -> DGT | L61: RAC | M61: 54903.209 | N61: =IF(L61="TOTAL",(M61*0.19),0) -> 0 | O61: =M61*1.19 -> 65334.818 | P61: =M61/S61 -> 61.619763 | Q61: =IF(L61="TOTAL",(P61*0.19),0) -> 0 | R61: =P61*1.19 -> 73.327518 | S61: =INDEX(FX!$D$3:$O$19,MATCH(B61,FX!$B$3:$B$32,0),MATCH(D61,FX!$D$2:$O$2,0)) -> 891 | T61: Commission (2da Quincena) | U61: Provision (Based on External Report) | V61: Invoice | W61: =VLOOKUP(I61,Map!$F$18:$H$51,3,0) -> Variable | X61: AP Completed | Y61: =VLOOKUP(L61,Map!$C$18:$D$29,2,0) -> DGT | AA61: =IF(Y61="TOTAL",(Z61*0.19),0) -> 0 | AB61: =Z61*1.19 -> 0 | AC61: =Z61/S61 -> 0 | AD61: =IF(Y61="TOTAL",(AC61*0.19),0) -> 0 | AE61: =AC61*1.19 -> 0
B62: 2026 | C62: MAY 11 to 26 | D62: MAY | E62: JUL (Provision) | F62: JUL | G62: 46177 | H62: 3719 | I62: PARIS (FULLKOM) | J62: =IFERROR(VLOOKUP(I62,Map!$F$18:$G$56,2,0),"Add in Map") -> 3P | K62: =VLOOKUP(L62,Map!$C$18:$D$29,2,0) -> DLT | L62: Air Cleaner | M62: 16787.885 | N62: =IF(L62="TOTAL",(M62*0.19),0) -> 0 | O62: =M62*1.19 -> 19977.583 | P62: =M62/S62 -> 18.841622 | Q62: =IF(L62="TOTAL",(P62*0.19),0) -> 0 | R62: =P62*1.19 -> 22.42153 | S62: =INDEX(FX!$D$3:$O$19,MATCH(B62,FX!$B$3:$B$32,0),MATCH(D62,FX!$D$2:$O$2,0)) -> 891 | T62: Commission (2da Quincena) | U62: Provision (Based on External Report) | V62: Invoice | W62: =VLOOKUP(I62,Map!$F$18:$H$51,3,0) -> Variable | X62: AP Completed | Y62: =VLOOKUP(L62,Map!$C$18:$D$29,2,0) -> DLT | AA62: =IF(Y62="TOTAL",(Z62*0.19),0) -> 0 | AB62: =Z62*1.19 -> 0 | AC62: =Z62/S62 -> 0 | AD62: =IF(Y62="TOTAL",(AC62*0.19),0) -> 0 | AE62: =AC62*1.19 -> 0
B63: 2026 | C63: MAY 11 to 26 | D63: MAY | E63: JUL (Provision) | F63: JUL | G63: 46177 | H63: 3719 | I63: PARIS (FULLKOM) | J63: =IFERROR(VLOOKUP(I63,Map!$F$18:$G$56,2,0),"Add in Map") -> 3P | K63: =VLOOKUP(L63,Map!$C$18:$D$29,2,0) -> DMT | L63: SAC | M63: 0 | N63: =IF(L63="TOTAL",(M63*0.19),0) -> 0 | O63: =M63*1.19 -> 0 | P63: =M63/S63 -> 0 | Q63: =IF(L63="TOTAL",(P63*0.19),0) -> 0 | R63: =P63*1.19 -> 0 | S63: =INDEX(FX!$D$3:$O$19,MATCH(B63,FX!$B$3:$B$32,0),MATCH(D63,FX!$D$2:$O$2,0)) -> 891 | T63: Commission (2da Quincena) | U63: Provision (Based on External Report) | V63: Invoice | W63: =VLOOKUP(I63,Map!$F$18:$H$51,3,0) -> Variable | X63: AP Completed | Y63: =VLOOKUP(L63,Map!$C$18:$D$29,2,0) -> DMT | AA63: =IF(Y63="TOTAL",(Z63*0.19),0) -> 0 | AB63: =Z63*1.19 -> 0 | AC63: =Z63/S63 -> 0 | AD63: =IF(Y63="TOTAL",(AC63*0.19),0) -> 0 | AE63: =AC63*1.19 -> 0
B64: 2026 | C64: MAY 11 to 26 | D64: MAY | E64: JUL (Provision) | F64: JUL | G64: 46177 | H64: 3719 | I64: PARIS (FULLKOM) | J64: =IFERROR(VLOOKUP(I64,Map!$F$18:$G$56,2,0),"Add in Map") -> 3P | K64: =VLOOKUP(L64,Map!$C$18:$D$29,2,0) -> TOTAL | L64: TOTAL | M64: =SUM(M53:M63) -> 11257458 | N64: =IF(L64="TOTAL",(M64*0.19),0) -> 2138917 | O64: =M64*1.19 -> 13396375 | P64: =M64/S64 -> 12634.633 | Q64: =IF(L64="TOTAL",(P64*0.19),0) -> 2400.5803 | R64: =P64*1.19 -> 15035.213 | S64: =INDEX(FX!$D$3:$O$19,MATCH(B64,FX!$B$3:$B$32,0),MATCH(D64,FX!$D$2:$O$2,0)) -> 891 | T64: Commission (2da Quincena) | U64: Provision (Based on External Report) | V64: Invoice | W64: =VLOOKUP(I64,Map!$F$18:$H$51,3,0) -> Variable | X64: AP Completed | Y64: =VLOOKUP(L64,Map!$C$18:$D$29,2,0) -> TOTAL | AA64: =IF(Y64="TOTAL",(Z64*0.19),0) -> 0 | AB64: =Z64*1.19 -> 0 | AC64: =Z64/S64 -> 0 | AD64: =IF(Y64="TOTAL",(AC64*0.19),0) -> 0 | AE64: =AC64*1.19 -> 0
B65: 2026 | C65: 2026 MAR | D65: JUL | E65: JUL (Provision) | F65: Pending | I65: PARIS (FULLKOM) | J65: =IFERROR(VLOOKUP(I65,Map!$F$18:$G$56,2,0),"Add in Map") -> 3P | K65: =VLOOKUP(L65,Map!$C$18:$D$29,2,0) -> CNT | L65: Refrigeration | M65: 5510370.3 | N65: =IF(L65="TOTAL",(M65*0.19),0) -> 0 | O65: =M65*1.19 -> 6557340.7 | P65: =M65/S65 -> 5963.6042 | Q65: =IF(L65="TOTAL",(P65*0.19),0) -> 0 | R65: =P65*1.19 -> 7096.689 | S65: =INDEX(FX!$D$3:$O$19,MATCH(B65,FX!$B$3:$B$32,0),MATCH(D65,FX!$D$2:$O$2,0)) -> 924 | T65: Logistic Cost | U65: Provision (Based on External Report) | V65: Invoice | W65: =VLOOKUP(I65,Map!$F$18:$H$51,3,0) -> Variable | X65: Pending | Y65: =VLOOKUP(L65,Map!$C$18:$D$29,2,0) -> CNT | AA65: =IF(Y65="TOTAL",(Z65*0.19),0) -> 0 | AB65: =Z65*1.19 -> 0 | AC65: =Z65/S65 -> 0 | AD65: =IF(Y65="TOTAL",(AC65*0.19),0) -> 0 | AE65: =AC65*1.19 -> 0
B66: 2026 | C66: 2026 MAR | D66: JUL | E66: JUL (Provision) | F66: Pending | I66: PARIS (FULLKOM) | J66: =IFERROR(VLOOKUP(I66,Map!$F$18:$G$56,2,0),"Add in Map") -> 3P | K66: =VLOOKUP(L66,Map!$C$18:$D$29,2,0) -> CVT | L66: Cooking | M66: 0 | N66: =IF(L66="TOTAL",(M66*0.19),0) -> 0 | O66: =M66*1.19 -> 0 | P66: =M66/S66 -> 0 | Q66: =IF(L66="TOTAL",(P66*0.19),0) -> 0 | R66: =P66*1.19 -> 0 | S66: =INDEX(FX!$D$3:$O$19,MATCH(B66,FX!$B$3:$B$32,0),MATCH(D66,FX!$D$2:$O$2,0)) -> 924 | T66: Logistic Cost | U66: Provision (Based on External Report) | V66: Invoice | W66: =VLOOKUP(I66,Map!$F$18:$H$51,3,0) -> Variable | X66: Pending | Y66: =VLOOKUP(L66,Map!$C$18:$D$29,2,0) -> CVT | AA66: =IF(Y66="TOTAL",(Z66*0.19),0) -> 0 | AB66: =Z66*1.19 -> 0 | AC66: =Z66/S66 -> 0 | AD66: =IF(Y66="TOTAL",(AC66*0.19),0) -> 0 | AE66: =AC66*1.19 -> 0
B67: 2026 | C67: 2026 MAR | D67: JUL | E67: JUL (Provision) | F67: Pending | I67: PARIS (FULLKOM) | J67: =IFERROR(VLOOKUP(I67,Map!$F$18:$G$56,2,0),"Add in Map") -> 3P | K67: =VLOOKUP(L67,Map!$C$18:$D$29,2,0) -> CDT | L67: Dishwasher | M67: 70645.773 | N67: =IF(L67="TOTAL",(M67*0.19),0) -> 0 | O67: =M67*1.19 -> 84068.47 | P67: =M67/S67 -> 76.456464 | Q67: =IF(L67="TOTAL",(P67*0.19),0) -> 0 | R67: =P67*1.19 -> 90.983193 | S67: =INDEX(FX!$D$3:$O$19,MATCH(B67,FX!$B$3:$B$32,0),MATCH(D67,FX!$D$2:$O$2,0)) -> 924 | T67: Logistic Cost | U67: Provision (Based on External Report) | V67: Invoice | W67: =VLOOKUP(I67,Map!$F$18:$H$51,3,0) -> Variable | X67: Pending | Y67: =VLOOKUP(L67,Map!$C$18:$D$29,2,0) -> CDT | AA67: =IF(Y67="TOTAL",(Z67*0.19),0) -> 0 | AB67: =Z67*1.19 -> 0 | AC67: =Z67/S67 -> 0 | AD67: =IF(Y67="TOTAL",(AC67*0.19),0) -> 0 | AE67: =AC67*1.19 -> 0
B68: 2026 | C68: 2026 MAR | D68: JUL | E68: JUL (Provision) | F68: Pending | I68: PARIS (FULLKOM) | J68: =IFERROR(VLOOKUP(I68,Map!$F$18:$G$56,2,0),"Add in Map") -> 3P | K68: =VLOOKUP(L68,Map!$C$18:$D$29,2,0) -> DFT | L68: WM | M68: 13281405 | N68: =IF(L68="TOTAL",(M68*0.19),0) -> 0 | O68: =M68*1.19 -> 15804872 | P68: =M68/S68 -> 14373.815 | Q68: =IF(L68="TOTAL",(P68*0.19),0) -> 0 | R68: =P68*1.19 -> 17104.84 | S68: =INDEX(FX!$D$3:$O$19,MATCH(B68,FX!$B$3:$B$32,0),MATCH(D68,FX!$D$2:$O$2,0)) -> 924 | T68: Logistic Cost | U68: Provision (Based on External Report) | V68: Invoice | W68: =VLOOKUP(I68,Map!$F$18:$H$51,3,0) -> Variable | X68: Pending | Y68: =VLOOKUP(L68,Map!$C$18:$D$29,2,0) -> DFT | AA68: =IF(Y68="TOTAL",(Z68*0.19),0) -> 0 | AB68: =Z68*1.19 -> 0 | AC68: =Z68/S68 -> 0 | AD68: =IF(Y68="TOTAL",(AC68*0.19),0) -> 0 | AE68: =AC68*1.19 -> 0
B69: 2026 | C69: 2026 MAR | D69: JUL | E69: JUL (Provision) | F69: Pending | I69: PARIS (FULLKOM) | J69: =IFERROR(VLOOKUP(I69,Map!$F$18:$G$56,2,0),"Add in Map") -> 3P | K69: =VLOOKUP(L69,Map!$C$18:$D$29,2,0) -> DVT | L69: VCC | M69: 0 | N69: =IF(L69="TOTAL",(M69*0.19),0) -> 0 | O69: =M69*1.19 -> 0 | P69: =M69/S69 -> 0 | Q69: =IF(L69="TOTAL",(P69*0.19),0) -> 0 | R69: =P69*1.19 -> 0 | S69: =INDEX(FX!$D$3:$O$19,MATCH(B69,FX!$B$3:$B$32,0),MATCH(D69,FX!$D$2:$O$2,0)) -> 924 | T69: Logistic Cost | U69: Provision (Based on External Report) | V69: Invoice | W69: =VLOOKUP(I69,Map!$F$18:$H$51,3,0) -> Variable | X69: Pending | Y69: =VLOOKUP(L69,Map!$C$18:$D$29,2,0) -> DVT | AA69: =IF(Y69="TOTAL",(Z69*0.19),0) -> 0 | AB69: =Z69*1.19 -> 0 | AC69: =Z69/S69 -> 0 | AD69: =IF(Y69="TOTAL",(AC69*0.19),0) -> 0 | AE69: =AC69*1.19 -> 0
B70: 2026 | C70: 2026 MAR | D70: JUL | E70: JUL (Provision) | F70: Pending | I70: PARIS (FULLKOM) | J70: =IFERROR(VLOOKUP(I70,Map!$F$18:$G$56,2,0),"Add in Map") -> 3P | K70: =VLOOKUP(L70,Map!$C$18:$D$29,2,0) -> GLT | L70: Television | M70: 2896476.7 | N70: =IF(L70="TOTAL",(M70*0.19),0) -> 0 | O70: =M70*1.19 -> 3446807.3 | P70: =M70/S70 -> 3134.715 | Q70: =IF(L70="TOTAL",(P70*0.19),0) -> 0 | R70: =P70*1.19 -> 3730.3109 | S70: =INDEX(FX!$D$3:$O$19,MATCH(B70,FX!$B$3:$B$32,0),MATCH(D70,FX!$D$2:$O$2,0)) -> 924 | T70: Logistic Cost | U70: Provision (Based on External Report) | V70: Invoice | W70: =VLOOKUP(I70,Map!$F$18:$H$51,3,0) -> Variable | X70: Pending | Y70: =VLOOKUP(L70,Map!$C$18:$D$29,2,0) -> GLT | AA70: =IF(Y70="TOTAL",(Z70*0.19),0) -> 0 | AB70: =Z70*1.19 -> 0 | AC70: =Z70/S70 -> 0 | AD70: =IF(Y70="TOTAL",(AC70*0.19),0) -> 0 | AE70: =AC70*1.19 -> 0
B71: 2026 | C71: 2026 MAR | D71: JUL | E71: JUL (Provision) | F71: Pending | I71: PARIS (FULLKOM) | J71: =IFERROR(VLOOKUP(I71,Map!$F$18:$G$56,2,0),"Add in Map") -> 3P | K71: =VLOOKUP(L71,Map!$C$18:$D$29,2,0) -> PNT | L71: Audio | M71: 494520.41 | N71: =IF(L71="TOTAL",(M71*0.19),0) -> 0 | O71: =M71*1.19 -> 588479.29 | P71: =M71/S71 -> 535.19525 | Q71: =IF(L71="TOTAL",(P71*0.19),0) -> 0 | R71: =P71*1.19 -> 636.88235 | S71: =INDEX(FX!$D$3:$O$19,MATCH(B71,FX!$B$3:$B$32,0),MATCH(D71,FX!$D$2:$O$2,0)) -> 924 | T71: Logistic Cost | U71: Provision (Based on External Report) | V71: Invoice | W71: =VLOOKUP(I71,Map!$F$18:$H$51,3,0) -> Variable | X71: Pending | Y71: =VLOOKUP(L71,Map!$C$18:$D$29,2,0) -> PNT | AA71: =IF(Y71="TOTAL",(Z71*0.19),0) -> 0 | AB71: =Z71*1.19 -> 0 | AC71: =Z71/S71 -> 0 | AD71: =IF(Y71="TOTAL",(AC71*0.19),0) -> 0 | AE71: =AC71*1.19 -> 0
B72: 2026 | C72: 2026 MAR | D72: JUL | E72: JUL (Provision) | F72: Pending | I72: PARIS (FULLKOM) | J72: =IFERROR(VLOOKUP(I72,Map!$F$18:$G$56,2,0),"Add in Map") -> 3P | K72: =VLOOKUP(L72,Map!$C$18:$D$29,2,0) -> GTT | L72: Monitor | M72: 282583.09 | N72: =IF(L72="TOTAL",(M72*0.19),0) -> 0 | O72: =M72*1.19 -> 336273.88 | P72: =M72/S72 -> 305.82586 | Q72: =IF(L72="TOTAL",(P72*0.19),0) -> 0 | R72: =P72*1.19 -> 363.93277 | S72: =INDEX(FX!$D$3:$O$19,MATCH(B72,FX!$B$3:$B$32,0),MATCH(D72,FX!$D$2:$O$2,0)) -> 924 | T72: Logistic Cost | U72: Provision (Based on External Report) | V72: Invoice | W72: =VLOOKUP(I72,Map!$F$18:$H$51,3,0) -> Variable | X72: Pending | Y72: =VLOOKUP(L72,Map!$C$18:$D$29,2,0) -> GTT | AA72: =IF(Y72="TOTAL",(Z72*0.19),0) -> 0 | AB72: =Z72*1.19 -> 0 | AC72: =Z72/S72 -> 0 | AD72: =IF(Y72="TOTAL",(AC72*0.19),0) -> 0 | AE72: =AC72*1.19 -> 0
B73: 2026 | C73: 2026 MAR | D73: JUL | E73: JUL (Provision) | F73: Pending | I73: PARIS (FULLKOM) | J73: =IFERROR(VLOOKUP(I73,Map!$F$18:$G$56,2,0),"Add in Map") -> 3P | K73: =VLOOKUP(L73,Map!$C$18:$D$29,2,0) -> DGT | L73: RAC | M73: 211937.32 | N73: =IF(L73="TOTAL",(M73*0.19),0) -> 0 | O73: =M73*1.19 -> 252205.41 | P73: =M73/S73 -> 229.36939 | Q73: =IF(L73="TOTAL",(P73*0.19),0) -> 0 | R73: =P73*1.19 -> 272.94958 | S73: =INDEX(FX!$D$3:$O$19,MATCH(B73,FX!$B$3:$B$32,0),MATCH(D73,FX!$D$2:$O$2,0)) -> 924 | T73: Logistic Cost | U73: Provision (Based on External Report) | V73: Invoice | W73: =VLOOKUP(I73,Map!$F$18:$H$51,3,0) -> Variable | X73: Pending | Y73: =VLOOKUP(L73,Map!$C$18:$D$29,2,0) -> DGT | AA73: =IF(Y73="TOTAL",(Z73*0.19),0) -> 0 | AB73: =Z73*1.19 -> 0 | AC73: =Z73/S73 -> 0 | AD73: =IF(Y73="TOTAL",(AC73*0.19),0) -> 0 | AE73: =AC73*1.19 -> 0
B74: 2026 | C74: 2026 MAR | D74: JUL | E74: JUL (Provision) | F74: Pending | I74: PARIS (FULLKOM) | J74: =IFERROR(VLOOKUP(I74,Map!$F$18:$G$56,2,0),"Add in Map") -> 3P | K74: =VLOOKUP(L74,Map!$C$18:$D$29,2,0) -> DLT | L74: Air Cleaner | M74: 70645.773 | N74: =IF(L74="TOTAL",(M74*0.19),0) -> 0 | O74: =M74*1.19 -> 84068.47 | P74: =M74/S74 -> 76.456464 | Q74: =IF(L74="TOTAL",(P74*0.19),0) -> 0 | R74: =P74*1.19 -> 90.983193 | S74: =INDEX(FX!$D$3:$O$19,MATCH(B74,FX!$B$3:$B$32,0),MATCH(D74,FX!$D$2:$O$2,0)) -> 924 | T74: Logistic Cost | U74: Provision (Based on External Report) | V74: Invoice | W74: =VLOOKUP(I74,Map!$F$18:$H$51,3,0) -> Variable | X74: Pending | Y74: =VLOOKUP(L74,Map!$C$18:$D$29,2,0) -> DLT | AA74: =IF(Y74="TOTAL",(Z74*0.19),0) -> 0 | AB74: =Z74*1.19 -> 0 | AC74: =Z74/S74 -> 0 | AD74: =IF(Y74="TOTAL",(AC74*0.19),0) -> 0 | AE74: =AC74*1.19 -> 0
B75: 2026 | C75: 2026 MAR | D75: JUL | E75: JUL (Provision) | F75: Pending | I75: PARIS (FULLKOM) | J75: =IFERROR(VLOOKUP(I75,Map!$F$18:$G$56,2,0),"Add in Map") -> 3P | K75: =VLOOKUP(L75,Map!$C$18:$D$29,2,0) -> DMT | L75: SAC | M75: 0 | N75: =IF(L75="TOTAL",(M75*0.19),0) -> 0 | O75: =M75*1.19 -> 0 | P75: =M75/S75 -> 0 | Q75: =IF(L75="TOTAL",(P75*0.19),0) -> 0 | R75: =P75*1.19 -> 0 | S75: =INDEX(FX!$D$3:$O$19,MATCH(B75,FX!$B$3:$B$32,0),MATCH(D75,FX!$D$2:$O$2,0)) -> 924 | T75: Logistic Cost | U75: Provision (Based on External Report) | V75: Invoice | W75: =VLOOKUP(I75,Map!$F$18:$H$51,3,0) -> Variable | X75: Pending | Y75: =VLOOKUP(L75,Map!$C$18:$D$29,2,0) -> DMT | AA75: =IF(Y75="TOTAL",(Z75*0.19),0) -> 0 | AB75: =Z75*1.19 -> 0 | AC75: =Z75/S75 -> 0 | AD75: =IF(Y75="TOTAL",(AC75*0.19),0) -> 0 | AE75: =AC75*1.19 -> 0
B76: 2026 | C76: 2026 MAR | D76: JUL | E76: JUL (Provision) | F76: Pending | I76: PARIS (FULLKOM) | J76: =IFERROR(VLOOKUP(I76,Map!$F$18:$G$56,2,0),"Add in Map") -> 3P | K76: =VLOOKUP(L76,Map!$C$18:$D$29,2,0) -> TOTAL | L76: TOTAL | M76: =SUM(M65:M75) -> 22818585 | N76: =IF(L76="TOTAL",(M76*0.19),0) -> 4335531.1 | O76: =M76*1.19 -> 27154116 | P76: =M76/S76 -> 24695.438 | Q76: =IF(L76="TOTAL",(P76*0.19),0) -> 4692.1332 | R76: =P76*1.19 -> 29387.571 | S76: =INDEX(FX!$D$3:$O$19,MATCH(B76,FX!$B$3:$B$32,0),MATCH(D76,FX!$D$2:$O$2,0)) -> 924 | T76: Logistic Cost | U76: Provision (Based on External Report) | V76: Invoice | W76: =VLOOKUP(I76,Map!$F$18:$H$51,3,0) -> Variable | X76: Pending | Y76: =VLOOKUP(L76,Map!$C$18:$D$29,2,0) -> TOTAL | AA76: =IF(Y76="TOTAL",(Z76*0.19),0) -> 0 | AB76: =Z76*1.19 -> 0 | AC76: =Z76/S76 -> 0 | AD76: =IF(Y76="TOTAL",(AC76*0.19),0) -> 0 | AE76: =AC76*1.19 -> 0
B77: 2026 | C77: 2026 APR | D77: JUL | E77: JUL (Provision) | F77: Pending | I77: PARIS (FULLKOM) | J77: =IFERROR(VLOOKUP(I77,Map!$F$18:$G$56,2,0),"Add in Map") -> 3P | K77: =VLOOKUP(L77,Map!$C$18:$D$29,2,0) -> CNT | L77: Refrigeration | M77: 2753819.5 | N77: =IF(L77="TOTAL",(M77*0.19),0) -> 0 | O77: =M77*1.19 -> 3277045.2 | P77: =M77/S77 -> 2980.3241 | Q77: =IF(L77="TOTAL",(P77*0.19),0) -> 0 | R77: =P77*1.19 -> 3546.5857 | S77: =INDEX(FX!$D$3:$O$19,MATCH(B77,FX!$B$3:$B$32,0),MATCH(D77,FX!$D$2:$O$2,0)) -> 924 | T77: Logistic Cost | U77: Provision (Based on External Report) | V77: Invoice | W77: =VLOOKUP(I77,Map!$F$18:$H$51,3,0) -> Variable | X77: Pending | Y77: =VLOOKUP(L77,Map!$C$18:$D$29,2,0) -> CNT | AA77: =IF(Y77="TOTAL",(Z77*0.19),0) -> 0 | AB77: =Z77*1.19 -> 0 | AC77: =Z77/S77 -> 0 | AD77: =IF(Y77="TOTAL",(AC77*0.19),0) -> 0 | AE77: =AC77*1.19 -> 0
B78: 2026 | C78: 2026 APR | D78: JUL | E78: JUL (Provision) | F78: Pending | I78: PARIS (FULLKOM) | J78: =IFERROR(VLOOKUP(I78,Map!$F$18:$G$56,2,0),"Add in Map") -> 3P | K78: =VLOOKUP(L78,Map!$C$18:$D$29,2,0) -> CVT | L78: Cooking | M78: 0 | N78: =IF(L78="TOTAL",(M78*0.19),0) -> 0 | O78: =M78*1.19 -> 0 | P78: =M78/S78 -> 0 | Q78: =IF(L78="TOTAL",(P78*0.19),0) -> 0 | R78: =P78*1.19 -> 0 | S78: =INDEX(FX!$D$3:$O$19,MATCH(B78,FX!$B$3:$B$32,0),MATCH(D78,FX!$D$2:$O$2,0)) -> 924 | T78: Logistic Cost | U78: Provision (Based on External Report) | V78: Invoice | W78: =VLOOKUP(I78,Map!$F$18:$H$51,3,0) -> Variable | X78: Pending | Y78: =VLOOKUP(L78,Map!$C$18:$D$29,2,0) -> CVT | AA78: =IF(Y78="TOTAL",(Z78*0.19),0) -> 0 | AB78: =Z78*1.19 -> 0 | AC78: =Z78/S78 -> 0 | AD78: =IF(Y78="TOTAL",(AC78*0.19),0) -> 0 | AE78: =AC78*1.19 -> 0
B79: 2026 | C79: 2026 APR | D79: JUL | E79: JUL (Provision) | F79: Pending | I79: PARIS (FULLKOM) | J79: =IFERROR(VLOOKUP(I79,Map!$F$18:$G$56,2,0),"Add in Map") -> 3P | K79: =VLOOKUP(L79,Map!$C$18:$D$29,2,0) -> CDT | L79: Dishwasher | M79: 35305.378 | N79: =IF(L79="TOTAL",(M79*0.19),0) -> 0 | O79: =M79*1.19 -> 42013.399 | P79: =M79/S79 -> 38.209283 | Q79: =IF(L79="TOTAL",(P79*0.19),0) -> 0 | R79: =P79*1.19 -> 45.469047 | S79: =INDEX(FX!$D$3:$O$19,MATCH(B79,FX!$B$3:$B$32,0),MATCH(D79,FX!$D$2:$O$2,0)) -> 924 | T79: Logistic Cost | U79: Provision (Based on External Report) | V79: Invoice | W79: =VLOOKUP(I79,Map!$F$18:$H$51,3,0) -> Variable | X79: Pending | Y79: =VLOOKUP(L79,Map!$C$18:$D$29,2,0) -> CDT | AA79: =IF(Y79="TOTAL",(Z79*0.19),0) -> 0 | AB79: =Z79*1.19 -> 0 | AC79: =Z79/S79 -> 0 | AD79: =IF(Y79="TOTAL",(AC79*0.19),0) -> 0 | AE79: =AC79*1.19 -> 0
B80: 2026 | C80: 2026 APR | D80: JUL | E80: JUL (Provision) | F80: Pending | I80: PARIS (FULLKOM) | J80: =IFERROR(VLOOKUP(I80,Map!$F$18:$G$56,2,0),"Add in Map") -> 3P | K80: =VLOOKUP(L80,Map!$C$18:$D$29,2,0) -> DFT | L80: WM | M80: 6637411 | N80: =IF(L80="TOTAL",(M80*0.19),0) -> 0 | O80: =M80*1.19 -> 7898519.1 | P80: =M80/S80 -> 7183.3452 | Q80: =IF(L80="TOTAL",(P80*0.19),0) -> 0 | R80: =P80*1.19 -> 8548.1808 | S80: =INDEX(FX!$D$3:$O$19,MATCH(B80,FX!$B$3:$B$32,0),MATCH(D80,FX!$D$2:$O$2,0)) -> 924 | T80: Logistic Cost | U80: Provision (Based on External Report) | V80: Invoice | W80: =VLOOKUP(I80,Map!$F$18:$H$51,3,0) -> Variable | X80: Pending | Y80: =VLOOKUP(L80,Map!$C$18:$D$29,2,0) -> DFT | AA80: =IF(Y80="TOTAL",(Z80*0.19),0) -> 0 | AB80: =Z80*1.19 -> 0 | AC80: =Z80/S80 -> 0 | AD80: =IF(Y80="TOTAL",(AC80*0.19),0) -> 0 | AE80: =AC80*1.19 -> 0
B81: 2026 | C81: 2026 APR | D81: JUL | E81: JUL (Provision) | F81: Pending | I81: PARIS (FULLKOM) | J81: =IFERROR(VLOOKUP(I81,Map!$F$18:$G$56,2,0),"Add in Map") -> 3P | K81: =VLOOKUP(L81,Map!$C$18:$D$29,2,0) -> DVT | L81: VCC | M81: 0 | N81: =IF(L81="TOTAL",(M81*0.19),0) -> 0 | O81: =M81*1.19 -> 0 | P81: =M81/S81 -> 0 | Q81: =IF(L81="TOTAL",(P81*0.19),0) -> 0 | R81: =P81*1.19 -> 0 | S81: =INDEX(FX!$D$3:$O$19,MATCH(B81,FX!$B$3:$B$32,0),MATCH(D81,FX!$D$2:$O$2,0)) -> 924 | T81: Logistic Cost | U81: Provision (Based on External Report) | V81: Invoice | W81: =VLOOKUP(I81,Map!$F$18:$H$51,3,0) -> Variable | X81: Pending | Y81: =VLOOKUP(L81,Map!$C$18:$D$29,2,0) -> DVT | AA81: =IF(Y81="TOTAL",(Z81*0.19),0) -> 0 | AB81: =Z81*1.19 -> 0 | AC81: =Z81/S81 -> 0 | AD81: =IF(Y81="TOTAL",(AC81*0.19),0) -> 0 | AE81: =AC81*1.19 -> 0
B82: 2026 | C82: 2026 APR | D82: JUL | E82: JUL (Provision) | F82: Pending | I82: PARIS (FULLKOM) | J82: =IFERROR(VLOOKUP(I82,Map!$F$18:$G$56,2,0),"Add in Map") -> 3P | K82: =VLOOKUP(L82,Map!$C$18:$D$29,2,0) -> GLT | L82: Television | M82: 1447520.5 | N82: =IF(L82="TOTAL",(M82*0.19),0) -> 0 | O82: =M82*1.19 -> 1722549.4 | P82: =M82/S82 -> 1566.5806 | Q82: =IF(L82="TOTAL",(P82*0.19),0) -> 0 | R82: =P82*1.19 -> 1864.2309 | S82: =INDEX(FX!$D$3:$O$19,MATCH(B82,FX!$B$3:$B$32,0),MATCH(D82,FX!$D$2:$O$2,0)) -> 924 | T82: Logistic Cost | U82: Provision (Based on External Report) | V82: Invoice | W82: =VLOOKUP(I82,Map!$F$18:$H$51,3,0) -> Variable | X82: Pending | Y82: =VLOOKUP(L82,Map!$C$18:$D$29,2,0) -> GLT | AA82: =IF(Y82="TOTAL",(Z82*0.19),0) -> 0 | AB82: =Z82*1.19 -> 0 | AC82: =Z82/S82 -> 0 | AD82: =IF(Y82="TOTAL",(AC82*0.19),0) -> 0 | AE82: =AC82*1.19 -> 0
B83: 2026 | C83: 2026 APR | D83: JUL | E83: JUL (Provision) | F83: Pending | I83: PARIS (FULLKOM) | J83: =IFERROR(VLOOKUP(I83,Map!$F$18:$G$56,2,0),"Add in Map") -> 3P | K83: =VLOOKUP(L83,Map!$C$18:$D$29,2,0) -> PNT | L83: Audio | M83: 247137.64 | N83: =IF(L83="TOTAL",(M83*0.19),0) -> 0 | O83: =M83*1.19 -> 294093.8 | P83: =M83/S83 -> 267.46498 | Q83: =IF(L83="TOTAL",(P83*0.19),0) -> 0 | R83: =P83*1.19 -> 318.28333 | S83: =INDEX(FX!$D$3:$O$19,MATCH(B83,FX!$B$3:$B$32,0),MATCH(D83,FX!$D$2:$O$2,0)) -> 924 | T83: Logistic Cost | U83: Provision (Based on External Report) | V83: Invoice | W83: =VLOOKUP(I83,Map!$F$18:$H$51,3,0) -> Variable | X83: Pending | Y83: =VLOOKUP(L83,Map!$C$18:$D$29,2,0) -> PNT | AA83: =IF(Y83="TOTAL",(Z83*0.19),0) -> 0 | AB83: =Z83*1.19 -> 0 | AC83: =Z83/S83 -> 0 | AD83: =IF(Y83="TOTAL",(AC83*0.19),0) -> 0 | AE83: =AC83*1.19 -> 0
B84: 2026 | C84: 2026 APR | D84: JUL | E84: JUL (Provision) | F84: Pending | I84: PARIS (FULLKOM) | J84: =IFERROR(VLOOKUP(I84,Map!$F$18:$G$56,2,0),"Add in Map") -> 3P | K84: =VLOOKUP(L84,Map!$C$18:$D$29,2,0) -> GTT | L84: Monitor | M84: 141221.51 | N84: =IF(L84="TOTAL",(M84*0.19),0) -> 0 | O84: =M84*1.19 -> 168053.6 | P84: =M84/S84 -> 152.83713 | Q84: =IF(L84="TOTAL",(P84*0.19),0) -> 0 | R84: =P84*1.19 -> 181.87619 | S84: =INDEX(FX!$D$3:$O$19,MATCH(B84,FX!$B$3:$B$32,0),MATCH(D84,FX!$D$2:$O$2,0)) -> 924 | T84: Logistic Cost | U84: Provision (Based on External Report) | V84: Invoice | W84: =VLOOKUP(I84,Map!$F$18:$H$51,3,0) -> Variable | X84: Pending | Y84: =VLOOKUP(L84,Map!$C$18:$D$29,2,0) -> GTT | AA84: =IF(Y84="TOTAL",(Z84*0.19),0) -> 0 | AB84: =Z84*1.19 -> 0 | AC84: =Z84/S84 -> 0 | AD84: =IF(Y84="TOTAL",(AC84*0.19),0) -> 0 | AE84: =AC84*1.19 -> 0
B85: 2026 | C85: 2026 APR | D85: JUL | E85: JUL (Provision) | F85: Pending | I85: PARIS (FULLKOM) | J85: =IFERROR(VLOOKUP(I85,Map!$F$18:$G$56,2,0),"Add in Map") -> 3P | K85: =VLOOKUP(L85,Map!$C$18:$D$29,2,0) -> DGT | L85: RAC | M85: 105916.13 | N85: =IF(L85="TOTAL",(M85*0.19),0) -> 0 | O85: =M85*1.19 -> 126040.2 | P85: =M85/S85 -> 114.62785 | Q85: =IF(L85="TOTAL",(P85*0.19),0) -> 0 | R85: =P85*1.19 -> 136.40714 | S85: =INDEX(FX!$D$3:$O$19,MATCH(B85,FX!$B$3:$B$32,0),MATCH(D85,FX!$D$2:$O$2,0)) -> 924 | T85: Logistic Cost | U85: Provision (Based on External Report) | V85: Invoice | W85: =VLOOKUP(I85,Map!$F$18:$H$51,3,0) -> Variable | X85: Pending | Y85: =VLOOKUP(L85,Map!$C$18:$D$29,2,0) -> DGT | AA85: =IF(Y85="TOTAL",(Z85*0.19),0) -> 0 | AB85: =Z85*1.19 -> 0 | AC85: =Z85/S85 -> 0 | AD85: =IF(Y85="TOTAL",(AC85*0.19),0) -> 0 | AE85: =AC85*1.19 -> 0
B86: 2026 | C86: 2026 APR | D86: JUL | E86: JUL (Provision) | F86: Pending | I86: PARIS (FULLKOM) | J86: =IFERROR(VLOOKUP(I86,Map!$F$18:$G$56,2,0),"Add in Map") -> 3P | K86: =VLOOKUP(L86,Map!$C$18:$D$29,2,0) -> DLT | L86: Air Cleaner | M86: 35305.378 | N86: =IF(L86="TOTAL",(M86*0.19),0) -> 0 | O86: =M86*1.19 -> 42013.399 | P86: =M86/S86 -> 38.209283 | Q86: =IF(L86="TOTAL",(P86*0.19),0) -> 0 | R86: =P86*1.19 -> 45.469047 | S86: =INDEX(FX!$D$3:$O$19,MATCH(B86,FX!$B$3:$B$32,0),MATCH(D86,FX!$D$2:$O$2,0)) -> 924 | T86: Logistic Cost | U86: Provision (Based on External Report) | V86: Invoice | W86: =VLOOKUP(I86,Map!$F$18:$H$51,3,0) -> Variable | X86: Pending | Y86: =VLOOKUP(L86,Map!$C$18:$D$29,2,0) -> DLT | AA86: =IF(Y86="TOTAL",(Z86*0.19),0) -> 0 | AB86: =Z86*1.19 -> 0 | AC86: =Z86/S86 -> 0 | AD86: =IF(Y86="TOTAL",(AC86*0.19),0) -> 0 | AE86: =AC86*1.19 -> 0
B87: 2026 | C87: 2026 APR | D87: JUL | E87: JUL (Provision) | F87: Pending | I87: PARIS (FULLKOM) | J87: =IFERROR(VLOOKUP(I87,Map!$F$18:$G$56,2,0),"Add in Map") -> 3P | K87: =VLOOKUP(L87,Map!$C$18:$D$29,2,0) -> DMT | L87: SAC | M87: 0 | N87: =IF(L87="TOTAL",(M87*0.19),0) -> 0 | O87: =M87*1.19 -> 0 | P87: =M87/S87 -> 0 | Q87: =IF(L87="TOTAL",(P87*0.19),0) -> 0 | R87: =P87*1.19 -> 0 | S87: =INDEX(FX!$D$3:$O$19,MATCH(B87,FX!$B$3:$B$32,0),MATCH(D87,FX!$D$2:$O$2,0)) -> 924 | T87: Logistic Cost | U87: Provision (Based on External Report) | V87: Invoice | W87: =VLOOKUP(I87,Map!$F$18:$H$51,3,0) -> Variable | X87: Pending | Y87: =VLOOKUP(L87,Map!$C$18:$D$29,2,0) -> DMT | AA87: =IF(Y87="TOTAL",(Z87*0.19),0) -> 0 | AB87: =Z87*1.19 -> 0 | AC87: =Z87/S87 -> 0 | AD87: =IF(Y87="TOTAL",(AC87*0.19),0) -> 0 | AE87: =AC87*1.19 -> 0
B88: 2026 | C88: 2026 APR | D88: JUL | E88: JUL (Provision) | F88: Pending | I88: PARIS (FULLKOM) | J88: =IFERROR(VLOOKUP(I88,Map!$F$18:$G$56,2,0),"Add in Map") -> 3P | K88: =VLOOKUP(L88,Map!$C$18:$D$29,2,0) -> TOTAL | L88: TOTAL | M88: =SUM(M77:M87) -> 11403637 | N88: =IF(L88="TOTAL",(M88*0.19),0) -> 2166691 | O88: =M88*1.19 -> 13570328 | P88: =M88/S88 -> 12341.598 | Q88: =IF(L88="TOTAL",(P88*0.19),0) -> 2344.9037 | R88: =P88*1.19 -> 14686.502 | S88: =INDEX(FX!$D$3:$O$19,MATCH(B88,FX!$B$3:$B$32,0),MATCH(D88,FX!$D$2:$O$2,0)) -> 924 | T88: Logistic Cost | U88: Provision (Based on External Report) | V88: Invoice | W88: =VLOOKUP(I88,Map!$F$18:$H$51,3,0) -> Variable | X88: Pending | Y88: =VLOOKUP(L88,Map!$C$18:$D$29,2,0) -> TOTAL | AA88: =IF(Y88="TOTAL",(Z88*0.19),0) -> 0 | AB88: =Z88*1.19 -> 0 | AC88: =Z88/S88 -> 0 | AD88: =IF(Y88="TOTAL",(AC88*0.19),0) -> 0 | AE88: =AC88*1.19 -> 0
B89: 2026 | C89: NOV-DIC 2025 / JAN-FEB 2026 | D89: JUN | E89: JUL (Provision) | F89: JUL | G89: 46209 | H89: 3825 | I89: PARIS (FULLKOM) | J89: =IFERROR(VLOOKUP(I89,Map!$F$18:$G$56,2,0),"Add in Map") -> 3P | K89: =VLOOKUP(L89,Map!$C$18:$D$29,2,0) -> CNT | L89: Refrigeration | M89: 4386097.2 | N89: =IF(L89="TOTAL",(M89*0.19),0) -> 0 | O89: =M89*1.19 -> 5219455.6 | P89: =M89/S89 -> 4752.0012 | Q89: =IF(L89="TOTAL",(P89*0.19),0) -> 0 | R89: =P89*1.19 -> 5654.8815 | S89: =INDEX(FX!$D$3:$O$19,MATCH(B89,FX!$B$3:$B$32,0),MATCH(D89,FX!$D$2:$O$2,0)) -> 923 | T89: Logistic Cost | U89: Provision (Based on External Report) | V89: Invoice | W89: =VLOOKUP(I89,Map!$F$18:$H$51,3,0) -> Variable | X89: AP Completed | Y89: =VLOOKUP(L89,Map!$C$18:$D$29,2,0) -> CNT | AA89: =IF(Y89="TOTAL",(Z89*0.19),0) -> 0 | AB89: =Z89*1.19 -> 0 | AC89: =Z89/S89 -> 0 | AD89: =IF(Y89="TOTAL",(AC89*0.19),0) -> 0 | AE89: =AC89*1.19 -> 0
B90: 2026 | C90: NOV-DIC 2025 / JAN-FEB 2026 | D90: JUN | E90: JUL (Provision) | F90: JUL | G90: 46209 | H90: 3825 | I90: PARIS (FULLKOM) | J90: =IFERROR(VLOOKUP(I90,Map!$F$18:$G$56,2,0),"Add in Map") -> 3P | K90: =VLOOKUP(L90,Map!$C$18:$D$29,2,0) -> CVT | L90: Cooking | M90: 106612.13 | N90: =IF(L90="TOTAL",(M90*0.19),0) -> 0 | O90: =M90*1.19 -> 126868.43 | P90: =M90/S90 -> 115.5061 | Q90: =IF(L90="TOTAL",(P90*0.19),0) -> 0 | R90: =P90*1.19 -> 137.45225 | S90: =INDEX(FX!$D$3:$O$19,MATCH(B90,FX!$B$3:$B$32,0),MATCH(D90,FX!$D$2:$O$2,0)) -> 923 | T90: Logistic Cost | U90: Provision (Based on External Report) | V90: Invoice | W90: =VLOOKUP(I90,Map!$F$18:$H$51,3,0) -> Variable | X90: AP Completed | Y90: =VLOOKUP(L90,Map!$C$18:$D$29,2,0) -> CVT | AA90: =IF(Y90="TOTAL",(Z90*0.19),0) -> 0 | AB90: =Z90*1.19 -> 0 | AC90: =Z90/S90 -> 0 | AD90: =IF(Y90="TOTAL",(AC90*0.19),0) -> 0 | AE90: =AC90*1.19 -> 0
B91: 2026 | C91: NOV-DIC 2025 / JAN-FEB 2026 | D91: JUN | E91: JUL (Provision) | F91: JUL | G91: 46209 | H91: 3825 | I91: PARIS (FULLKOM) | J91: =IFERROR(VLOOKUP(I91,Map!$F$18:$G$56,2,0),"Add in Map") -> 3P | K91: =VLOOKUP(L91,Map!$C$18:$D$29,2,0) -> CDT | L91: Dishwasher | M91: 109759.66 | N91: =IF(L91="TOTAL",(M91*0.19),0) -> 0 | O91: =M91*1.19 -> 130613.99 | P91: =M91/S91 -> 118.91621 | Q91: =IF(L91="TOTAL",(P91*0.19),0) -> 0 | R91: =P91*1.19 -> 141.51029 | S91: =INDEX(FX!$D$3:$O$19,MATCH(B91,FX!$B$3:$B$32,0),MATCH(D91,FX!$D$2:$O$2,0)) -> 923 | T91: Logistic Cost | U91: Provision (Based on External Report) | V91: Invoice | W91: =VLOOKUP(I91,Map!$F$18:$H$51,3,0) -> Variable | X91: AP Completed | Y91: =VLOOKUP(L91,Map!$C$18:$D$29,2,0) -> CDT | AA91: =IF(Y91="TOTAL",(Z91*0.19),0) -> 0 | AB91: =Z91*1.19 -> 0 | AC91: =Z91/S91 -> 0 | AD91: =IF(Y91="TOTAL",(AC91*0.19),0) -> 0 | AE91: =AC91*1.19 -> 0
B92: 2026 | C92: NOV-DIC 2025 / JAN-FEB 2026 | D92: JUN | E92: JUL (Provision) | F92: JUL | G92: 46209 | H92: 3825 | I92: PARIS (FULLKOM) | J92: =IFERROR(VLOOKUP(I92,Map!$F$18:$G$56,2,0),"Add in Map") -> 3P | K92: =VLOOKUP(L92,Map!$C$18:$D$29,2,0) -> DFT | L92: WM | M92: 9147577.4 | N92: =IF(L92="TOTAL",(M92*0.19),0) -> 0 | O92: =M92*1.19 -> 10885617 | P92: =M92/S92 -> 9910.7014 | Q92: =IF(L92="TOTAL",(P92*0.19),0) -> 0 | R92: =P92*1.19 -> 11793.735 | S92: =INDEX(FX!$D$3:$O$19,MATCH(B92,FX!$B$3:$B$32,0),MATCH(D92,FX!$D$2:$O$2,0)) -> 923 | T92: Logistic Cost | U92: Provision (Based on External Report) | V92: Invoice | W92: =VLOOKUP(I92,Map!$F$18:$H$51,3,0) -> Variable | X92: AP Completed | Y92: =VLOOKUP(L92,Map!$C$18:$D$29,2,0) -> DFT | AA92: =IF(Y92="TOTAL",(Z92*0.19),0) -> 0 | AB92: =Z92*1.19 -> 0 | AC92: =Z92/S92 -> 0 | AD92: =IF(Y92="TOTAL",(AC92*0.19),0) -> 0 | AE92: =AC92*1.19 -> 0
B93: 2026 | C93: NOV-DIC 2025 / JAN-FEB 2026 | D93: JUN | E93: JUL (Provision) | F93: JUL | G93: 46209 | H93: 3825 | I93: PARIS (FULLKOM) | J93: =IFERROR(VLOOKUP(I93,Map!$F$18:$G$56,2,0),"Add in Map") -> 3P | K93: =VLOOKUP(L93,Map!$C$18:$D$29,2,0) -> DVT | L93: VCC | M93: 0 | N93: =IF(L93="TOTAL",(M93*0.19),0) -> 0 | O93: =M93*1.19 -> 0 | P93: =M93/S93 -> 0 | Q93: =IF(L93="TOTAL",(P93*0.19),0) -> 0 | R93: =P93*1.19 -> 0 | S93: =INDEX(FX!$D$3:$O$19,MATCH(B93,FX!$B$3:$B$32,0),MATCH(D93,FX!$D$2:$O$2,0)) -> 923 | T93: Logistic Cost | U93: Provision (Based on External Report) | V93: Invoice | W93: =VLOOKUP(I93,Map!$F$18:$H$51,3,0) -> Variable | X93: AP Completed | Y93: =VLOOKUP(L93,Map!$C$18:$D$29,2,0) -> DVT | AA93: =IF(Y93="TOTAL",(Z93*0.19),0) -> 0 | AB93: =Z93*1.19 -> 0 | AC93: =Z93/S93 -> 0 | AD93: =IF(Y93="TOTAL",(AC93*0.19),0) -> 0 | AE93: =AC93*1.19 -> 0
B94: 2026 | C94: NOV-DIC 2025 / JAN-FEB 2026 | D94: JUN | E94: JUL (Provision) | F94: JUL | G94: 46209 | H94: 3825 | I94: PARIS (FULLKOM) | J94: =IFERROR(VLOOKUP(I94,Map!$F$18:$G$56,2,0),"Add in Map") -> 3P | K94: =VLOOKUP(L94,Map!$C$18:$D$29,2,0) -> GLT | L94: Television | M94: 5944270.3 | N94: =IF(L94="TOTAL",(M94*0.19),0) -> 0 | O94: =M94*1.19 -> 7073681.6 | P94: =M94/S94 -> 6440.1628 | Q94: =IF(L94="TOTAL",(P94*0.19),0) -> 0 | R94: =P94*1.19 -> 7663.7938 | S94: =INDEX(FX!$D$3:$O$19,MATCH(B94,FX!$B$3:$B$32,0),MATCH(D94,FX!$D$2:$O$2,0)) -> 923 | T94: Logistic Cost | U94: Provision (Based on External Report) | V94: Invoice | W94: =VLOOKUP(I94,Map!$F$18:$H$51,3,0) -> Variable | X94: AP Completed | Y94: =VLOOKUP(L94,Map!$C$18:$D$29,2,0) -> GLT | AA94: =IF(Y94="TOTAL",(Z94*0.19),0) -> 0 | AB94: =Z94*1.19 -> 0 | AC94: =Z94/S94 -> 0 | AD94: =IF(Y94="TOTAL",(AC94*0.19),0) -> 0 | AE94: =AC94*1.19 -> 0
B95: 2026 | C95: NOV-DIC 2025 / JAN-FEB 2026 | D95: JUN | E95: JUL (Provision) | F95: JUL | G95: 46209 | H95: 3825 | I95: PARIS (FULLKOM) | J95: =IFERROR(VLOOKUP(I95,Map!$F$18:$G$56,2,0),"Add in Map") -> 3P | K95: =VLOOKUP(L95,Map!$C$18:$D$29,2,0) -> PNT | L95: Audio | M95: 644985.29 | N95: =IF(L95="TOTAL",(M95*0.19),0) -> 0 | O95: =M95*1.19 -> 767532.49 | P95: =M95/S95 -> 698.79229 | Q95: =IF(L95="TOTAL",(P95*0.19),0) -> 0 | R95: =P95*1.19 -> 831.56283 | S95: =INDEX(FX!$D$3:$O$19,MATCH(B95,FX!$B$3:$B$32,0),MATCH(D95,FX!$D$2:$O$2,0)) -> 923 | T95: Logistic Cost | U95: Provision (Based on External Report) | V95: Invoice | W95: =VLOOKUP(I95,Map!$F$18:$H$51,3,0) -> Variable | X95: AP Completed | Y95: =VLOOKUP(L95,Map!$C$18:$D$29,2,0) -> PNT | AA95: =IF(Y95="TOTAL",(Z95*0.19),0) -> 0 | AB95: =Z95*1.19 -> 0 | AC95: =Z95/S95 -> 0 | AD95: =IF(Y95="TOTAL",(AC95*0.19),0) -> 0 | AE95: =AC95*1.19 -> 0
B96: 2026 | C96: NOV-DIC 2025 / JAN-FEB 2026 | D96: JUN | E96: JUL (Provision) | F96: JUL | G96: 46209 | H96: 3825 | I96: PARIS (FULLKOM) | J96: =IFERROR(VLOOKUP(I96,Map!$F$18:$G$56,2,0),"Add in Map") -> 3P | K96: =VLOOKUP(L96,Map!$C$18:$D$29,2,0) -> GTT | L96: Monitor | M96: 395194.55 | N96: =IF(L96="TOTAL",(M96*0.19),0) -> 0 | O96: =M96*1.19 -> 470281.52 | P96: =M96/S96 -> 428.16311 | Q96: =IF(L96="TOTAL",(P96*0.19),0) -> 0 | R96: =P96*1.19 -> 509.51411 | S96: =INDEX(FX!$D$3:$O$19,MATCH(B96,FX!$B$3:$B$32,0),MATCH(D96,FX!$D$2:$O$2,0)) -> 923 | T96: Logistic Cost | U96: Provision (Based on External Report) | V96: Invoice | W96: =VLOOKUP(I96,Map!$F$18:$H$51,3,0) -> Variable | X96: AP Completed | Y96: =VLOOKUP(L96,Map!$C$18:$D$29,2,0) -> GTT | AA96: =IF(Y96="TOTAL",(Z96*0.19),0) -> 0 | AB96: =Z96*1.19 -> 0 | AC96: =Z96/S96 -> 0 | AD96: =IF(Y96="TOTAL",(AC96*0.19),0) -> 0 | AE96: =AC96*1.19 -> 0
B97: 2026 | C97: NOV-DIC 2025 / JAN-FEB 2026 | D97: JUN | E97: JUL (Provision) | F97: JUL | G97: 46209 | H97: 3825 | I97: PARIS (FULLKOM) | J97: =IFERROR(VLOOKUP(I97,Map!$F$18:$G$56,2,0),"Add in Map") -> 3P | K97: =VLOOKUP(L97,Map!$C$18:$D$29,2,0) -> DGT | L97: RAC | M97: 352083.62 | N97: =IF(L97="TOTAL",(M97*0.19),0) -> 0 | O97: =M97*1.19 -> 418979.51 | P97: =M97/S97 -> 381.45571 | Q97: =IF(L97="TOTAL",(P97*0.19),0) -> 0 | R97: =P97*1.19 -> 453.93229 | S97: =INDEX(FX!$D$3:$O$19,MATCH(B97,FX!$B$3:$B$32,0),MATCH(D97,FX!$D$2:$O$2,0)) -> 923 | T97: Logistic Cost | U97: Provision (Based on External Report) | V97: Invoice | W97: =VLOOKUP(I97,Map!$F$18:$H$51,3,0) -> Variable | X97: AP Completed | Y97: =VLOOKUP(L97,Map!$C$18:$D$29,2,0) -> DGT | AA97: =IF(Y97="TOTAL",(Z97*0.19),0) -> 0 | AB97: =Z97*1.19 -> 0 | AC97: =Z97/S97 -> 0 | AD97: =IF(Y97="TOTAL",(AC97*0.19),0) -> 0 | AE97: =AC97*1.19 -> 0
B98: 2026 | C98: NOV-DIC 2025 / JAN-FEB 2026 | D98: JUN | E98: JUL (Provision) | F98: JUL | G98: 46209 | H98: 3825 | I98: PARIS (FULLKOM) | J98: =IFERROR(VLOOKUP(I98,Map!$F$18:$G$56,2,0),"Add in Map") -> 3P | K98: =VLOOKUP(L98,Map!$C$18:$D$29,2,0) -> DLT | L98: Air Cleaner | M98: 79535.909 | N98: =IF(L98="TOTAL",(M98*0.19),0) -> 0 | O98: =M98*1.19 -> 94647.731 | P98: =M98/S98 -> 86.171082 | Q98: =IF(L98="TOTAL",(P98*0.19),0) -> 0 | R98: =P98*1.19 -> 102.54359 | S98: =INDEX(FX!$D$3:$O$19,MATCH(B98,FX!$B$3:$B$32,0),MATCH(D98,FX!$D$2:$O$2,0)) -> 923 | T98: Logistic Cost | U98: Provision (Based on External Report) | V98: Invoice | W98: =VLOOKUP(I98,Map!$F$18:$H$51,3,0) -> Variable | X98: AP Completed | Y98: =VLOOKUP(L98,Map!$C$18:$D$29,2,0) -> DLT | AA98: =IF(Y98="TOTAL",(Z98*0.19),0) -> 0 | AB98: =Z98*1.19 -> 0 | AC98: =Z98/S98 -> 0 | AD98: =IF(Y98="TOTAL",(AC98*0.19),0) -> 0 | AE98: =AC98*1.19 -> 0
B99: 2026 | C99: NOV-DIC 2025 / JAN-FEB 2026 | D99: JUN | E99: JUL (Provision) | F99: JUL | G99: 46209 | H99: 3825 | I99: PARIS (FULLKOM) | J99: =IFERROR(VLOOKUP(I99,Map!$F$18:$G$56,2,0),"Add in Map") -> 3P | K99: =VLOOKUP(L99,Map!$C$18:$D$29,2,0) -> DMT | L99: SAC | M99: 0 | N99: =IF(L99="TOTAL",(M99*0.19),0) -> 0 | O99: =M99*1.19 -> 0 | P99: =M99/S99 -> 0 | Q99: =IF(L99="TOTAL",(P99*0.19),0) -> 0 | R99: =P99*1.19 -> 0 | S99: =INDEX(FX!$D$3:$O$19,MATCH(B99,FX!$B$3:$B$32,0),MATCH(D99,FX!$D$2:$O$2,0)) -> 923 | T99: Logistic Cost | U99: Provision (Based on External Report) | V99: Invoice | W99: =VLOOKUP(I99,Map!$F$18:$H$51,3,0) -> Variable | X99: AP Completed | Y99: =VLOOKUP(L99,Map!$C$18:$D$29,2,0) -> DMT | AA99: =IF(Y99="TOTAL",(Z99*0.19),0) -> 0 | AB99: =Z99*1.19 -> 0 | AC99: =Z99/S99 -> 0 | AD99: =IF(Y99="TOTAL",(AC99*0.19),0) -> 0 | AE99: =AC99*1.19 -> 0
B100: 2026 | C100: NOV-DIC 2025 / JAN-FEB 2026 | D100: JUN | E100: JUL (Provision) | F100: JUL | G100: 46209 | H100: 3825 | I100: PARIS (FULLKOM) | J100: =IFERROR(VLOOKUP(I100,Map!$F$18:$G$56,2,0),"Add in Map") -> 3P | K100: =VLOOKUP(L100,Map!$C$18:$D$29,2,0) -> TOTAL | L100: TOTAL | M100: =SUM(M89:M99) -> 21166116 | N100: =IF(L100="TOTAL",(M100*0.19),0) -> 4021562 | O100: =M100*1.19 -> 25187678 | P100: =M100/S100 -> 22931.87 | Q100: =IF(L100="TOTAL",(P100*0.19),0) -> 4357.0553 | R100: =P100*1.19 -> 27288.925 | S100: =INDEX(FX!$D$3:$O$19,MATCH(B100,FX!$B$3:$B$32,0),MATCH(D100,FX!$D$2:$O$2,0)) -> 923 | T100: Logistic Cost | U100: Provision (Based on External Report) | V100: Invoice | W100: =VLOOKUP(I100,Map!$F$18:$H$51,3,0) -> Variable | X100: AP Completed | Y100: =VLOOKUP(L100,Map!$C$18:$D$29,2,0) -> TOTAL | AA100: =IF(Y100="TOTAL",(Z100*0.19),0) -> 0 | AB100: =Z100*1.19 -> 0 | AC100: =Z100/S100 -> 0 | AD100: =IF(Y100="TOTAL",(AC100*0.19),0) -> 0 | AE100: =AC100*1.19 -> 0
B101: 2026 | C101: NOV-DIC 2025 / JAN-FEB 2026 | D101: JUN | E101: JUL (Provision) | F101: JUL | G101: 46209 | H101: 3826 | I101: PARIS (FULLKOM) | J101: =IFERROR(VLOOKUP(I101,Map!$F$18:$G$56,2,0),"Add in Map") -> 3P | K101: =VLOOKUP(L101,Map!$C$18:$D$29,2,0) -> CNT | L101: Refrigeration | M101: 2930386.9 | N101: =IF(L101="TOTAL",(M101*0.19),0) -> 0 | O101: =M101*1.19 -> 3487160.4 | P101: =M101/S101 -> 3174.8504 | Q101: =IF(L101="TOTAL",(P101*0.19),0) -> 0 | R101: =P101*1.19 -> 3778.072 | S101: =INDEX(FX!$D$3:$O$19,MATCH(B101,FX!$B$3:$B$32,0),MATCH(D101,FX!$D$2:$O$2,0)) -> 923 | T101: Logistic Cost | U101: Provision (Based on External Report) | V101: Invoice | W101: =VLOOKUP(I101,Map!$F$18:$H$51,3,0) -> Variable | X101: AP Completed | Y101: =VLOOKUP(L101,Map!$C$18:$D$29,2,0) -> CNT | AA101: =IF(Y101="TOTAL",(Z101*0.19),0) -> 0 | AB101: =Z101*1.19 -> 0 | AC101: =Z101/S101 -> 0 | AD101: =IF(Y101="TOTAL",(AC101*0.19),0) -> 0 | AE101: =AC101*1.19 -> 0
B102: 2026 | C102: NOV-DIC 2025 / JAN-FEB 2026 | D102: JUN | E102: JUL (Provision) | F102: JUL | G102: 46209 | H102: 3826 | I102: PARIS (FULLKOM) | J102: =IFERROR(VLOOKUP(I102,Map!$F$18:$G$56,2,0),"Add in Map") -> 3P | K102: =VLOOKUP(L102,Map!$C$18:$D$29,2,0) -> CVT | L102: Cooking | M102: 71228.422 | N102: =IF(L102="TOTAL",(M102*0.19),0) -> 0 | O102: =M102*1.19 -> 84761.823 | P102: =M102/S102 -> 77.170555 | Q102: =IF(L102="TOTAL",(P102*0.19),0) -> 0 | R102: =P102*1.19 -> 91.832961 | S102: =INDEX(FX!$D$3:$O$19,MATCH(B102,FX!$B$3:$B$32,0),MATCH(D102,FX!$D$2:$O$2,0)) -> 923 | T102: Logistic Cost | U102: Provision (Based on External Report) | V102: Invoice | W102: =VLOOKUP(I102,Map!$F$18:$H$51,3,0) -> Variable | X102: AP Completed | Y102: =VLOOKUP(L102,Map!$C$18:$D$29,2,0) -> CVT | AA102: =IF(Y102="TOTAL",(Z102*0.19),0) -> 0 | AB102: =Z102*1.19 -> 0 | AC102: =Z102/S102 -> 0 | AD102: =IF(Y102="TOTAL",(AC102*0.19),0) -> 0 | AE102: =AC102*1.19 -> 0
...

Sheet Sheet1
C4: Accrual F-2048 OMS SOPTEC Fixed Commission 5300K USD, From 2024/ Jul 2026 | D4: 4887714 | E4: Ingresar | G4: Fixed
C5: Accrual F-2063 OMS SOPTEC Fixed Commission 5300K USD, From 2024/ Aug 2026 | D5: 4920625 | E5: Ingresar | G5: Fixed
C6: Accrual F-3934 Vector Licence Fixed Commission 40 UF, From 2025/Aug 2026 | D6: 1633792 | E6: Ingresar | G6: Fixed
C7: Accrual - Commission 3P PARIS (Fullkom), 10.9% (8.0%+2.9%) - 1era Quincena Aug 2026 | D7: 11104183 | E7: Ingresar | F7: RAW
C8: Accrual - Commission 3P PARIS (Fullkom), 10.9% (8.0%+2.9%) - 1era Quincena Jul 2026 | D8: 17265550 | E8: Draft Ok | F8: RAW | G8: Montlhy Raw
C9: Accrual - Commission 3P PARIS (Fullkom), 10.9% (8.0%+2.9%) - 2da Quincena Aug 2026 | D9: 14355291 | E9: Ingresar | F9: RAW
C10: Accrual - Commission 3P PARIS (Fullkom), 10.9% (8.0%+2.9%) - 2da Quincena Jul 2026 | D10: 16791454 | E10: Draft Ok | F10: RAW | G10: Montlhy Raw
C11: Accrual - Commission 3P PARIS (Fullkom), 10.9% (8.0%+2.9%) - Costo Logístico Mar and Apr 2026 | D11: 34222221 | E11: Ingresar | F11: RAW
C12: Accrual - Commission 3P RIPLEY (Fullkom), 10.9% (8.0%+2.9%) - 1era Quincena Aug 2026 | D12: 7249875 | E12: Ingresar | F12: RAW
C13: Accrual - Commission 3P RIPLEY (Fullkom), 10.9% (8.0%+2.9%) - 1era Quincena Jul 2026 | D13: 2735581 | E13: Draft Ok | F13: RAW | G13: Montlhy Raw
C14: Accrual - Commission 3P RIPLEY (Fullkom), 10.9% (8.0%+2.9%) - 2da Quincena Aug 2026 | D14: 4291111 | E14: Ingresar | F14: RAW
C15: Accrual - Commission 3P RIPLEY (Fullkom), 10.9% (8.0%+2.9%) - 2da Quincena Jul 2026 | D15: 6558778 | E15: Draft Ok | F15: RAW | G15: Montlhy Raw
C16: Accrual - Commission 3P WALMART (Fullkom), 7.65% (4.75%+2.9%) - 1era Quincena Aug 2026 | D16: 10173825 | E16: Ingresar | F16: RAW
C17: Accrual - Commission 3P WALMART (Fullkom), 7.65% (4.75%+2.9%) - 1era Quincena Jul 2026 | D17: 9202503 | E17: Draft Ok | F17: RAW | G17: Montlhy Raw
C18: Accrual - Commission 3P WALMART (Fullkom), 7.65% (4.75%+2.9%) - 2da Quincena Aug 2026 | D18: 5460550 | E18: Ingresar | F18: RAW
C19: Accrual - Commission 3P WALMART (Fullkom), 7.65% (4.75%+2.9%) - 2da Quincena Jul 2026 | D19: 9167914 | E19: Draft Ok | F19: RAW | G19: Montlhy Raw
C20: Accrual - Credit memo Commission 3P FALABELLA Direct (Integration May 2026), 10%-13% - Aug 2026 | D20: -82304998 | E20: Ingresar | F20: RAW
C21: Accrual - PG Commission MERCADO PAGO, 1.0%-2.3% - Aug 2026 | D21: 7255544 | E21: Approving | F21: RAW
C22: Accrual - PG Commission MERCADO PAGO, 1.0%-2.3% - Jul 2026 | D22: 5778925 | E22: Approving | F22: RAW
C23: Accrual - PG Commission MERCADO PAGO, 1.0%-2.3% - May 2026 | D23: 5049776 | E23: Approving | F23: RAW
C24: Accrual - PG Commission TRANSBANK, 0.9%-1.4% - Aug 2026 | D24: 7261731 | E24: Ingresar | F24: RAW
C25: Accrual - PG Commission TRANSBANK, 0.9%-1.4% - Jul 2026 | D25: 6122739 | E25: Draft Pending Report | F25: RAW
C26: Accrual -Commission 3P FALABELLA Direct (Integration May 2026), 10%-13% - Aug 2026 | D26: 203330052 | E26: Ingresar | F26: RAW
C27: Accrual - OMS Variable Commission, Orders< 3000=0.89$ USD, >3000=0.84$ USD - Aug 2026 | D27: 1534706 | E27: Ingresar Joseph | G27: Julio?
C28: Accrual F-2049 OMS SOPTEC Licence Fixed Commission 20 UF, From 2025/Jul 2026 | D28: 816461 | E28: Ingresar Joseph | G28: Fixed
C29: Accrual F-2064 OMS SOPTEC Licence Fixed Commission 20 UF, From 2025/ Aug 2026 | D29: 816896 | E29: Ingresar Joseph | G29: Fixed
C30: Accrual OMS Variable Commission, Orders< 3000=0.89$ USD, >3000=0.84$ USD, etc, From 2024/Oct/24 - Jun 2026 | D30: 2378589 | E30: Ingresar Joseph | F30: RAW | G30: Agosto!
C32: Ingresar Notas de Credito

Sheet Master 2_STEPS
B2: → | C2: →
B3: STEPS | C3: 1 | D3: 2 | E3: 3 | F3: 4 | G3: 5 | H3: 6 | I3: 7 | J3: 8 | K3: 9 | L3: 10 | M3: 11 | N3: 12 | O3: 13 | P3: 14 | Q3: 15 | R3: 16 | S3: 17 | T3: 18 | U3: 19 | V3: 20 | W3: 21 | X3: 22 | Y3: 23 | Z3: 24 | AA3: 25 | AB3: 26 | AC3: 27 | AD3: 28 | AE3: 29 | AF3: 30 | AG3: 31 | AH3: 32
K4: ACTION 1 | Q4: ACTION 2 | R4: ACTION 3 | S4: ACTION 4 | V4: ACTION 5 | W4: ACTION 6 | X4: ACTION 7 | Y4: ACTION 8 | Z4: ACTION 9 | AA4: ACTION 10 | AB4: ACTION 11 | AC4: ACTION 12 | AF4: ACTION 13 | AG4: ACTION 14 | AH4: ACTION 15
C5: Payee | D5: Doc No | E5: Doc Type | F5: System Module | G5: Invoice Type | H5: Invoice No | I5: Date | J5: Payee Code | K5: Total Amount in Invoice Detail | L5: Description (F/CN-123 + title + MMYY) | M5: Expense | N5: TAX | O5: Credit-Account | P5: Debit-Department | Q5: Manual BU Distribuition or from Provision | R5: Button of "Add" in Debit-Line_Type | S5: TAX_CODE column in the VAT Line (Last line) | T5: VAT Tax Code | U5: Debit-Account | V5: Debit - Amount Column | W5: Product Column (List) | X5: Product Column (Field) | Y5: Description Column | Z5: Icon in DFF column | AA5: DFF: ISSUE_DATE | AB5: DFF: SUPPLY_PRICE | AC5: DFF: ORIGINAL_TAX_AMOUNT | AD5: VAT DFF - Supplier | AE5: VAT DFF - TAX Rate Code | AF5: SAVE | AG5: DFF: TAX_RATE_CODE | AH5: SUBMIT
C6: FALABELLA (DIRECT) | D6: 33 | E6: Invoice | F6: Complex voucher | G6: Vendor Invoice (CHL) | H6: Find in sheet "Master 1" | I6: Select in GEVS Calendar (from sheet "Master 1" the "Invoice Date" column). Find in sheet "Master 1" | J6: =VLOOKUP(C6,Map!$F$16:$J$35,5,0) -> CL004831 | L6: Commission 3P FALABELLA Direct (Integration May 2026), 10%-13% - | O6: 21117701 | P6: =VLOOKUP(C6,Map!$F$18:$I$30,4,0) -> 20168 | Q6: Distribute manually Net Amt by BU (Use sheet "Sales Portion" to divide and sheet "ROUND" to remove decimals) | R6: Add Debit Lines by BU + 1 Line of VAT | S6: Select VAT Line Type: VAT | T6: CLIDD19 | U6: =VLOOKUP(C6,Map!$F$17:$K$38,6,0) -> 51357755 | V6: Fill the Net Amt by BU (w/o decimals) + 1 Line of VAT amt (from sheet "ROUND") | W6: Select in Product: DIV/DIV Group (Keep empty in VAT Line) | X6: Fill the GBU (e.i. DIV:CNT), (Keep empty the VAT field) | Y6: Paste the Description in all Debit Lines (Including VAT Description) | Z6: Fill the DFF(pop-up) of only the VAT Debit line | AA6: In DFF pop-up: Select in "Issue_Date" the same date as "Step 7" | AB6: In DFF pop-up: Fill "Supply_Price" with Total Net Amount (w/o spaces or comas) from sheet "ROUND" | AC6: In DFF pop-up: Fill "Original_Tax_Amount" with VAT amt (w/o spaces or comas) from sheet "ROUND" | AD6: =J6 -> CL004831 | AE6: =T6 -> CLIDD19 | AF6: SAVE | AG6: Attach: 1. Invoice, 2. Distribution, 3. Detail | AH6: SUBMIT
C7: FALABELLA (DIRECT) | D7: 61 | E7: Credit Note | F7: Complex voucher | G7: Vendor Invoice (CHL) | H7: Find in sheet "Master 1" | I7: Select in GEVS Calendar (from sheet "Master 1" the "Invoice Date" column). Find in sheet "Master 1" | J7: =VLOOKUP(C7,Map!$F$16:$J$35,5,0) -> CL004831 | L7: Commission 3P FALABELLA Direct (Integration May 2026), 10%-13% - | O7: 21117701 | P7: =VLOOKUP(C7,Map!$F$18:$I$30,4,0) -> 20168 | Q7: Distribute manually Net Amt by BU (Use sheet "ROUND" to remove decimals) ALL in NEGATIVE | R7: Add Debit Lines by BU + 1 Line of VAT ALL in NEGATIVE | S7: Select VAT Line Type: VAT | T7: CLIDD19 | U7: =VLOOKUP(C7,Map!$F$17:$K$38,6,0) -> 51357755 | V7: Fill the Net Amt by BU (w/o decimals) + 1 Line of VAT amt (from sheet "ROUND") ALL in NEGATIVE | W7: Select in Product: DIV/DIV Group (Keep empty in VAT Line) | X7: Fill the GBU (e.i. DIV:CNT), (Keep empty the VAT field) | Y7: Paste the Description in all Debit Lines (Including VAT Description) | Z7: Fill the DFF(pop-up) of only the VAT Debit line | AA7: In DFF pop-up: Select in "Issue_Date" the same date as "Step 7" | AB7: In DFF pop-up: Fill "Supply_Price" with Total Net Amount (w/o spaces or comas) from sheet "ROUND" ALL in NEGATIVE | AC7: In DFF pop-up: Fill "Original_Tax_Amount" with VAT amt (w/o spaces or comas) from sheet "ROUND" ALL in NEGATIVE | AD7: =J7 -> CL004831 | AE7: =T7 -> CLIDD19 | AF7: SAVE | AG7: Attach: 1. Invoice, 2. Distribution, 3. Detail | AH7: SUBMIT
C8: FALABELLA (DIRECT) | E8: Debit Note | F8: Complex voucher | G8: Vendor Invoice (CHL) | H8: Find in sheet "Master 1" | I8: Select in GEVS Calendar (from sheet "Master 1" the "Invoice Date" column). Find in sheet "Master 1" | J8: =VLOOKUP(C8,Map!$F$16:$J$35,5,0) -> CL004831 | L8: Commission 3P FALABELLA Direct (Integration May 2026), 10%-13% - | O8: 21117701 | P8: =VLOOKUP(C8,Map!$F$18:$I$30,4,0) -> 20168 | Q8: Distribute manually Net Amt by BU (Use sheet "ROUND" to remove decimals) | R8: Add Debit Lines by BU + 1 Line of VAT | S8: Select VAT Line Type: VAT | T8: CLIDD19 | U8: =VLOOKUP(C8,Map!$F$17:$K$38,6,0) -> 51357755 | V8: Fill the Net Amt by BU (w/o decimals) + 1 Line of VAT amt (from sheet "ROUND") | W8: Select in Product: DIV/DIV Group (Keep empty in VAT Line) | X8: Fill the GBU (e.i. DIV:CNT), (Keep empty the VAT field) | Y8: Paste the Description in all Debit Lines (Including VAT Description) | Z8: Fill the DFF(pop-up) of only the VAT Debit line | AA8: In DFF pop-up: Select in "Issue_Date" the same date as "Step 7" | AB8: In DFF pop-up: Fill "Supply_Price" with Total Net Amount (w/o spaces or comas) from sheet "ROUND" | AC8: In DFF pop-up: Fill "Original_Tax_Amount" with VAT amt (w/o spaces or comas) from sheet "ROUND" | AD8: =J8 -> CL004831 | AE8: =T8 -> CLIDD19 | AF8: SAVE | AG8: Attach: 1. Invoice, 2. Distribution, 3. Detail | AH8: SUBMIT
C9: PARIS (FULLKOM) | D9: 33 | E9: Invoice | F9: Complex voucher | G9: Vendor Invoice (CHL) | H9: Find in sheet "Master 1" | I9: Select in GEVS Calendar (from sheet "Master 1" the "Invoice Date" column). Find in sheet "Master 1" | J9: =VLOOKUP(C9,Map!$F$16:$J$35,5,0) -> CL004915 | L9: Commission 3P PARIS (Fullkom), 10.9% (8.0%+2.9%) - | O9: 21117701 | P9: =VLOOKUP(C9,Map!$F$18:$I$30,4,0) -> 20169 | Q9: Distribute manually Net Amt by BU (Use sheet "ROUND" to remove decimals) | R9: Add Debit Lines by BU + 1 Line of VAT | S9: Select VAT Line Type: VAT | T9: CLIDD19 | U9: =VLOOKUP(C9,Map!$F$17:$K$38,6,0) -> 51357755 | V9: Fill the Net Amt by BU (w/o decimals) + 1 Line of VAT amt (from sheet "ROUND") | W9: Select in Product: DIV/DIV Group (Keep empty in VAT Line) | X9: Fill the GBU (e.i. DIV:CNT), (Keep empty the VAT field) | Y9: Paste the Description in all Debit Lines (Including VAT Description) | Z9: Fill the DFF(pop-up) of only the VAT Debit line | AA9: In DFF pop-up: Select in "Issue_Date" the same date as "Step 7" | AB9: In DFF pop-up: Fill "Supply_Price" with Total Net Amount (w/o spaces or comas) from sheet "ROUND" | AC9: In DFF pop-up: Fill "Original_Tax_Amount" with VAT amt (w/o spaces or comas) from sheet "ROUND" | AD9: =J9 -> CL004915 | AE9: =T9 -> CLIDD19 | AF9: SAVE | AG9: Attach: 1. Invoice, 2. Distribution, 3. Detail | AH9: SUBMIT
C10: WALMART (FULLKOM) | D10: 33 | E10: Invoice | F10: Complex voucher | G10: Vendor Invoice (CHL) | H10: Find in sheet "Master 1" | I10: Select in GEVS Calendar (from sheet "Master 1" the "Invoice Date" column). Find in sheet "Master 1" | J10: =VLOOKUP(C10,Map!$F$16:$J$35,5,0) -> CL004915 | L10: Commission 3P WALMART (Fullkom), 7.65% (4.75%+2.9%) - | O10: 21117701 | P10: =VLOOKUP(C10,Map!$F$18:$I$30,4,0) -> 20170 | Q10: Distribute manually Net Amt by BU (Use sheet "ROUND" to remove decimals) | R10: Add Debit Lines by BU + 1 Line of VAT | S10: Select VAT Line Type: VAT | T10: CLIDD19 | U10: =VLOOKUP(C10,Map!$F$17:$K$38,6,0) -> 51357755 | V10: Fill the Net Amt by BU (w/o decimals) + 1 Line of VAT amt (from sheet "ROUND") | W10: Select in Product: DIV/DIV Group (Keep empty in VAT Line) | X10: Fill the GBU (e.i. DIV:CNT), (Keep empty the VAT field) | Y10: Paste the Description in all Debit Lines (Including VAT Description) | Z10: Fill the DFF(pop-up) of only the VAT Debit line | AA10: In DFF pop-up: Select in "Issue_Date" the same date as "Step 7" | AB10: In DFF pop-up: Fill "Supply_Price" with Total Net Amount (w/o spaces or comas) from sheet "ROUND" | AC10: In DFF pop-up: Fill "Original_Tax_Amount" with VAT amt (w/o spaces or comas) from sheet "ROUND" | AD10: =J10 -> CL004915 | AE10: =T10 -> CLIDD19 | AF10: SAVE | AG10: Attach: 1. Invoice, 2. Distribution, 3. Detail | AH10: SUBMIT
C11: RIPLEY (FULLKOM) | D11: 33 | E11: Invoice | F11: Complex voucher | G11: Vendor Invoice (CHL) | H11: Find in sheet "Master 1" | I11: Select in GEVS Calendar (from sheet "Master 1" the "Invoice Date" column). Find in sheet "Master 1" | J11: =VLOOKUP(C11,Map!$F$16:$J$35,5,0) -> CL004915 | L11: Commission 3P RIPLEY (Fullkom), 10.9% (8.0%+2.9%) - | O11: 21117701 | P11: =VLOOKUP(C11,Map!$F$18:$I$30,4,0) -> 20171 | Q11: Distribute manually Net Amt by BU (Use sheet "ROUND" to remove decimals) | R11: Add Debit Lines by BU + 1 Line of VAT | S11: Select VAT Line Type: VAT | T11: CLIDD19 | U11: =VLOOKUP(C11,Map!$F$17:$K$38,6,0) -> 51357755 | V11: Fill the Net Amt by BU (w/o decimals) + 1 Line of VAT amt (from sheet "ROUND") | W11: Select in Product: DIV/DIV Group (Keep empty in VAT Line) | X11: Fill the GBU (e.i. DIV:CNT), (Keep empty the VAT field) | Y11: Paste the Description in all Debit Lines (Including VAT Description) | Z11: Fill the DFF(pop-up) of only the VAT Debit line | AA11: In DFF pop-up: Select in "Issue_Date" the same date as "Step 7" | AB11: In DFF pop-up: Fill "Supply_Price" with Total Net Amount (w/o spaces or comas) from sheet "ROUND" | AC11: In DFF pop-up: Fill "Original_Tax_Amount" with VAT amt (w/o spaces or comas) from sheet "ROUND" | AD11: =J11 -> CL004915 | AE11: =T11 -> CLIDD19 | AF11: SAVE | AG11: Attach: 1. Invoice, 2. Distribution, 3. Detail | AH11: SUBMIT
